  1           0 LOAD_CONST               0 (-1)
              3 LOAD_CONST               1 (None)
              6 IMPORT_NAME              0 (marshal)
              9 STORE_NAME               0 (marshal)
             12 LOAD_CONST               0 (-1)
             15 LOAD_CONST               1 (None)
             18 IMPORT_NAME              1 (zlib)
             21 STORE_NAME               1 (zlib)
             24 LOAD_CONST               0 (-1)
             27 LOAD_CONST               1 (None)
             30 IMPORT_NAME              2 (base64)
             33 STORE_NAME               2 (base64)

  2          36 LOAD_CONST               2 (131)
             39 LOAD_CONST               3 (55)
             42 LOAD_CONST               4 (122)
             45 LOAD_CONST               5 (5)
             48 LOAD_CONST               6 (219)
             51 LOAD_CONST               7 (125)
             54 LOAD_CONST               8 (157)
             57 LOAD_CONST               9 (115)
             60 LOAD_CONST              10 (35)
             63 LOAD_CONST              11 (194)
             66 LOAD_CONST              12 (120)
             69 LOAD_CONST              13 (86)
             72 LOAD_CONST              14 (127)
             75 LOAD_CONST              15 (169)
             78 LOAD_CONST              16 (168)
             81 LOAD_CONST              17 (75)
             84 LOAD_CONST              18 (218)
             87 LOAD_CONST              19 (198)
             90 LOAD_CONST              20 (45)
             93 LOAD_CONST              21 (160)
             96 LOAD_CONST              16 (168)
             99 LOAD_CONST              22 (99)
            102 LOAD_CONST              23 (159)
            105 LOAD_CONST              24 (60)
            108 LOAD_CONST              25 (29)
            111 LOAD_CONST               7 (125)
            114 LOAD_CONST              26 (0)
            117 LOAD_CONST              27 (24)
            120 LOAD_CONST              28 (102)
            123 LOAD_CONST              29 (104)
            126 LOAD_CONST              30 (31)
            129 LOAD_CONST              31 (51)
            132 LOAD_CONST              32 (80)
            135 LOAD_CONST              33 (161)
            138 LOAD_CONST              34 (110)
            141 LOAD_CONST              35 (4)
            144 LOAD_CONST              36 (20)
            147 LOAD_CONST              37 (23)
            150 LOAD_CONST              38 (17)
            153 LOAD_CONST              39 (134)
            156 LOAD_CONST              29 (104)
            159 LOAD_CONST              40 (223)
            162 LOAD_CONST              11 (194)
            165 LOAD_CONST              41 (114)
            168 LOAD_CONST              42 (193)
            171 LOAD_CONST              43 (179)
            174 LOAD_CONST              12 (120)
            177 LOAD_CONST              44 (200)
            180 LOAD_CONST              45 (9)
            183 LOAD_CONST              46 (195)
            186 LOAD_CONST              47 (42)
            189 LOAD_CONST              48 (118)
            192 LOAD_CONST              49 (19)
            195 LOAD_CONST              50 (73)
            198 LOAD_CONST              51 (189)
            201 LOAD_CONST              52 (233)
            204 LOAD_CONST              53 (201)
            207 LOAD_CONST              54 (49)
            210 LOAD_CONST              55 (204)
            213 LOAD_CONST              56 (12)
            216 LOAD_CONST              57 (178)
            219 LOAD_CONST              58 (68)
            222 LOAD_CONST               5 (5)
            225 LOAD_CONST              59 (197)
            228 LOAD_CONST              60 (14)
            231 LOAD_CONST              61 (150)
            234 LOAD_CONST              39 (134)
            237 LOAD_CONST              62 (208)
            240 LOAD_CONST              57 (178)
            243 LOAD_CONST              18 (218)
            246 LOAD_CONST              63 (69)
            249 LOAD_CONST              64 (234)
            252 LOAD_CONST              65 (206)
            255 LOAD_CONST              66 (54)
            258 LOAD_CONST              67 (239)
            261 LOAD_CONST              68 (47)
            264 LOAD_CONST              69 (138)
            267 LOAD_CONST              43 (179)
            270 LOAD_CONST              70 (74)
            273 LOAD_CONST              71 (242)
            276 LOAD_CONST              41 (114)
            279 LOAD_CONST              72 (93)
            282 LOAD_CONST              73 (72)
            285 LOAD_CONST              74 (123)
            288 LOAD_CONST              75 (191)
            291 LOAD_CONST              76 (2)
            294 LOAD_CONST              77 (107)
            297 LOAD_CONST              25 (29)
            300 LOAD_CONST              44 (200)
            303 LOAD_CONST              78 (171)
            306 LOAD_CONST              79 (27)
            309 LOAD_CONST              25 (29)
            312 LOAD_CONST              80 (48)
            315 LOAD_CONST              81 (188)
            318 LOAD_CONST              82 (230)
            321 LOAD_CONST              63 (69)
            324 LOAD_CONST              83 (90)
            327 LOAD_CONST              84 (202)
            330 LOAD_CONST              11 (194)
            333 LOAD_CONST              85 (76)
            336 LOAD_CONST              86 (245)
            339 LOAD_CONST              87 (149)
            342 LOAD_CONST              88 (26)
            345 LOAD_CONST              89 (165)
            348 LOAD_CONST              17 (75)
            351 LOAD_CONST              90 (71)
            354 LOAD_CONST              91 (211)
            357 LOAD_CONST              92 (248)
            360 LOAD_CONST              36 (20)
            363 LOAD_CONST              93 (126)
            366 LOAD_CONST              74 (123)
            369 LOAD_CONST              94 (167)
            372 LOAD_CONST              95 (174)
            375 LOAD_CONST              96 (78)
            378 LOAD_CONST              97 (158)
            381 LOAD_CONST              98 (89)
            384 LOAD_CONST              99 (108)
            387 LOAD_CONST               8 (157)
            390 LOAD_CONST              56 (12)
            393 LOAD_CONST             100 (64)
            396 LOAD_CONST              30 (31)
            399 LOAD_CONST              66 (54)
            402 LOAD_CONST             101 (166)
            405 LOAD_CONST              92 (248)
            408 LOAD_CONST             102 (15)
            411 LOAD_CONST             103 (36)
            414 LOAD_CONST             104 (65)
            417 LOAD_CONST             105 (255)
            420 LOAD_CONST             106 (109)
            423 LOAD_CONST             107 (151)
            426 LOAD_CONST              90 (71)
            429 LOAD_CONST               6 (219)
            432 LOAD_CONST              75 (191)
            435 LOAD_CONST             108 (185)
            438 LOAD_CONST              19 (198)
            441 LOAD_CONST             109 (50)
            444 LOAD_CONST             110 (214)
            447 LOAD_CONST             111 (177)
            450 LOAD_CONST              58 (68)
            453 LOAD_CONST               6 (219)
            456 LOAD_CONST             112 (100)
            459 LOAD_CONST              34 (110)
            462 LOAD_CONST             113 (63)
            465 LOAD_CONST             114 (192)
            468 LOAD_CONST              72 (93)
            471 LOAD_CONST             115 (77)
            474 LOAD_CONST               9 (115)
            477 LOAD_CONST             116 (84)
            480 LOAD_CONST             117 (6)
            483 LOAD_CONST             118 (95)
            486 LOAD_CONST              80 (48)
            489 LOAD_CONST             119 (154)
            492 LOAD_CONST              57 (178)
            495 LOAD_CONST             120 (145)
            498 LOAD_CONST             121 (112)
            501 LOAD_CONST             122 (124)
            504 LOAD_CONST             123 (33)
            507 LOAD_CONST             124 (229)
            510 LOAD_CONST              65 (206)
            513 LOAD_CONST             125 (153)
            516 LOAD_CONST              48 (118)
            519 LOAD_CONST             126 (216)
            522 LOAD_CONST             127 (164)
            525 LOAD_CONST              24 (60)
            528 LOAD_CONST              17 (75)
            531 LOAD_CONST              11 (194)
            534 LOAD_CONST             128 (7)
            537 LOAD_CONST              72 (93)
            540 LOAD_CONST             129 (207)
            543 LOAD_CONST             130 (105)
            546 LOAD_CONST             110 (214)
            549 LOAD_CONST             131 (16)
            552 LOAD_CONST             132 (196)
            555 LOAD_CONST              86 (245)
            558 LOAD_CONST             133 (210)
            561 LOAD_CONST              92 (248)
            564 LOAD_CONST             134 (244)
            567 LOAD_CONST             135 (98)
            570 LOAD_CONST             125 (153)
            573 LOAD_CONST             136 (52)
            576 LOAD_CONST             137 (240)
            579 LOAD_CONST             138 (91)
            582 LOAD_CONST             139 (163)
            585 LOAD_CONST              64 (234)
            588 LOAD_CONST              82 (230)
            591 LOAD_CONST              35 (4)
            594 LOAD_CONST              18 (218)
            597 LOAD_CONST             140 (187)
            600 LOAD_CONST              80 (48)
            603 LOAD_CONST              41 (114)
            606 LOAD_CONST             102 (15)
            609 LOAD_CONST             141 (87)
            612 LOAD_CONST             142 (199)
            615 LOAD_CONST              13 (86)
            618 LOAD_CONST              98 (89)
            621 LOAD_CONST             143 (175)
            624 LOAD_CONST             135 (98)
            627 LOAD_CONST             144 (209)
            630 LOAD_CONST             145 (82)
            633 LOAD_CONST              62 (208)
            636 LOAD_CONST              93 (126)
            639 LOAD_CONST             146 (228)
            642 LOAD_CONST             147 (182)
            645 LOAD_CONST              90 (71)
            648 LOAD_CONST             148 (237)
            651 LOAD_CONST              73 (72)
            654 LOAD_CONST              46 (195)
            657 LOAD_CONST             149 (135)
            660 LOAD_CONST             150 (238)
            663 LOAD_CONST             151 (152)
            666 LOAD_CONST              27 (24)
            669 LOAD_CONST              72 (93)
            672 LOAD_CONST             152 (203)
            675 LOAD_CONST             153 (146)
            678 LOAD_CONST             154 (252)
            681 LOAD_CONST              16 (168)
            684 LOAD_CONST              86 (245)
            687 LOAD_CONST              90 (71)
            690 LOAD_CONST             155 (249)
            693 LOAD_CONST             156 (232)
            696 LOAD_CONST              20 (45)
            699 LOAD_CONST               3 (55)
            702 LOAD_CONST             156 (232)
            705 LOAD_CONST              29 (104)
            708 LOAD_CONST              75 (191)
            711 LOAD_CONST             145 (82)
            714 LOAD_CONST             138 (91)
            717 LOAD_CONST             157 (53)
            720 LOAD_CONST             158 (139)
            723 LOAD_CONST               9 (115)
            726 LOAD_CONST             147 (182)
            729 LOAD_CONST              85 (76)
            732 LOAD_CONST              42 (193)
            735 LOAD_CONST              96 (78)
            738 LOAD_CONST              85 (76)
            741 LOAD_CONST              71 (242)
            744 LOAD_CONST             159 (212)
            747 LOAD_CONST             149 (135)
            750 LOAD_CONST             160 (18)
            753 LOAD_CONST              42 (193)
            756 LOAD_CONST               3 (55)
            759 LOAD_CONST             145 (82)
            762 LOAD_CONST              22 (99)
            765 LOAD_CONST             161 (181)
            768 LOAD_CONST             162 (132)
            771 LOAD_CONST              22 (99)
            774 LOAD_CONST             145 (82)
            777 LOAD_CONST             110 (214)
            780 LOAD_CONST             149 (135)
            783 LOAD_CONST              44 (200)
            786 LOAD_CONST             163 (40)
            789 LOAD_CONST              18 (218)
            792 LOAD_CONST              84 (202)
            795 LOAD_CONST             129 (207)
            798 LOAD_CONST             164 (143)
            801 LOAD_CONST              71 (242)
            804 LOAD_CONST             165 (62)
            807 LOAD_CONST              26 (0)
            810 LOAD_CONST               5 (5)
            813 LOAD_CONST              95 (174)
            816 LOAD_CONST              60 (14)
            819 LOAD_CONST             120 (145)
            822 LOAD_CONST             166 (113)
            825 LOAD_CONST             123 (33)
            828 LOAD_CONST             147 (182)
            831 LOAD_CONST              93 (126)
            834 LOAD_CONST             167 (85)
            837 LOAD_CONST              14 (127)
            840 LOAD_CONST             139 (163)
            843 LOAD_CONST              95 (174)
            846 LOAD_CONST             168 (79)
            849 LOAD_CONST              15 (169)
            852 LOAD_CONST              42 (193)
            855 LOAD_CONST             169 (46)
            858 LOAD_CONST             101 (166)
            861 LOAD_CONST             159 (212)
            864 LOAD_CONST             170 (22)
            867 LOAD_CONST             151 (152)
            870 LOAD_CONST             171 (58)
            873 LOAD_CONST             172 (111)
            876 LOAD_CONST               4 (122)
            879 LOAD_CONST             122 (124)
            882 LOAD_CONST              79 (27)
            885 LOAD_CONST             131 (16)
            888 LOAD_CONST              25 (29)
            891 LOAD_CONST              27 (24)
            894 LOAD_CONST              96 (78)
            897 LOAD_CONST             167 (85)
            900 LOAD_CONST             159 (212)
            903 LOAD_CONST              79 (27)
            906 LOAD_CONST             173 (8)
            909 LOAD_CONST             174 (28)
            912 LOAD_CONST             130 (105)
            915 LOAD_CONST              38 (17)
            918 LOAD_CONST             137 (240)
            921 LOAD_CONST             175 (96)
            924 LOAD_CONST             176 (173)
            927 LOAD_CONST              65 (206)
            930 LOAD_CONST             121 (112)
            933 LOAD_CONST              43 (179)
            936 LOAD_CONST             177 (186)
            939 LOAD_CONST             178 (13)
            942 LOAD_CONST             179 (184)
            945 LOAD_CONST               7 (125)
            948 LOAD_CONST              84 (202)
            951 LOAD_CONST              72 (93)
            954 LOAD_CONST              76 (2)
            957 LOAD_CONST              37 (23)
            960 LOAD_CONST             180 (61)
            963 LOAD_CONST             111 (177)
            966 LOAD_CONST              23 (159)
            969 LOAD_CONST              55 (204)
            972 LOAD_CONST              50 (73)
            975 LOAD_CONST              65 (206)
            978 LOAD_CONST              60 (14)
            981 LOAD_CONST             181 (180)
            984 LOAD_CONST               3 (55)
            987 LOAD_CONST               9 (115)
            990 LOAD_CONST             161 (181)
            993 LOAD_CONST             173 (8)
            996 LOAD_CONST              87 (149)
            999 LOAD_CONST              71 (242)
           1002 LOAD_CONST              91 (211)
           1005 LOAD_CONST             161 (181)
           1008 LOAD_CONST              21 (160)
           1011 LOAD_CONST             157 (53)
           1014 LOAD_CONST             182 (227)
           1017 LOAD_CONST             183 (205)
           1020 LOAD_CONST             184 (59)
           1023 LOAD_CONST             150 (238)
           1026 LOAD_CONST             185 (44)
           1029 LOAD_CONST             186 (142)
           1032 LOAD_CONST             142 (199)
           1035 LOAD_CONST             100 (64)
           1038 LOAD_CONST             187 (243)
           1041 LOAD_CONST             188 (117)
           1044 LOAD_CONST             118 (95)
           1047 LOAD_CONST             168 (79)
           1050 LOAD_CONST              45 (9)
           1053 LOAD_CONST              53 (201)
           1056 LOAD_CONST              60 (14)
           1059 LOAD_CONST             189 (97)
           1062 LOAD_CONST              79 (27)
           1065 LOAD_CONST              55 (204)
           1068 LOAD_CONST             190 (170)
           1071 LOAD_CONST              36 (20)
           1074 LOAD_CONST              77 (107)
           1077 LOAD_CONST             191 (67)
           1080 LOAD_CONST              51 (189)
           1083 LOAD_CONST              23 (159)
           1086 LOAD_CONST             136 (52)
           1089 LOAD_CONST             141 (87)
           1092 LOAD_CONST              51 (189)
           1095 LOAD_CONST              11 (194)
           1098 LOAD_CONST             171 (58)
           1101 LOAD_CONST             192 (241)
           1104 LOAD_CONST              87 (149)
           1107 LOAD_CONST              88 (26)
           1110 LOAD_CONST             127 (164)
           1113 LOAD_CONST             113 (63)
           1116 LOAD_CONST             193 (66)
           1119 LOAD_CONST              89 (165)
           1122 LOAD_CONST             194 (141)
           1125 LOAD_CONST             195 (101)
           1128 LOAD_CONST             102 (15)
           1131 LOAD_CONST             102 (15)
           1134 LOAD_CONST             196 (213)
           1137 LOAD_CONST              95 (174)
           1140 LOAD_CONST             193 (66)
           1143 LOAD_CONST              67 (239)
           1146 LOAD_CONST             163 (40)
           1149 LOAD_CONST              38 (17)
           1152 LOAD_CONST             119 (154)
           1155 LOAD_CONST             178 (13)
           1158 LOAD_CONST             100 (64)
           1161 LOAD_CONST              79 (27)
           1164 LOAD_CONST              70 (74)
           1167 LOAD_CONST             197 (221)
           1170 LOAD_CONST              92 (248)
           1173 LOAD_CONST             122 (124)
           1176 LOAD_CONST              32 (80)
           1179 LOAD_CONST             165 (62)
           1182 LOAD_CONST             198 (246)
           1185 LOAD_CONST             131 (16)
           1188 LOAD_CONST              87 (149)
           1191 LOAD_CONST             193 (66)
           1194 LOAD_CONST               6 (219)
           1197 LOAD_CONST              57 (178)
           1200 LOAD_CONST             147 (182)
           1203 LOAD_CONST             142 (199)
           1206 LOAD_CONST             184 (59)
           1209 LOAD_CONST             127 (164)
           1212 LOAD_CONST              19 (198)
           1215 LOAD_CONST              58 (68)
           1218 LOAD_CONST             199 (222)
           1221 LOAD_CONST             189 (97)
           1224 LOAD_CONST              34 (110)
           1227 LOAD_CONST              24 (60)
           1230 LOAD_CONST              51 (189)
           1233 LOAD_CONST             200 (92)
           1236 LOAD_CONST              96 (78)
           1239 LOAD_CONST              48 (118)
           1242 LOAD_CONST              98 (89)
           1245 LOAD_CONST              48 (118)
           1248 LOAD_CONST              13 (86)
           1251 LOAD_CONST              58 (68)
           1254 LOAD_CONST             119 (154)
           1257 LOAD_CONST             132 (196)
           1260 LOAD_CONST             107 (151)
           1263 LOAD_CONST              48 (118)
           1266 LOAD_CONST              41 (114)
           1269 LOAD_CONST             138 (91)
           1272 LOAD_CONST             201 (226)
           1275 LOAD_CONST             161 (181)
           1278 LOAD_CONST             125 (153)
           1281 LOAD_CONST              35 (4)
           1284 LOAD_CONST             176 (173)
           1287 LOAD_CONST             199 (222)
           1290 LOAD_CONST              70 (74)
           1293 LOAD_CONST             115 (77)
           1296 LOAD_CONST             202 (176)
           1299 LOAD_CONST              48 (118)
           1302 LOAD_CONST             163 (40)
           1305 LOAD_CONST             177 (186)
           1308 LOAD_CONST              79 (27)
           1311 LOAD_CONST             127 (164)
           1314 LOAD_CONST             203 (30)
           1317 LOAD_CONST              11 (194)
           1320 LOAD_CONST             198 (246)
           1323 LOAD_CONST             204 (215)
           1326 LOAD_CONST             192 (241)
           1329 LOAD_CONST             205 (133)
           1332 LOAD_CONST             112 (100)
           1335 LOAD_CONST             182 (227)
           1338 LOAD_CONST             100 (64)
           1341 LOAD_CONST             205 (133)
           1344 LOAD_CONST             206 (43)
           1347 LOAD_CONST              94 (167)
           1350 LOAD_CONST             125 (153)
           1353 LOAD_CONST              82 (230)
           1356 LOAD_CONST              74 (123)
           1359 LOAD_CONST              18 (218)
           1362 LOAD_CONST             152 (203)
           1365 LOAD_CONST             104 (65)
           1368 LOAD_CONST              26 (0)
           1371 LOAD_CONST              41 (114)
           1374 LOAD_CONST             145 (82)
           1377 LOAD_CONST             108 (185)
           1380 LOAD_CONST             167 (85)
           1383 LOAD_CONST             169 (46)
           1386 LOAD_CONST             196 (213)
           1389 LOAD_CONST             175 (96)
           1392 LOAD_CONST             207 (162)
           1395 LOAD_CONST             208 (88)
           1398 LOAD_CONST             207 (162)
           1401 LOAD_CONST             209 (119)
           1404 LOAD_CONST              87 (149)
           1407 LOAD_CONST              46 (195)
           1410 LOAD_CONST              96 (78)
           1413 LOAD_CONST              97 (158)
           1416 LOAD_CONST             168 (79)
           1419 LOAD_CONST              53 (201)
           1422 LOAD_CONST             194 (141)
           1425 LOAD_CONST              87 (149)
           1428 LOAD_CONST              23 (159)
           1431 LOAD_CONST             210 (25)
           1434 LOAD_CONST             211 (83)
           1437 LOAD_CONST             177 (186)
           1440 LOAD_CONST             182 (227)
           1443 LOAD_CONST              69 (138)
           1446 LOAD_CONST             143 (175)
           1449 LOAD_CONST             186 (142)
           1452 LOAD_CONST             191 (67)
           1455 LOAD_CONST              92 (248)
           1458 LOAD_CONST             119 (154)
           1461 LOAD_CONST              13 (86)
           1464 LOAD_CONST               3 (55)
           1467 LOAD_CONST             212 (225)
           1470 LOAD_CONST              77 (107)
           1473 LOAD_CONST              44 (200)
           1476 LOAD_CONST             213 (32)
           1479 LOAD_CONST              98 (89)
           1482 LOAD_CONST             100 (64)
           1485 LOAD_CONST             186 (142)
           1488 LOAD_CONST              41 (114)
           1491 LOAD_CONST             111 (177)
           1494 LOAD_CONST             165 (62)
           1497 LOAD_CONST              84 (202)
           1500 LOAD_CONST             180 (61)
           1503 LOAD_CONST             115 (77)
           1506 LOAD_CONST             192 (241)
           1509 LOAD_CONST             196 (213)
           1512 LOAD_CONST             149 (135)
           1515 LOAD_CONST              36 (20)
           1518 LOAD_CONST              43 (179)
           1521 LOAD_CONST              63 (69)
           1524 LOAD_CONST             214 (38)
           1527 LOAD_CONST             170 (22)
           1530 LOAD_CONST              75 (191)
           1533 LOAD_CONST             155 (249)
           1536 LOAD_CONST             203 (30)
           1539 LOAD_CONST              10 (35)
           1542 LOAD_CONST             207 (162)
           1545 LOAD_CONST             215 (247)
           1548 LOAD_CONST             183 (205)
           1551 LOAD_CONST             169 (46)
           1554 LOAD_CONST              95 (174)
           1557 LOAD_CONST             140 (187)
           1560 LOAD_CONST             129 (207)
           1563 LOAD_CONST             137 (240)
           1566 LOAD_CONST             216 (140)
           1569 LOAD_CONST             217 (57)
           1572 LOAD_CONST             188 (117)
           1575 LOAD_CONST              26 (0)
           1578 LOAD_CONST             218 (172)
           1581 LOAD_CONST             219 (11)
           1584 LOAD_CONST              64 (234)
           1587 LOAD_CONST             220 (3)
           1590 LOAD_CONST              32 (80)
           1593 LOAD_CONST              46 (195)
           1596 LOAD_CONST              48 (118)
           1599 LOAD_CONST             221 (34)
           1602 LOAD_CONST              60 (14)
           1605 LOAD_CONST             126 (216)
           1608 LOAD_CONST              16 (168)
           1611 LOAD_CONST              50 (73)
           1614 LOAD_CONST             197 (221)
           1617 LOAD_CONST             181 (180)
           1620 LOAD_CONST             200 (92)
           1623 LOAD_CONST              62 (208)
           1626 LOAD_CONST             159 (212)
           1629 LOAD_CONST             222 (103)
           1632 LOAD_CONST              23 (159)
           1635 LOAD_CONST              17 (75)
           1638 LOAD_CONST             223 (106)
           1641 LOAD_CONST              45 (9)
           1644 LOAD_CONST              93 (126)
           1647 LOAD_CONST             106 (109)
           1650 LOAD_CONST             135 (98)
           1653 LOAD_CONST              77 (107)
           1656 LOAD_CONST             131 (16)
           1659 LOAD_CONST              54 (49)
           1662 LOAD_CONST             141 (87)
           1665 LOAD_CONST             143 (175)
           1668 LOAD_CONST              25 (29)
           1671 LOAD_CONST             220 (3)
           1674 LOAD_CONST              25 (29)
           1677 LOAD_CONST             112 (100)
           1680 LOAD_CONST             170 (22)
           1683 LOAD_CONST             224 (129)
           1686 LOAD_CONST             203 (30)
           1689 LOAD_CONST              16 (168)
           1692 LOAD_CONST              59 (197)
           1695 LOAD_CONST             225 (116)
           1698 LOAD_CONST              59 (197)
           1701 LOAD_CONST              51 (189)
           1704 LOAD_CONST             102 (15)
           1707 LOAD_CONST              75 (191)
           1710 LOAD_CONST             226 (10)
           1713 LOAD_CONST              55 (204)
           1716 LOAD_CONST             169 (46)
           1719 LOAD_CONST              48 (118)
           1722 LOAD_CONST              28 (102)
           1725 LOAD_CONST              54 (49)
           1728 LOAD_CONST             181 (180)
           1731 LOAD_CONST              64 (234)
           1734 LOAD_CONST             183 (205)
           1737 LOAD_CONST              80 (48)
           1740 LOAD_CONST             227 (190)
           1743 LOAD_CONST              12 (120)
           1746 LOAD_CONST              19 (198)
           1749 LOAD_CONST              63 (69)
           1752 LOAD_CONST               9 (115)
           1755 LOAD_CONST             161 (181)
           1758 LOAD_CONST               5 (5)
           1761 LOAD_CONST             228 (148)
           1764 LOAD_CONST             224 (129)
           1767 LOAD_CONST              33 (161)
           1770 LOAD_CONST              57 (178)
           1773 LOAD_CONST               6 (219)
           1776 LOAD_CONST             109 (50)
           1779 LOAD_CONST             201 (226)
           1782 LOAD_CONST             108 (185)
           1785 LOAD_CONST              54 (49)
           1788 LOAD_CONST             229 (235)
           1791 LOAD_CONST             230 (94)
           1794 LOAD_CONST             231 (254)
           1797 LOAD_CONST             111 (177)
           1800 LOAD_CONST              50 (73)
           1803 LOAD_CONST             215 (247)
           1806 LOAD_CONST             225 (116)
           1809 LOAD_CONST             169 (46)
           1812 LOAD_CONST             165 (62)
           1815 LOAD_CONST              45 (9)
           1818 LOAD_CONST             179 (184)
           1821 LOAD_CONST              35 (4)
           1824 LOAD_CONST             112 (100)
           1827 LOAD_CONST             172 (111)
           1830 LOAD_CONST              65 (206)
           1833 LOAD_CONST             204 (215)
           1836 LOAD_CONST              28 (102)
           1839 LOAD_CONST              88 (26)
           1842 LOAD_CONST             232 (70)
           1845 LOAD_CONST             108 (185)
           1848 LOAD_CONST             150 (238)
           1851 LOAD_CONST              66 (54)
           1854 LOAD_CONST             138 (91)
           1857 LOAD_CONST              81 (188)
           1860 LOAD_CONST             108 (185)
           1863 LOAD_CONST             180 (61)
           1866 LOAD_CONST              71 (242)
           1869 LOAD_CONST              87 (149)
           1872 LOAD_CONST              88 (26)
           1875 LOAD_CONST             110 (214)
           1878 LOAD_CONST              17 (75)
           1881 LOAD_CONST             193 (66)
           1884 LOAD_CONST             101 (166)
           1887 LOAD_CONST             231 (254)
           1890 LOAD_CONST             210 (25)
           1893 LOAD_CONST              93 (126)
           1896 LOAD_CONST             178 (13)
           1899 LOAD_CONST              91 (211)
           1902 LOAD_CONST              16 (168)
           1905 LOAD_CONST             193 (66)
           1908 LOAD_CONST             150 (238)
           1911 LOAD_CONST              47 (42)
           1914 LOAD_CONST             175 (96)
           1917 LOAD_CONST             150 (238)
           1920 LOAD_CONST             233 (121)
           1923 LOAD_CONST             168 (79)
           1926 LOAD_CONST              77 (107)
           1929 LOAD_CONST              70 (74)
           1932 LOAD_CONST              94 (167)
           1935 LOAD_CONST             234 (130)
           1938 LOAD_CONST             219 (11)
           1941 LOAD_CONST             116 (84)
           1944 LOAD_CONST             109 (50)
           1947 LOAD_CONST             154 (252)
           1950 LOAD_CONST             135 (98)
           1953 LOAD_CONST             235 (147)
           1956 LOAD_CONST             193 (66)
           1959 LOAD_CONST             236 (220)
           1962 LOAD_CONST              81 (188)
           1965 LOAD_CONST             179 (184)
           1968 LOAD_CONST             177 (186)
           1971 LOAD_CONST             171 (58)
           1974 LOAD_CONST             127 (164)
           1977 LOAD_CONST             152 (203)
           1980 LOAD_CONST              31 (51)
           1983 LOAD_CONST              89 (165)
           1986 LOAD_CONST             112 (100)
           1989 LOAD_CONST              99 (108)
           1992 LOAD_CONST             171 (58)
           1995 LOAD_CONST              57 (178)
           1998 LOAD_CONST              83 (90)
           2001 LOAD_CONST              96 (78)
           2004 LOAD_CONST              12 (120)
           2007 LOAD_CONST             237 (37)
           2010 LOAD_CONST             225 (116)
           2013 LOAD_CONST             238 (41)
           2016 LOAD_CONST             113 (63)
           2019 LOAD_CONST             119 (154)
           2022 LOAD_CONST             111 (177)
           2025 LOAD_CONST             239 (231)
           2028 LOAD_CONST             188 (117)
           2031 LOAD_CONST               4 (122)
           2034 LOAD_CONST              13 (86)
           2037 LOAD_CONST             124 (229)
           2040 LOAD_CONST             132 (196)
           2043 LOAD_CONST             156 (232)
           2046 LOAD_CONST             219 (11)
           2049 LOAD_CONST             199 (222)
           2052 LOAD_CONST              33 (161)
           2055 LOAD_CONST             113 (63)
           2058 LOAD_CONST              54 (49)
           2061 LOAD_CONST             132 (196)
           2064 LOAD_CONST             128 (7)
           2067 LOAD_CONST              47 (42)
           2070 LOAD_CONST              81 (188)
           2073 LOAD_CONST              88 (26)
           2076 LOAD_CONST              94 (167)
           2079 LOAD_CONST             106 (109)
           2082 LOAD_CONST              42 (193)
           2085 LOAD_CONST               2 (131)
           2088 LOAD_CONST             204 (215)
           2091 LOAD_CONST             234 (130)
           2094 LOAD_CONST             215 (247)
           2097 LOAD_CONST             240 (21)
           2100 LOAD_CONST             239 (231)
           2103 LOAD_CONST              80 (48)
           2106 LOAD_CONST             192 (241)
           2109 LOAD_CONST             241 (39)
           2112 LOAD_CONST             110 (214)
           2115 LOAD_CONST             242 (155)
           2118 LOAD_CONST             124 (229)
           2121 LOAD_CONST              12 (120)
           2124 LOAD_CONST             236 (220)
           2127 LOAD_CONST              55 (204)
           2130 LOAD_CONST               3 (55)
           2133 LOAD_CONST             209 (119)
           2136 LOAD_CONST             209 (119)
           2139 LOAD_CONST             213 (32)
           2142 LOAD_CONST             147 (182)
           2145 LOAD_CONST              13 (86)
           2148 LOAD_CONST             206 (43)
           2151 LOAD_CONST             139 (163)
           2154 LOAD_CONST             170 (22)
           2157 LOAD_CONST             204 (215)
           2160 LOAD_CONST             243 (81)
           2163 LOAD_CONST             159 (212)
           2166 LOAD_CONST              56 (12)
           2169 LOAD_CONST             228 (148)
           2172 LOAD_CONST             202 (176)
           2175 LOAD_CONST             232 (70)
           2178 LOAD_CONST             229 (235)
           2181 LOAD_CONST              85 (76)
           2184 LOAD_CONST              42 (193)
           2187 LOAD_CONST             194 (141)
           2190 LOAD_CONST             228 (148)
           2193 LOAD_CONST             229 (235)
           2196 LOAD_CONST              27 (24)
           2199 LOAD_CONST             221 (34)
           2202 LOAD_CONST             227 (190)
           2205 LOAD_CONST             107 (151)
           2208 LOAD_CONST             216 (140)
           2211 LOAD_CONST             126 (216)
           2214 LOAD_CONST             244 (136)
           2217 LOAD_CONST              90 (71)
           2220 LOAD_CONST              92 (248)
           2223 LOAD_CONST             119 (154)
           2226 LOAD_CONST             185 (44)
           2229 LOAD_CONST              58 (68)
           2232 LOAD_CONST             212 (225)
           2235 LOAD_CONST              34 (110)
           2238 LOAD_CONST              75 (191)
           2241 LOAD_CONST             211 (83)
           2244 LOAD_CONST             138 (91)
           2247 LOAD_CONST               3 (55)
           2250 LOAD_CONST              69 (138)
           2253 LOAD_CONST             220 (3)
           2256 LOAD_CONST              46 (195)
           2259 LOAD_CONST             136 (52)
           2262 LOAD_CONST              19 (198)
           2265 LOAD_CONST             245 (56)
           2268 LOAD_CONST             113 (63)
           2271 LOAD_CONST             162 (132)
           2274 LOAD_CONST             204 (215)
           2277 LOAD_CONST              86 (245)
           2280 LOAD_CONST             240 (21)
           2283 LOAD_CONST             114 (192)
           2286 LOAD_CONST              90 (71)
           2289 LOAD_CONST             243 (81)
           2292 LOAD_CONST              36 (20)
           2295 LOAD_CONST             227 (190)
           2298 LOAD_CONST             155 (249)
           2301 LOAD_CONST              99 (108)
           2304 LOAD_CONST             116 (84)
           2307 LOAD_CONST             207 (162)
           2310 LOAD_CONST             137 (240)
           2313 LOAD_CONST             177 (186)
           2316 LOAD_CONST              83 (90)
           2319 LOAD_CONST             190 (170)
           2322 LOAD_CONST              19 (198)
           2325 LOAD_CONST              51 (189)
           2328 LOAD_CONST             192 (241)
           2331 LOAD_CONST             215 (247)
           2334 LOAD_CONST             180 (61)
           2337 LOAD_CONST             117 (6)
           2340 LOAD_CONST              35 (4)
           2343 LOAD_CONST             197 (221)
           2346 LOAD_CONST             226 (10)
           2349 LOAD_CONST              97 (158)
           2352 LOAD_CONST             209 (119)
           2355 LOAD_CONST              68 (47)
           2358 LOAD_CONST              46 (195)
           2361 LOAD_CONST             209 (119)
           2364 LOAD_CONST             116 (84)
           2367 LOAD_CONST              60 (14)
           2370 LOAD_CONST              95 (174)
           2373 LOAD_CONST             126 (216)
           2376 LOAD_CONST              85 (76)
           2379 LOAD_CONST             133 (210)
           2382 LOAD_CONST              11 (194)
           2385 LOAD_CONST             206 (43)
           2388 LOAD_CONST              33 (161)
           2391 LOAD_CONST             133 (210)
           2394 LOAD_CONST             195 (101)
           2397 LOAD_CONST             246 (156)
           2400 LOAD_CONST              73 (72)
           2403 LOAD_CONST             174 (28)
           2406 LOAD_CONST             178 (13)
           2409 LOAD_CONST               7 (125)
           2412 LOAD_CONST             106 (109)
           2415 LOAD_CONST              36 (20)
           2418 LOAD_CONST              99 (108)
           2421 LOAD_CONST             223 (106)
           2424 LOAD_CONST             136 (52)
           2427 LOAD_CONST             145 (82)
           2430 LOAD_CONST              95 (174)
           2433 LOAD_CONST             106 (109)
           2436 LOAD_CONST               5 (5)
           2439 LOAD_CONST              29 (104)
           2442 LOAD_CONST              49 (19)
           2445 LOAD_CONST              22 (99)
           2448 LOAD_CONST             137 (240)
           2451 LOAD_CONST             189 (97)
           2454 LOAD_CONST              91 (211)
           2457 LOAD_CONST             247 (183)
           2460 LOAD_CONST              12 (120)
           2463 LOAD_CONST             161 (181)
           2466 LOAD_CONST              43 (179)
           2469 LOAD_CONST             219 (11)
           2472 LOAD_CONST              55 (204)
           2475 LOAD_CONST              56 (12)
           2478 LOAD_CONST             179 (184)
           2481 LOAD_CONST             211 (83)
           2484 LOAD_CONST             121 (112)
           2487 LOAD_CONST              38 (17)
           2490 LOAD_CONST             113 (63)
           2493 LOAD_CONST             181 (180)
           2496 LOAD_CONST             148 (237)
           2499 LOAD_CONST             227 (190)
           2502 LOAD_CONST              50 (73)
           2505 LOAD_CONST              75 (191)
           2508 LOAD_CONST              60 (14)
           2511 LOAD_CONST              57 (178)
           2514 LOAD_CONST             193 (66)
           2517 LOAD_CONST             128 (7)
           2520 LOAD_CONST              11 (194)
           2523 LOAD_CONST              45 (9)
           2526 LOAD_CONST              82 (230)
           2529 LOAD_CONST              71 (242)
           2532 LOAD_CONST              94 (167)
           2535 LOAD_CONST             147 (182)
           2538 LOAD_CONST             101 (166)
           2541 LOAD_CONST              63 (69)
           2544 LOAD_CONST             146 (228)
           2547 LOAD_CONST             181 (180)
           2550 LOAD_CONST             104 (65)
           2553 LOAD_CONST             124 (229)
           2556 LOAD_CONST             185 (44)
           2559 LOAD_CONST             198 (246)
           2562 LOAD_CONST             114 (192)
           2565 LOAD_CONST             171 (58)
           2568 LOAD_CONST              71 (242)
           2571 LOAD_CONST              35 (4)
           2574 LOAD_CONST             200 (92)
           2577 LOAD_CONST              50 (73)
           2580 LOAD_CONST              14 (127)
           2583 LOAD_CONST             129 (207)
           2586 LOAD_CONST             102 (15)
           2589 LOAD_CONST             170 (22)
           2592 LOAD_CONST              30 (31)
           2595 LOAD_CONST              51 (189)
           2598 LOAD_CONST              89 (165)
           2601 LOAD_CONST             160 (18)
           2604 LOAD_CONST              38 (17)
           2607 LOAD_CONST              63 (69)
           2610 LOAD_CONST             227 (190)
           2613 LOAD_CONST             151 (152)
           2616 LOAD_CONST              66 (54)
           2619 LOAD_CONST             185 (44)
           2622 LOAD_CONST              55 (204)
           2625 LOAD_CONST              42 (193)
           2628 LOAD_CONST             115 (77)
           2631 LOAD_CONST              39 (134)
           2634 LOAD_CONST             248 (224)
           2637 LOAD_CONST             203 (30)
           2640 LOAD_CONST             207 (162)
           2643 LOAD_CONST             245 (56)
           2646 LOAD_CONST             184 (59)
           2649 LOAD_CONST             144 (209)
           2652 LOAD_CONST             105 (255)
           2655 LOAD_CONST              49 (19)
           2658 LOAD_CONST              93 (126)
           2661 LOAD_CONST             233 (121)
           2664 LOAD_CONST             127 (164)
           2667 LOAD_CONST             236 (220)
           2670 LOAD_CONST              73 (72)
           2673 LOAD_CONST             150 (238)
           2676 LOAD_CONST             169 (46)
           2679 LOAD_CONST              36 (20)
           2682 LOAD_CONST             228 (148)
           2685 LOAD_CONST             226 (10)
           2688 LOAD_CONST             191 (67)
           2691 LOAD_CONST             106 (109)
           2694 LOAD_CONST              17 (75)
           2697 LOAD_CONST             133 (210)
           2700 LOAD_CONST             134 (244)
           2703 LOAD_CONST              14 (127)
           2706 LOAD_CONST              32 (80)
           2709 LOAD_CONST             136 (52)
           2712 LOAD_CONST             249 (253)
           2715 LOAD_CONST             175 (96)
           2718 LOAD_CONST             153 (146)
           2721 LOAD_CONST             245 (56)
           2724 LOAD_CONST             139 (163)
           2727 LOAD_CONST             129 (207)
           2730 LOAD_CONST             227 (190)
           2733 LOAD_CONST             147 (182)
           2736 LOAD_CONST             109 (50)
           2739 LOAD_CONST             199 (222)
           2742 LOAD_CONST             147 (182)
           2745 LOAD_CONST             165 (62)
           2748 LOAD_CONST             236 (220)
           2751 LOAD_CONST              36 (20)
           2754 LOAD_CONST              77 (107)
           2757 LOAD_CONST             217 (57)
           2760 LOAD_CONST             111 (177)
           2763 LOAD_CONST              68 (47)
           2766 LOAD_CONST              70 (74)
           2769 LOAD_CONST             225 (116)
           2772 LOAD_CONST             243 (81)
           2775 LOAD_CONST              76 (2)
           2778 LOAD_CONST              20 (45)
           2781 LOAD_CONST              31 (51)
           2784 LOAD_CONST             119 (154)
           2787 LOAD_CONST              59 (197)
           2790 LOAD_CONST             119 (154)
           2793 LOAD_CONST             209 (119)
           2796 LOAD_CONST              74 (123)
           2799 LOAD_CONST             213 (32)
           2802 LOAD_CONST             239 (231)
           2805 LOAD_CONST              11 (194)
           2808 LOAD_CONST             124 (229)
           2811 LOAD_CONST             188 (117)
           2814 LOAD_CONST               6 (219)
           2817 LOAD_CONST             204 (215)
           2820 LOAD_CONST              24 (60)
           2823 LOAD_CONST             184 (59)
           2826 LOAD_CONST              55 (204)
           2829 LOAD_CONST              26 (0)
           2832 LOAD_CONST              20 (45)
           2835 LOAD_CONST             111 (177)
           2838 LOAD_CONST             172 (111)
           2841 LOAD_CONST             139 (163)
           2844 LOAD_CONST              88 (26)
           2847 LOAD_CONST             247 (183)
           2850 LOAD_CONST             105 (255)
           2853 LOAD_CONST              62 (208)
           2856 LOAD_CONST             234 (130)
           2859 LOAD_CONST              86 (245)
           2862 LOAD_CONST              22 (99)
           2865 LOAD_CONST             250 (144)
           2868 LOAD_CONST              80 (48)
           2871 LOAD_CONST             251 (128)
           2874 LOAD_CONST             185 (44)
           2877 LOAD_CONST              21 (160)
           2880 LOAD_CONST              52 (233)
           2883 LOAD_CONST             119 (154)
           2886 LOAD_CONST              12 (120)
           2889 LOAD_CONST               6 (219)
           2892 LOAD_CONST              55 (204)
           2895 LOAD_CONST             191 (67)
           2898 LOAD_CONST              56 (12)
           2901 LOAD_CONST               9 (115)
           2904 LOAD_CONST             141 (87)
           2907 LOAD_CONST             108 (185)
           2910 LOAD_CONST             214 (38)
           2913 LOAD_CONST             118 (95)
           2916 LOAD_CONST             101 (166)
           2919 LOAD_CONST             175 (96)
           2922 LOAD_CONST              94 (167)
           2925 LOAD_CONST             221 (34)
           2928 LOAD_CONST             127 (164)
           2931 LOAD_CONST              56 (12)
           2934 LOAD_CONST             150 (238)
           2937 LOAD_CONST              11 (194)
           2940 LOAD_CONST             232 (70)
           2943 LOAD_CONST             229 (235)
           2946 LOAD_CONST             184 (59)
           2949 LOAD_CONST              11 (194)
           2952 LOAD_CONST             158 (139)
           2955 LOAD_CONST              87 (149)
           2958 LOAD_CONST             119 (154)
           2961 LOAD_CONST             175 (96)
           2964 LOAD_CONST             241 (39)
           2967 LOAD_CONST              51 (189)
           2970 LOAD_CONST              82 (230)
           2973 LOAD_CONST              69 (138)
           2976 LOAD_CONST             126 (216)
           2979 LOAD_CONST             134 (244)
           2982 LOAD_CONST              90 (71)
           2985 LOAD_CONST             252 (251)
           2988 LOAD_CONST             148 (237)
           2991 LOAD_CONST             185 (44)
           2994 LOAD_CONST              24 (60)
           2997 LOAD_CONST             248 (224)
           3000 LOAD_CONST             172 (111)
           3003 LOAD_CONST             142 (199)
           3006 LOAD_CONST             214 (38)
           3009 LOAD_CONST             206 (43)
           3012 LOAD_CONST              58 (68)
           3015 LOAD_CONST             164 (143)
           3018 LOAD_CONST               9 (115)
           3021 LOAD_CONST              11 (194)
           3024 LOAD_CONST             136 (52)
           3027 LOAD_CONST              84 (202)
           3030 LOAD_CONST              17 (75)
           3033 LOAD_CONST              63 (69)
           3036 LOAD_CONST               2 (131)
           3039 LOAD_CONST              62 (208)
           3042 LOAD_CONST             251 (128)
           3045 LOAD_CONST              37 (23)
           3048 LOAD_CONST             161 (181)
           3051 LOAD_CONST              31 (51)
           3054 LOAD_CONST              13 (86)
           3057 LOAD_CONST              49 (19)
           3060 LOAD_CONST             132 (196)
           3063 LOAD_CONST             137 (240)
           3066 LOAD_CONST             203 (30)
           3069 LOAD_CONST             145 (82)
           3072 LOAD_CONST             101 (166)
           3075 LOAD_CONST             234 (130)
           3078 LOAD_CONST              19 (198)
           3081 LOAD_CONST             163 (40)
           3084 LOAD_CONST               6 (219)
           3087 LOAD_CONST              84 (202)
           3090 LOAD_CONST             179 (184)
           3093 LOAD_CONST             192 (241)
           3096 LOAD_CONST             234 (130)
           3099 LOAD_CONST             171 (58)
           3102 LOAD_CONST             121 (112)
           3105 LOAD_CONST             225 (116)
           3108 LOAD_CONST              33 (161)
           3111 LOAD_CONST             233 (121)
           3114 LOAD_CONST             151 (152)
           3117 LOAD_CONST             121 (112)
           3120 LOAD_CONST             169 (46)
           3123 LOAD_CONST             108 (185)
           3126 LOAD_CONST              12 (120)
           3129 LOAD_CONST              13 (86)
           3132 LOAD_CONST             225 (116)
           3135 LOAD_CONST              15 (169)
           3138 LOAD_CONST              95 (174)
           3141 LOAD_CONST              96 (78)
           3144 LOAD_CONST              40 (223)
           3147 LOAD_CONST             247 (183)
           3150 LOAD_CONST             238 (41)
           3153 LOAD_CONST             159 (212)
           3156 LOAD_CONST             139 (163)
           3159 LOAD_CONST             131 (16)
           3162 LOAD_CONST             253 (236)
           3165 LOAD_CONST             184 (59)
           3168 LOAD_CONST              27 (24)
           3171 LOAD_CONST              56 (12)
           3174 LOAD_CONST             254 (1)
           3177 LOAD_CONST              30 (31)
           3180 LOAD_CONST             112 (100)
           3183 LOAD_CONST             130 (105)
           3186 LOAD_CONST              79 (27)
           3189 LOAD_CONST             104 (65)
           3192 LOAD_CONST             243 (81)
           3195 LOAD_CONST              62 (208)
           3198 LOAD_CONST             106 (109)
           3201 LOAD_CONST             254 (1)
           3204 LOAD_CONST             174 (28)
           3207 LOAD_CONST             131 (16)
           3210 LOAD_CONST              36 (20)
           3213 LOAD_CONST             187 (243)
           3216 LOAD_CONST             223 (106)
           3219 LOAD_CONST             190 (170)
           3222 LOAD_CONST              57 (178)
           3225 LOAD_CONST             166 (113)
           3228 LOAD_CONST              46 (195)
           3231 LOAD_CONST             152 (203)
           3234 LOAD_CONST             122 (124)
           3237 LOAD_CONST              81 (188)
           3240 LOAD_CONST             173 (8)
           3243 LOAD_CONST             183 (205)
           3246 LOAD_CONST              83 (90)
           3249 LOAD_CONST             254 (1)
           3252 LOAD_CONST              28 (102)
           3255 LOAD_CONST             184 (59)
           3258 LOAD_CONST             181 (180)
           3261 LOAD_CONST             124 (229)
           3264 LOAD_CONST              55 (204)
           3267 LOAD_CONST             180 (61)
           3270 LOAD_CONST             140 (187)
           3273 LOAD_CONST              14 (127)
           3276 LOAD_CONST             142 (199)
           3279 LOAD_CONST              80 (48)
           3282 LOAD_CONST               7 (125)
           3285 LOAD_CONST             161 (181)
           3288 LOAD_CONST              14 (127)
           3291 LOAD_CONST             182 (227)
           3294 LOAD_CONST             205 (133)
           3297 LOAD_CONST               6 (219)
           3300 LOAD_CONST             179 (184)
           3303 LOAD_CONST             196 (213)
           3306 LOAD_CONST              90 (71)
           3309 LOAD_CONST             153 (146)
           3312 LOAD_CONST              84 (202)
           3315 LOAD_CONST             100 (64)
           3318 LOAD_CONST             124 (229)
           3321 LOAD_CONST              20 (45)
           3324 LOAD_CONST             255 (137)
           3327 LOAD_CONST             132 (196)
           3330 LOAD_CONST              85 (76)
           3333 LOAD_CONST             155 (249)
           3336 LOAD_CONST              12 (120)
           3339 LOAD_CONST              83 (90)
           3342 LOAD_CONST             136 (52)
           3345 LOAD_CONST             121 (112)
           3348 LOAD_CONST             161 (181)
           3351 LOAD_CONST              26 (0)
           3354 LOAD_CONST             112 (100)
           3357 LOAD_CONST             172 (111)
           3360 LOAD_CONST              55 (204)
           3363 LOAD_CONST              62 (208)
           3366 LOAD_CONST             160 (18)
           3369 LOAD_CONST              79 (27)
           3372 LOAD_CONST             136 (52)
           3375 LOAD_CONST              53 (201)
           3378 LOAD_CONST             150 (238)
           3381 LOAD_CONST              31 (51)
           3384 LOAD_CONST              72 (93)
           3387 LOAD_CONST             227 (190)
           3390 LOAD_CONST             202 (176)
           3393 LOAD_CONST             165 (62)
           3396 LOAD_CONST             162 (132)
           3399 LOAD_CONST             120 (145)
           3402 LOAD_CONST              30 (31)
           3405 LOAD_CONST              21 (160)
           3408 LOAD_CONST             184 (59)
           3411 LOAD_CONST             157 (53)
           3414 LOAD_CONST             110 (214)
           3417 LOAD_CONST             158 (139)
           3420 LOAD_CONST             210 (25)
           3423 LOAD_CONST              93 (126)
           3426 LOAD_CONST             173 (8)
           3429 LOAD_CONST              62 (208)
           3432 LOAD_CONST               6 (219)
           3435 LOAD_CONST              24 (60)
           3438 LOAD_CONST             253 (236)
           3441 LOAD_CONST              83 (90)
           3444 LOAD_CONST             222 (103)
           3447 LOAD_CONST              52 (233)
           3450 LOAD_CONST             233 (121)
           3453 LOAD_CONST              96 (78)
           3456 LOAD_CONST             172 (111)
           3459 LOAD_CONST              63 (69)
           3462 LOAD_CONST             196 (213)
           3465 LOAD_CONST             187 (243)
           3468 LOAD_CONST             188 (117)
           3471 LOAD_CONST             230 (94)
           3474 LOAD_CONST              31 (51)
           3477 LOAD_CONST             154 (252)
           3480 LOAD_CONST              99 (108)
           3483 LOAD_CONST              87 (149)
           3486 LOAD_CONST             157 (53)
           3489 LOAD_CONST             199 (222)
           3492 LOAD_CONST              84 (202)
           3495 LOAD_CONST             140 (187)
           3498 LOAD_CONST              43 (179)
           3501 LOAD_CONST              90 (71)
           3504 LOAD_CONST             196 (213)
           3507 LOAD_CONST             114 (192)
           3510 LOAD_CONST             191 (67)
           3513 LOAD_CONST             256 (217)
           3516 LOAD_CONST              37 (23)
           3519 LOAD_CONST              34 (110)
           3522 LOAD_CONST             136 (52)
           3525 LOAD_CONST              81 (188)
           3528 LOAD_CONST             169 (46)
           3531 LOAD_CONST             115 (77)
           3534 LOAD_CONST             220 (3)
           3537 LOAD_CONST              32 (80)
           3540 LOAD_CONST              41 (114)
           3543 LOAD_CONST             200 (92)
           3546 LOAD_CONST              54 (49)
           3549 LOAD_CONST             250 (144)
           3552 LOAD_CONST              59 (197)
           3555 LOAD_CONST             120 (145)
           3558 LOAD_CONST              35 (4)
           3561 LOAD_CONST               7 (125)
           3564 LOAD_CONST             214 (38)
           3567 LOAD_CONST             229 (235)
           3570 LOAD_CONST              59 (197)
           3573 LOAD_CONST              67 (239)
           3576 LOAD_CONST               5 (5)
           3579 LOAD_CONST              91 (211)
           3582 LOAD_CONST             133 (210)
           3585 LOAD_CONST             191 (67)
           3588 LOAD_CONST             184 (59)
           3591 LOAD_CONST              43 (179)
           3594 LOAD_CONST              26 (0)
           3597 LOAD_CONST             208 (88)
           3600 LOAD_CONST             129 (207)
           3603 LOAD_CONST             172 (111)
           3606 LOAD_CONST              94 (167)
           3609 LOAD_CONST              27 (24)
           3612 LOAD_CONST             132 (196)
           3615 LOAD_CONST             137 (240)
           3618 LOAD_CONST             207 (162)
           3621 LOAD_CONST             205 (133)
           3624 LOAD_CONST               2 (131)
           3627 LOAD_CONST              36 (20)
           3630 LOAD_CONST             228 (148)
           3633 LOAD_CONST             217 (57)
           3636 LOAD_CONST             192 (241)
           3639 LOAD_CONST             118 (95)
           3642 LOAD_CONST             133 (210)
           3645 LOAD_CONST              97 (158)
           3648 LOAD_CONST             235 (147)
           3651 LOAD_CONST              93 (126)
           3654 LOAD_CONST              16 (168)
           3657 LOAD_CONST             247 (183)
           3660 LOAD_CONST             193 (66)
           3663 LOAD_CONST              35 (4)
           3666 LOAD_CONST              76 (2)
           3669 LOAD_CONST             123 (33)
           3672 LOAD_CONST              43 (179)
           3675 LOAD_CONST             167 (85)
           3678 LOAD_CONST             169 (46)
           3681 LOAD_CONST              95 (174)
           3684 LOAD_CONST              29 (104)
           3687 LOAD_CONST             133 (210)
           3690 LOAD_CONST             123 (33)
           3693 LOAD_CONST             159 (212)
           3696 LOAD_CONST               4 (122)
           3699 LOAD_CONST             235 (147)
           3702 LOAD_CONST             247 (183)
           3705 LOAD_CONST              85 (76)
           3708 LOAD_CONST             229 (235)
           3711 LOAD_CONST              17 (75)
           3714 LOAD_CONST             202 (176)
           3717 LOAD_CONST             244 (136)
           3720 LOAD_CONST             248 (224)
           3723 LOAD_CONST             242 (155)
           3726 LOAD_CONST             170 (22)
           3729 LOAD_CONST             200 (92)
           3732 LOAD_CONST              51 (189)
           3735 LOAD_CONST              82 (230)
           3738 LOAD_CONST             154 (252)
           3741 LOAD_CONST             236 (220)
           3744 LOAD_CONST              92 (248)
           3747 LOAD_CONST              58 (68)
           3750 LOAD_CONST              92 (248)
           3753 LOAD_CONST             246 (156)
           3756 LOAD_CONST             241 (39)
           3759 LOAD_CONST              54 (49)
           3762 LOAD_CONST             148 (237)
           3765 LOAD_CONST              27 (24)
           3768 LOAD_CONST             129 (207)
           3771 LOAD_CONST             237 (37)
           3774 LOAD_CONST             230 (94)
           3777 LOAD_CONST             157 (53)
           3780 LOAD_CONST             155 (249)
           3783 LOAD_CONST             166 (113)
           3786 LOAD_CONST              57 (178)
           3789 LOAD_CONST             157 (53)
           3792 LOAD_CONST              84 (202)
           3795 LOAD_CONST              31 (51)
           3798 LOAD_CONST              58 (68)
           3801 LOAD_CONST             162 (132)
           3804 LOAD_CONST              89 (165)
           3807 LOAD_CONST             187 (243)
           3810 LOAD_CONST             160 (18)
           3813 LOAD_CONST             202 (176)
           3816 LOAD_CONST             168 (79)
           3819 LOAD_CONST             145 (82)
           3822 LOAD_CONST              37 (23)
           3825 LOAD_CONST              19 (198)
           3828 LOAD_CONST             251 (128)
           3831 LOAD_CONST              30 (31)
           3834 LOAD_CONST             241 (39)
           3837 LOAD_CONST              89 (165)
           3840 LOAD_CONST             134 (244)
           3843 LOAD_CONST             183 (205)
           3846 LOAD_CONST              72 (93)
           3849 LOAD_CONST              40 (223)
           3852 LOAD_CONST              75 (191)
           3855 LOAD_CONST              84 (202)
           3858 LOAD_CONST             252 (251)
           3861 LOAD_CONST             162 (132)
           3864 LOAD_CONST              66 (54)
           3867 LOAD_CONST               4 (122)
           3870 LOAD_CONST              14 (127)
           3873 LOAD_CONST             143 (175)
           3876 LOAD_CONST             219 (11)
           3879 LOAD_CONST             119 (154)
           3882 LOAD_CONST              14 (127)
           3885 LOAD_CONST             167 (85)
           3888 LOAD_CONST             181 (180)
           3891 LOAD_CONST              56 (12)
           3894 LOAD_CONST             243 (81)
           3897 LOAD_CONST              45 (9)
           3900 LOAD_CONST              95 (174)
           3903 LOAD_CONST             197 (221)
           3906 LOAD_CONST              73 (72)
           3909 LOAD_CONST              16 (168)
           3912 LOAD_CONST              84 (202)
           3915 LOAD_CONST             238 (41)
           3918 LOAD_CONST             144 (209)
           3921 LOAD_CONST              16 (168)
           3924 LOAD_CONST             240 (21)
           3927 LOAD_CONST             229 (235)
           3930 LOAD_CONST              90 (71)
           3933 LOAD_CONST              88 (26)
           3936 LOAD_CONST              12 (120)
           3939 LOAD_CONST             226 (10)
           3942 LOAD_CONST              99 (108)
           3945 LOAD_CONST              28 (102)
           3948 LOAD_CONST              99 (108)
           3951 LOAD_CONST             174 (28)
           3954 LOAD_CONST             232 (70)
           3957 LOAD_CONST             141 (87)
           3960 LOAD_CONST              89 (165)
           3963 LOAD_CONST              99 (108)
           3966 LOAD_CONST              45 (9)
           3969 LOAD_CONST              27 (24)
           3972 LOAD_CONST              28 (102)
           3975 LOAD_CONST              28 (102)
           3978 LOAD_CONST             215 (247)
           3981 LOAD_CONST              29 (104)
           3984 LOAD_CONST              16 (168)
           3987 LOAD_CONST              19 (198)
           3990 LOAD_CONST              12 (120)
           3993 LOAD_CONST             247 (183)
           3996 LOAD_CONST             108 (185)
           3999 LOAD_CONST             226 (10)
           4002 LOAD_CONST              75 (191)
           4005 LOAD_CONST              45 (9)
           4008 LOAD_CONST              65 (206)
           4011 LOAD_CONST             169 (46)
           4014 LOAD_CONST             117 (6)
           4017 LOAD_CONST              37 (23)
           4020 LOAD_CONST             115 (77)
           4023 LOAD_CONST             111 (177)
           4026 LOAD_CONST             119 (154)
           4029 LOAD_CONST              84 (202)
           4032 LOAD_CONST              70 (74)
           4035 LOAD_CONST              84 (202)
           4038 LOAD_CONST               4 (122)
           4041 LOAD_CONST              57 (178)
           4044 LOAD_CONST              58 (68)
           4047 LOAD_CONST             209 (119)
           4050 LOAD_CONST              51 (189)
           4053 LOAD_CONST               7 (125)
           4056 LOAD_CONST             212 (225)
           4059 LOAD_CONST             198 (246)
           4062 LOAD_CONST             204 (215)
           4065 LOAD_CONST             111 (177)
           4068 LOAD_CONST             110 (214)
           4071 LOAD_CONST             157 (53)
           4074 LOAD_CONST             239 (231)
           4077 LOAD_CONST              44 (200)
           4080 LOAD_CONST             193 (66)
           4083 LOAD_CONST              97 (158)
           4086 LOAD_CONST              98 (89)
           4089 LOAD_CONST             154 (252)
           4092 LOAD_CONST              59 (197)
           4095 LOAD_CONST              17 (75)
           4098 LOAD_CONST             215 (247)
           4101 LOAD_CONST             121 (112)
           4104 LOAD_CONST             200 (92)
           4107 LOAD_CONST              85 (76)
           4110 LOAD_CONST             122 (124)
           4113 LOAD_CONST              75 (191)
           4116 LOAD_CONST               9 (115)
           4119 LOAD_CONST             131 (16)
           4122 LOAD_CONST              79 (27)
           4125 LOAD_CONST              44 (200)
           4128 LOAD_CONST             139 (163)
           4131 LOAD_CONST              36 (20)
           4134 LOAD_CONST              88 (26)
           4137 LOAD_CONST             100 (64)
           4140 LOAD_CONST             140 (187)
           4143 LOAD_CONST             253 (236)
           4146 LOAD_CONST              63 (69)
           4149 LOAD_CONST             238 (41)
           4152 LOAD_CONST              65 (206)
           4155 LOAD_CONST              19 (198)
           4158 LOAD_CONST             180 (61)
           4161 LOAD_CONST             134 (244)
           4164 LOAD_CONST             248 (224)
           4167 LOAD_CONST             106 (109)
           4170 LOAD_CONST              62 (208)
           4173 LOAD_CONST             171 (58)
           4176 LOAD_CONST              54 (49)
           4179 LOAD_CONST             204 (215)
           4182 LOAD_CONST              69 (138)
           4185 LOAD_CONST              36 (20)
           4188 LOAD_CONST              60 (14)
           4191 LOAD_CONST             178 (13)
           4194 LOAD_CONST              62 (208)
           4197 LOAD_CONST              18 (218)
           4200 LOAD_CONST              17 (75)
           4203 LOAD_CONST             253 (236)
           4206 LOAD_CONST             211 (83)
           4209 LOAD_CONST              49 (19)
           4212 LOAD_CONST              64 (234)
           4215 LOAD_CONST             219 (11)
           4218 LOAD_CONST             100 (64)
           4221 LOAD_CONST             172 (111)
           4224 LOAD_CONST              17 (75)
           4227 LOAD_CONST              91 (211)
           4230 LOAD_CONST             215 (247)
           4233 LOAD_CONST             102 (15)
           4236 LOAD_CONST             230 (94)
           4239 LOAD_CONST             193 (66)
           4242 LOAD_CONST             215 (247)
           4245 LOAD_CONST              37 (23)
           4248 LOAD_CONST             124 (229)
           4251 LOAD_CONST              90 (71)
           4254 LOAD_CONST             236 (220)
           4257 LOAD_CONST              51 (189)
           4260 LOAD_CONST             140 (187)
           4263 LOAD_CONST             114 (192)
           4266 LOAD_CONST              90 (71)
           4269 LOAD_CONST              33 (161)
           4272 LOAD_CONST             181 (180)
           4275 LOAD_CONST               3 (55)
           4278 LOAD_CONST               6 (219)
           4281 LOAD_CONST              28 (102)
           4284 LOAD_CONST             223 (106)
           4287 LOAD_CONST             184 (59)
           4290 LOAD_CONST              42 (193)
           4293 LOAD_CONST             169 (46)
           4296 LOAD_CONST              24 (60)
           4299 LOAD_CONST             128 (7)
           4302 LOAD_CONST             123 (33)
           4305 LOAD_CONST             117 (6)
           4308 LOAD_CONST              72 (93)
           4311 LOAD_CONST              58 (68)
           4314 LOAD_CONST             239 (231)
           4317 LOAD_CONST              57 (178)
           4320 LOAD_CONST             153 (146)
           4323 LOAD_CONST             128 (7)
           4326 LOAD_CONST              45 (9)
           4329 LOAD_CONST             116 (84)
           4332 LOAD_CONST             228 (148)
           4335 LOAD_CONST              19 (198)
           4338 LOAD_CONST              67 (239)
           4341 LOAD_CONST             209 (119)
           4344 LOAD_CONST             133 (210)
           4347 LOAD_CONST              62 (208)
           4350 LOAD_CONST              96 (78)
           4353 LOAD_CONST             245 (56)
           4356 LOAD_CONST             202 (176)
           4359 LOAD_CONST             128 (7)
           4362 LOAD_CONST             169 (46)
           4365 LOAD_CONST             129 (207)
           4368 LOAD_CONST             130 (105)
           4371 LOAD_CONST              94 (167)
           4374 LOAD_CONST              38 (17)
           4377 LOAD_CONST              43 (179)
           4380 LOAD_CONST             162 (132)
           4383 LOAD_CONST             207 (162)
           4386 LOAD_CONST             192 (241)
           4389 LOAD_CONST             205 (133)
           4392 LOAD_CONST             135 (98)
           4395 LOAD_CONST             151 (152)
           4398 LOAD_CONST             217 (57)
           4401 LOAD_CONST              71 (242)
           4404 LOAD_CONST             200 (92)
           4407 LOAD_CONST             144 (209)
           4410 LOAD_CONST              64 (234)
           4413 LOAD_CONST             212 (225)
           4416 LOAD_CONST              12 (120)
           4419 LOAD_CONST              95 (174)
           4422 LOAD_CONST              75 (191)
           4425 LOAD_CONST             157 (53)
           4428 LOAD_CONST              48 (118)
           4431 LOAD_CONST             102 (15)
           4434 LOAD_CONST             123 (33)
           4437 LOAD_CONST             108 (185)
           4440 LOAD_CONST              32 (80)
           4443 LOAD_CONST             238 (41)
           4446 LOAD_CONST             133 (210)
           4449 LOAD_CONST              36 (20)
           4452 LOAD_CONST              21 (160)
           4455 LOAD_CONST             103 (36)
           4458 LOAD_CONST             256 (217)
           4461 LOAD_CONST              56 (12)
           4464 LOAD_CONST             212 (225)
           4467 LOAD_CONST              75 (191)
           4470 LOAD_CONST              90 (71)
           4473 LOAD_CONST              64 (234)
           4476 LOAD_CONST              96 (78)
           4479 LOAD_CONST             181 (180)
           4482 LOAD_CONST             257 (250)
           4485 LOAD_CONST             212 (225)
           4488 LOAD_CONST             119 (154)
           4491 LOAD_CONST             131 (16)
           4494 LOAD_CONST             214 (38)
           4497 LOAD_CONST             177 (186)
           4500 LOAD_CONST             120 (145)
           4503 LOAD_CONST             216 (140)
           4506 LOAD_CONST             126 (216)
           4509 LOAD_CONST             252 (251)
           4512 LOAD_CONST             109 (50)
           4515 LOAD_CONST             255 (137)
           4518 LOAD_CONST             119 (154)
           4521 LOAD_CONST             243 (81)
           4524 LOAD_CONST              90 (71)
           4527 LOAD_CONST             212 (225)
           4530 LOAD_CONST             174 (28)
           4533 LOAD_CONST             177 (186)
           4536 LOAD_CONST             243 (81)
           4539 LOAD_CONST             185 (44)
           4542 LOAD_CONST              31 (51)
           4545 LOAD_CONST             231 (254)
           4548 LOAD_CONST               5 (5)
           4551 LOAD_CONST              44 (200)
           4554 LOAD_CONST              73 (72)
           4557 LOAD_CONST              84 (202)
           4560 LOAD_CONST              50 (73)
           4563 LOAD_CONST              85 (76)
           4566 LOAD_CONST             192 (241)
           4569 LOAD_CONST             144 (209)
           4572 LOAD_CONST             251 (128)
           4575 LOAD_CONST             175 (96)
           4578 LOAD_CONST              11 (194)
           4581 LOAD_CONST              90 (71)
           4584 LOAD_CONST              13 (86)
           4587 LOAD_CONST              22 (99)
           4590 LOAD_CONST              57 (178)
           4593 LOAD_CONST             134 (244)
           4596 LOAD_CONST              34 (110)
           4599 LOAD_CONST             241 (39)
           4602 LOAD_CONST              16 (168)
           4605 LOAD_CONST             137 (240)
           4608 LOAD_CONST             108 (185)
           4611 LOAD_CONST              83 (90)
           4614 LOAD_CONST              16 (168)
           4617 LOAD_CONST              53 (201)
           4620 LOAD_CONST             177 (186)
           4623 LOAD_CONST             244 (136)
           4626 LOAD_CONST             192 (241)
           4629 LOAD_CONST               3 (55)
           4632 LOAD_CONST              76 (2)
           4635 LOAD_CONST               9 (115)
           4638 LOAD_CONST             236 (220)
           4641 LOAD_CONST              60 (14)
           4644 LOAD_CONST             120 (145)
           4647 LOAD_CONST             209 (119)
           4650 LOAD_CONST             145 (82)
           4653 LOAD_CONST             111 (177)
           4656 LOAD_CONST              48 (118)
           4659 LOAD_CONST              10 (35)
           4662 LOAD_CONST             102 (15)
           4665 LOAD_CONST             218 (172)
           4668 LOAD_CONST              18 (218)
           4671 LOAD_CONST              17 (75)
           4674 LOAD_CONST             126 (216)
           4677 LOAD_CONST             181 (180)
           4680 LOAD_CONST              72 (93)
           4683 LOAD_CONST             133 (210)
           4686 LOAD_CONST             101 (166)
           4689 LOAD_CONST             203 (30)
           4692 LOAD_CONST             156 (232)
           4695 LOAD_CONST             184 (59)
           4698 LOAD_CONST             130 (105)
           4701 LOAD_CONST             226 (10)
           4704 LOAD_CONST              60 (14)
           4707 LOAD_CONST              29 (104)
           4710 LOAD_CONST             195 (101)
           4713 LOAD_CONST             172 (111)
           4716 LOAD_CONST              99 (108)
           4719 LOAD_CONST              54 (49)
           4722 LOAD_CONST             141 (87)
           4725 LOAD_CONST              95 (174)
           4728 LOAD_CONST              29 (104)
           4731 LOAD_CONST              48 (118)
           4734 LOAD_CONST             240 (21)
           4737 LOAD_CONST             240 (21)
           4740 LOAD_CONST              36 (20)
           4743 LOAD_CONST             224 (129)
           4746 LOAD_CONST             172 (111)
           4749 LOAD_CONST             126 (216)
           4752 LOAD_CONST             161 (181)
           4755 LOAD_CONST             166 (113)
           4758 LOAD_CONST             129 (207)
           4761 LOAD_CONST              81 (188)
           4764 LOAD_CONST              74 (123)
           4767 LOAD_CONST             111 (177)
           4770 LOAD_CONST               7 (125)
           4773 LOAD_CONST             140 (187)
           4776 LOAD_CONST              20 (45)
           4779 LOAD_CONST              76 (2)
           4782 LOAD_CONST              36 (20)
           4785 LOAD_CONST             180 (61)
           4788 LOAD_CONST              46 (195)
           4791 LOAD_CONST             125 (153)
           4794 LOAD_CONST             177 (186)
           4797 LOAD_CONST              96 (78)
           4800 LOAD_CONST             202 (176)
           4803 LOAD_CONST              74 (123)
           4806 LOAD_CONST             181 (180)
           4809 LOAD_CONST             157 (53)
           4812 LOAD_CONST             117 (6)
           4815 LOAD_CONST             114 (192)
           4818 LOAD_CONST              56 (12)
           4821 LOAD_CONST             146 (228)
           4824 LOAD_CONST             234 (130)
           4827 LOAD_CONST             144 (209)
           4830 LOAD_CONST             132 (196)
           4833 LOAD_CONST             127 (164)
           4836 LOAD_CONST              66 (54)
           4839 LOAD_CONST             182 (227)
           4842 LOAD_CONST             129 (207)
           4845 LOAD_CONST             157 (53)
           4848 LOAD_CONST             229 (235)
           4851 LOAD_CONST             200 (92)
           4854 LOAD_CONST             216 (140)
           4857 LOAD_CONST             179 (184)
           4860 LOAD_CONST             100 (64)
           4863 LOAD_CONST             137 (240)
           4866 LOAD_CONST              35 (4)
           4869 LOAD_CONST             200 (92)
           4872 LOAD_CONST              50 (73)
           4875 LOAD_CONST              45 (9)
           4878 LOAD_CONST              81 (188)
           4881 LOAD_CONST              35 (4)
           4884 LOAD_CONST             223 (106)
           4887 LOAD_CONST              88 (26)
           4890 LOAD_CONST              53 (201)
           4893 LOAD_CONST              78 (171)
           4896 LOAD_CONST             222 (103)
           4899 LOAD_CONST              79 (27)
           4902 LOAD_CONST              58 (68)
           4905 LOAD_CONST             227 (190)
           4908 LOAD_CONST             156 (232)
           4911 LOAD_CONST               3 (55)
           4914 LOAD_CONST             238 (41)
           4917 LOAD_CONST             177 (186)
           4920 LOAD_CONST              59 (197)
           4923 LOAD_CONST             180 (61)
           4926 LOAD_CONST             205 (133)
           4929 LOAD_CONST             239 (231)
           4932 LOAD_CONST             210 (25)
           4935 LOAD_CONST              89 (165)
           4938 LOAD_CONST             168 (79)
           4941 LOAD_CONST              63 (69)
           4944 LOAD_CONST             207 (162)
           4947 LOAD_CONST             205 (133)
           4950 LOAD_CONST              37 (23)
           4953 LOAD_CONST              93 (126)
           4956 LOAD_CONST              56 (12)
           4959 LOAD_CONST             127 (164)
           4962 LOAD_CONST             236 (220)
           4965 LOAD_CONST             165 (62)
           4968 LOAD_CONST             151 (152)
           4971 LOAD_CONST             138 (91)
           4974 LOAD_CONST             106 (109)
           4977 LOAD_CONST             119 (154)
           4980 LOAD_CONST             226 (10)
           4983 LOAD_CONST              96 (78)
           4986 LOAD_CONST              27 (24)
           4989 LOAD_CONST             100 (64)
           4992 LOAD_CONST             101 (166)
           4995 LOAD_CONST             234 (130)
           4998 LOAD_CONST             219 (11)
           5001 LOAD_CONST             123 (33)
           5004 LOAD_CONST               3 (55)
           5007 LOAD_CONST             198 (246)
           5010 LOAD_CONST              37 (23)
           5013 LOAD_CONST             182 (227)
           5016 LOAD_CONST              58 (68)
           5019 LOAD_CONST              78 (171)
           5022 LOAD_CONST              51 (189)
           5025 LOAD_CONST              51 (189)
           5028 LOAD_CONST             181 (180)
           5031 LOAD_CONST             232 (70)
           5034 LOAD_CONST             196 (213)
           5037 LOAD_CONST              59 (197)
           5040 LOAD_CONST              31 (51)
           5043 LOAD_CONST             126 (216)
           5046 LOAD_CONST             131 (16)
           5049 LOAD_CONST             203 (30)
           5052 LOAD_CONST             165 (62)
           5055 LOAD_CONST             142 (199)
           5058 LOAD_CONST             118 (95)
           5061 LOAD_CONST              73 (72)
           5064 LOAD_CONST             128 (7)
           5067 LOAD_CONST             141 (87)
           5070 LOAD_CONST             225 (116)
           5073 LOAD_CONST             141 (87)
           5076 LOAD_CONST             109 (50)
           5079 LOAD_CONST             235 (147)
           5082 LOAD_CONST              11 (194)
           5085 LOAD_CONST             239 (231)
           5088 LOAD_CONST              35 (4)
           5091 LOAD_CONST             102 (15)
           5094 LOAD_CONST             141 (87)
           5097 LOAD_CONST             228 (148)
           5100 LOAD_CONST             114 (192)
           5103 LOAD_CONST             229 (235)
           5106 LOAD_CONST              48 (118)
           5109 LOAD_CONST             190 (170)
           5112 LOAD_CONST             127 (164)
           5115 LOAD_CONST             113 (63)
           5118 LOAD_CONST             180 (61)
           5121 LOAD_CONST             181 (180)
           5124 LOAD_CONST             220 (3)
           5127 LOAD_CONST             208 (88)
           5130 LOAD_CONST             140 (187)
           5133 LOAD_CONST              79 (27)
           5136 LOAD_CONST             110 (214)
           5139 LOAD_CONST              30 (31)
           5142 LOAD_CONST              59 (197)
           5145 LOAD_CONST             137 (240)
           5148 LOAD_CONST              89 (165)
           5151 LOAD_CONST              92 (248)
           5154 LOAD_CONST             224 (129)
           5157 LOAD_CONST             112 (100)
           5160 LOAD_CONST             250 (144)
           5163 LOAD_CONST             136 (52)
           5166 LOAD_CONST              71 (242)
           5169 LOAD_CONST             238 (41)
           5172 LOAD_CONST             207 (162)
           5175 LOAD_CONST             156 (232)
           5178 LOAD_CONST             242 (155)
           5181 LOAD_CONST             122 (124)
           5184 LOAD_CONST             197 (221)
           5187 LOAD_CONST              84 (202)
           5190 LOAD_CONST             193 (66)
           5193 LOAD_CONST             254 (1)
           5196 LOAD_CONST              41 (114)
           5199 LOAD_CONST              13 (86)
           5202 LOAD_CONST             181 (180)
           5205 LOAD_CONST             116 (84)
           5208 LOAD_CONST              20 (45)
           5211 LOAD_CONST             143 (175)
           5214 LOAD_CONST             195 (101)
           5217 LOAD_CONST              40 (223)
           5220 LOAD_CONST             211 (83)
           5223 LOAD_CONST              33 (161)
           5226 LOAD_CONST               4 (122)
           5229 LOAD_CONST             212 (225)
           5232 LOAD_CONST              19 (198)
           5235 LOAD_CONST             232 (70)
           5238 LOAD_CONST             242 (155)
           5241 LOAD_CONST              85 (76)
           5244 LOAD_CONST             247 (183)
           5247 LOAD_CONST              69 (138)
           5250 LOAD_CONST             153 (146)
           5253 LOAD_CONST             150 (238)
           5256 LOAD_CONST             240 (21)
           5259 LOAD_CONST             243 (81)
           5262 LOAD_CONST             108 (185)
           5265 LOAD_CONST             228 (148)
           5268 LOAD_CONST             164 (143)
           5271 LOAD_CONST             256 (217)
           5274 LOAD_CONST             154 (252)
           5277 LOAD_CONST             191 (67)
           5280 LOAD_CONST             216 (140)
           5283 LOAD_CONST             253 (236)
           5286 LOAD_CONST             116 (84)
           5289 LOAD_CONST             232 (70)
           5292 LOAD_CONST             212 (225)
           5295 LOAD_CONST              29 (104)
           5298 LOAD_CONST             179 (184)
           5301 LOAD_CONST              13 (86)
           5304 LOAD_CONST             163 (40)
           5307 LOAD_CONST             232 (70)
           5310 LOAD_CONST             205 (133)
           5313 LOAD_CONST             220 (3)
           5316 LOAD_CONST              59 (197)
           5319 LOAD_CONST             171 (58)
           5322 LOAD_CONST              59 (197)
           5325 LOAD_CONST             180 (61)
           5328 LOAD_CONST              17 (75)
           5331 LOAD_CONST             186 (142)
           5334 LOAD_CONST             144 (209)
           5337 LOAD_CONST             187 (243)
           5340 LOAD_CONST              22 (99)
           5343 LOAD_CONST              11 (194)
           5346 LOAD_CONST             232 (70)
           5349 LOAD_CONST             145 (82)
           5352 LOAD_CONST             160 (18)
           5355 LOAD_CONST              42 (193)
           5358 LOAD_CONST             134 (244)
           5361 LOAD_CONST             210 (25)
           5364 LOAD_CONST             116 (84)
           5367 LOAD_CONST             139 (163)
           5370 LOAD_CONST             134 (244)
           5373 LOAD_CONST             140 (187)
           5376 LOAD_CONST             163 (40)
           5379 LOAD_CONST              16 (168)
           5382 LOAD_CONST              81 (188)
           5385 LOAD_CONST              84 (202)
           5388 LOAD_CONST             192 (241)
           5391 LOAD_CONST             234 (130)
           5394 LOAD_CONST              85 (76)
           5397 LOAD_CONST             209 (119)
           5400 LOAD_CONST             209 (119)
           5403 LOAD_CONST              15 (169)
           5406 BUILD_LIST            1790
           5409 STORE_NAME               3 (loads)

  3        5412 LOAD_CONST             258 ('')
           5415 STORE_NAME               4 (string)

  4        5418 LOAD_CONST              26 (0)
           5421 LOAD_CONST              26 (0)
           5424 BUILD_TUPLE              2
           5427 UNPACK_SEQUENCE          2
           5430 STORE_NAME               5 (binary)
           5433 STORE_NAME               6 (dis)

  5        5436 LOAD_CONST             181 (180)
           5439 LOAD_CONST             102 (15)
           5442 LOAD_CONST             191 (67)
           5445 LOAD_CONST             232 (70)
           5448 LOAD_CONST             151 (152)
           5451 LOAD_CONST              73 (72)
           5454 LOAD_CONST              16 (168)
           5457 LOAD_CONST             232 (70)
           5460 LOAD_CONST             170 (22)
           5463 LOAD_CONST             251 (128)
           5466 LOAD_CONST              96 (78)
           5469 LOAD_CONST             131 (16)
           5472 LOAD_CONST             115 (77)
           5475 LOAD_CONST             119 (154)
           5478 LOAD_CONST             242 (155)
           5481 LOAD_CONST              93 (126)
           5484 LOAD_CONST             229 (235)
           5487 LOAD_CONST              71 (242)
           5490 LOAD_CONST             203 (30)
           5493 LOAD_CONST             124 (229)
           5496 LOAD_CONST             120 (145)
           5499 LOAD_CONST             214 (38)
           5502 LOAD_CONST             190 (170)
           5505 LOAD_CONST              14 (127)
           5508 LOAD_CONST              98 (89)
           5511 LOAD_CONST              24 (60)
           5514 LOAD_CONST             245 (56)
           5517 LOAD_CONST             169 (46)
           5520 LOAD_CONST              13 (86)
           5523 LOAD_CONST             230 (94)
           5526 LOAD_CONST             238 (41)
           5529 LOAD_CONST             209 (119)
           5532 LOAD_CONST             189 (97)
           5535 LOAD_CONST              61 (150)
           5538 LOAD_CONST             230 (94)
           5541 LOAD_CONST              80 (48)
           5544 LOAD_CONST             185 (44)
           5547 LOAD_CONST             243 (81)
           5550 LOAD_CONST             213 (32)
           5553 LOAD_CONST              59 (197)
           5556 LOAD_CONST             208 (88)
           5559 LOAD_CONST             229 (235)
           5562 LOAD_CONST             198 (246)
           5565 LOAD_CONST             100 (64)
           5568 LOAD_CONST             198 (246)
           5571 LOAD_CONST              69 (138)
           5574 LOAD_CONST              96 (78)
           5577 LOAD_CONST             255 (137)
           5580 LOAD_CONST             165 (62)
           5583 LOAD_CONST             257 (250)
           5586 LOAD_CONST              77 (107)
           5589 LOAD_CONST              31 (51)
           5592 LOAD_CONST             145 (82)
           5595 LOAD_CONST             173 (8)
           5598 LOAD_CONST             205 (133)
           5601 LOAD_CONST             236 (220)
           5604 LOAD_CONST             154 (252)
           5607 LOAD_CONST             173 (8)
           5610 LOAD_CONST             244 (136)
           5613 LOAD_CONST             115 (77)
           5616 LOAD_CONST             162 (132)
           5619 LOAD_CONST             254 (1)
           5622 LOAD_CONST              58 (68)
           5625 LOAD_CONST             162 (132)
           5628 LOAD_CONST              24 (60)
           5631 LOAD_CONST              21 (160)
           5634 LOAD_CONST             132 (196)
           5637 LOAD_CONST             182 (227)
           5640 LOAD_CONST             251 (128)
           5643 LOAD_CONST             201 (226)
           5646 LOAD_CONST               9 (115)
           5649 LOAD_CONST              91 (211)
           5652 LOAD_CONST             216 (140)
           5655 LOAD_CONST             220 (3)
           5658 LOAD_CONST             197 (221)
           5661 LOAD_CONST              25 (29)
           5664 LOAD_CONST             129 (207)
           5667 LOAD_CONST             224 (129)
           5670 LOAD_CONST              12 (120)
           5673 LOAD_CONST             114 (192)
           5676 LOAD_CONST             100 (64)
           5679 LOAD_CONST             223 (106)
           5682 LOAD_CONST             178 (13)
           5685 LOAD_CONST              73 (72)
           5688 LOAD_CONST             194 (141)
           5691 LOAD_CONST              66 (54)
           5694 LOAD_CONST             145 (82)
           5697 LOAD_CONST             169 (46)
           5700 LOAD_CONST              69 (138)
           5703 LOAD_CONST             153 (146)
           5706 LOAD_CONST              10 (35)
           5709 LOAD_CONST             163 (40)
           5712 LOAD_CONST              41 (114)
           5715 LOAD_CONST             194 (141)
           5718 LOAD_CONST             199 (222)
           5721 LOAD_CONST              41 (114)
           5724 LOAD_CONST             172 (111)
           5727 LOAD_CONST             164 (143)
           5730 LOAD_CONST             251 (128)
           5733 LOAD_CONST              12 (120)
           5736 LOAD_CONST             142 (199)
           5739 LOAD_CONST             204 (215)
           5742 LOAD_CONST             138 (91)
           5745 LOAD_CONST             228 (148)
           5748 LOAD_CONST              93 (126)
           5751 LOAD_CONST             220 (3)
           5754 LOAD_CONST             146 (228)
           5757 LOAD_CONST              51 (189)
           5760 LOAD_CONST             213 (32)
           5763 LOAD_CONST              85 (76)
           5766 LOAD_CONST              50 (73)
           5769 LOAD_CONST             124 (229)
           5772 LOAD_CONST              97 (158)
           5775 LOAD_CONST               4 (122)
           5778 LOAD_CONST               6 (219)
           5781 LOAD_CONST              77 (107)
           5784 LOAD_CONST             167 (85)
           5787 LOAD_CONST             218 (172)
           5790 LOAD_CONST             180 (61)
           5793 LOAD_CONST             209 (119)
           5796 LOAD_CONST             169 (46)
           5799 LOAD_CONST               9 (115)
           5802 LOAD_CONST             146 (228)
           5805 LOAD_CONST             114 (192)
           5808 LOAD_CONST             115 (77)
           5811 LOAD_CONST             222 (103)
           5814 LOAD_CONST             128 (7)
           5817 LOAD_CONST             129 (207)
           5820 LOAD_CONST             167 (85)
           5823 LOAD_CONST              21 (160)
           5826 LOAD_CONST             254 (1)
           5829 LOAD_CONST             119 (154)
           5832 LOAD_CONST             158 (139)
           5835 LOAD_CONST             186 (142)
           5838 LOAD_CONST               2 (131)
           5841 LOAD_CONST              76 (2)
           5844 LOAD_CONST             239 (231)
           5847 LOAD_CONST              71 (242)
           5850 LOAD_CONST             128 (7)
           5853 LOAD_CONST               8 (157)
           5856 LOAD_CONST              13 (86)
           5859 LOAD_CONST              83 (90)
           5862 LOAD_CONST             178 (13)
           5865 LOAD_CONST             162 (132)
           5868 LOAD_CONST             223 (106)
           5871 LOAD_CONST               4 (122)
           5874 LOAD_CONST             104 (65)
           5877 LOAD_CONST             175 (96)
           5880 LOAD_CONST              90 (71)
           5883 LOAD_CONST             172 (111)
           5886 LOAD_CONST             128 (7)
           5889 LOAD_CONST             207 (162)
           5892 LOAD_CONST             224 (129)
           5895 LOAD_CONST             139 (163)
           5898 LOAD_CONST             193 (66)
           5901 LOAD_CONST              17 (75)
           5904 LOAD_CONST             135 (98)
           5907 LOAD_CONST             133 (210)
           5910 LOAD_CONST             215 (247)
           5913 LOAD_CONST             236 (220)
           5916 LOAD_CONST              31 (51)
           5919 LOAD_CONST             229 (235)
           5922 LOAD_CONST             239 (231)
           5925 LOAD_CONST               4 (122)
           5928 LOAD_CONST             173 (8)
           5931 LOAD_CONST              86 (245)
           5934 LOAD_CONST             104 (65)
           5937 LOAD_CONST              77 (107)
           5940 LOAD_CONST             255 (137)
           5943 LOAD_CONST             230 (94)
           5946 LOAD_CONST             153 (146)
           5949 LOAD_CONST             238 (41)
           5952 LOAD_CONST             198 (246)
           5955 LOAD_CONST              19 (198)
           5958 LOAD_CONST             248 (224)
           5961 LOAD_CONST             114 (192)
           5964 LOAD_CONST             114 (192)
           5967 LOAD_CONST             213 (32)
           5970 LOAD_CONST              33 (161)
           5973 LOAD_CONST             254 (1)
           5976 LOAD_CONST             181 (180)
           5979 LOAD_CONST             203 (30)
           5982 LOAD_CONST             212 (225)
           5985 LOAD_CONST             197 (221)
           5988 LOAD_CONST             139 (163)
           5991 LOAD_CONST             180 (61)
           5994 LOAD_CONST              97 (158)
           5997 LOAD_CONST             186 (142)
           6000 LOAD_CONST             166 (113)
           6003 LOAD_CONST             136 (52)
           6006 LOAD_CONST              66 (54)
           6009 LOAD_CONST             195 (101)
           6012 LOAD_CONST             224 (129)
           6015 LOAD_CONST             222 (103)
           6018 LOAD_CONST             174 (28)
           6021 LOAD_CONST              61 (150)
           6024 LOAD_CONST              32 (80)
           6027 LOAD_CONST              82 (230)
           6030 LOAD_CONST             175 (96)
           6033 LOAD_CONST             248 (224)
           6036 LOAD_CONST              96 (78)
           6039 LOAD_CONST             110 (214)
           6042 LOAD_CONST             149 (135)
           6045 LOAD_CONST              14 (127)
           6048 LOAD_CONST             197 (221)
           6051 LOAD_CONST              12 (120)
           6054 LOAD_CONST             192 (241)
           6057 LOAD_CONST              75 (191)
           6060 LOAD_CONST             110 (214)
           6063 LOAD_CONST              16 (168)
           6066 LOAD_CONST             123 (33)
           6069 LOAD_CONST             112 (100)
           6072 LOAD_CONST             252 (251)
           6075 LOAD_CONST             207 (162)
           6078 LOAD_CONST             179 (184)
           6081 LOAD_CONST             150 (238)
           6084 LOAD_CONST             183 (205)
           6087 LOAD_CONST              48 (118)
           6090 LOAD_CONST             129 (207)
           6093 LOAD_CONST              40 (223)
           6096 LOAD_CONST             240 (21)
           6099 LOAD_CONST               5 (5)
           6102 LOAD_CONST             256 (217)
           6105 LOAD_CONST              47 (42)
           6108 LOAD_CONST             231 (254)
           6111 LOAD_CONST             131 (16)
           6114 LOAD_CONST              27 (24)
           6117 LOAD_CONST              76 (2)
           6120 LOAD_CONST              51 (189)
           6123 LOAD_CONST              90 (71)
           6126 LOAD_CONST             137 (240)
           6129 LOAD_CONST             178 (13)
           6132 LOAD_CONST             187 (243)
           6135 LOAD_CONST             226 (10)
           6138 LOAD_CONST             122 (124)
           6141 LOAD_CONST             247 (183)
           6144 LOAD_CONST             146 (228)
           6147 LOAD_CONST              42 (193)
           6150 LOAD_CONST             237 (37)
           6153 LOAD_CONST             162 (132)
           6156 LOAD_CONST              48 (118)
           6159 LOAD_CONST             175 (96)
           6162 LOAD_CONST             214 (38)
           6165 LOAD_CONST             149 (135)
           6168 LOAD_CONST              42 (193)
           6171 LOAD_CONST              83 (90)
           6174 LOAD_CONST              38 (17)
           6177 LOAD_CONST             250 (144)
           6180 LOAD_CONST              57 (178)
           6183 LOAD_CONST             105 (255)
           6186 LOAD_CONST              27 (24)
           6189 LOAD_CONST             229 (235)
           6192 LOAD_CONST             231 (254)
           6195 LOAD_CONST             155 (249)
           6198 LOAD_CONST              53 (201)
           6201 BUILD_LIST             255
           6204 STORE_NAME               7 (byte)

  6        6207 SETUP_LOOP             101 (to 6311)

  7     >> 6210 LOAD_NAME                5 (binary)
           6213 LOAD_NAME                8 (len)
           6216 LOAD_NAME                3 (loads)
           6219 CALL_FUNCTION            1
           6222 COMPARE_OP               5 (>=)
           6225 POP_JUMP_IF_FALSE     6232
           6228 BREAK_LOOP          
           6229 JUMP_FORWARD             0 (to 6232)

  8     >> 6232 LOAD_NAME                6 (dis)
           6235 LOAD_NAME                8 (len)
           6238 LOAD_NAME                7 (byte)
           6241 CALL_FUNCTION            1
           6244 COMPARE_OP               5 (>=)
           6247 POP_JUMP_IF_FALSE     6259
           6250 LOAD_CONST              26 (0)
           6253 STORE_NAME               6 (dis)
           6256 JUMP_FORWARD             0 (to 6259)

  9     >> 6259 LOAD_NAME                4 (string)
           6262 LOAD_NAME                9 (chr)
           6265 LOAD_NAME                3 (loads)
           6268 LOAD_NAME                5 (binary)
           6271 BINARY_SUBSCR       
           6272 LOAD_NAME                7 (byte)
           6275 LOAD_NAME                6 (dis)
           6278 BINARY_SUBSCR       
           6279 BINARY_XOR          
           6280 CALL_FUNCTION            1
           6283 INPLACE_ADD         
           6284 STORE_NAME               4 (string)

 10        6287 LOAD_NAME                5 (binary)
           6290 LOAD_CONST             254 (1)
           6293 INPLACE_ADD         
           6294 STORE_NAME               5 (binary)

 11        6297 LOAD_NAME                6 (dis)
           6300 LOAD_CONST             254 (1)
           6303 INPLACE_ADD         
           6304 STORE_NAME               6 (dis)
           6307 JUMP_ABSOLUTE         6210
           6310 POP_BLOCK           

 12     >> 6311 LOAD_NAME                0 (marshal)
           6314 LOAD_ATTR                3 (loads)
           6317 LOAD_NAME                1 (zlib)
           6320 LOAD_ATTR               10 (decompress)
           6323 LOAD_NAME                2 (base64)
           6326 LOAD_ATTR               11 (b16decode)
           6329 LOAD_NAME                4 (string)
           6332 CALL_FUNCTION            1
           6335 CALL_FUNCTION            1
           6338 CALL_FUNCTION            1
           6341 LOAD_CONST               1 (None)
           6344 DUP_TOP             
           6345 EXEC_STMT           
           6346 LOAD_CONST               1 (None)
           6349 RETURN_VALUE        
