  1           0 LOAD_CONST               0 (-1)
              3 LOAD_CONST               1 (None)
              6 IMPORT_NAME              0 (time)
              9 STORE_NAME               0 (time)
             12 LOAD_CONST               0 (-1)
             15 LOAD_CONST               1 (None)
             18 IMPORT_NAME              1 (sys)
             21 STORE_NAME               1 (sys)
             24 LOAD_CONST               2 ('EzzKun')
             27 LOAD_CONST               3 (<code object EzzKun at 0xb6c7ce78, file "tes.py", line 3>)

  3          30 MAKE_FUNCTION            0
             33 CALL_FUNCTION            0
             36 BUILD_CLASS         
             37 STORE_NAME               2 (EzzKun)
             40 SETUP_EXCEPT            11 (to 54)
             43 LOAD_NAME                2 (EzzKun)
             46 CALL_FUNCTION            0

 14          49 POP_TOP             
             50 POP_BLOCK           
             51 JUMP_FORWARD            17 (to 71)
        >>   54 DUP_TOP             
             55 LOAD_NAME                3 (EOFError)
             58 COMPARE_OP              10 (exception match)
             61 POP_JUMP_IF_FALSE       79
             64 POP_TOP             
             65 POP_TOP             
             66 POP_TOP             
             67 JUMP_FORWARD             1 (to 71)
             70 END_FINALLY         
        >>   71 LOAD_CONST               1 (None)
             74 RETURN_VALUE        
